Workbook
Name Slicer_Category: #N/A
Name Slicer_Gender: #N/A
Name Slicer_Order_Date__Year: #N/A
Name Slicer_Payment_Type: #N/A
Name Slicer_State: #N/A
Name Slicer_Store_ID: #N/A

Sheet Customer_Dim
A1: Customer_ID | B1: Name | C1: Age | D1: Gender | E1: City | F1: State | G1: Country | H1: Loyalty_Level
A2: CUST1000 | B2: sheena bonilla | C2: 55 | D2: Male | E2: Donaldton | F2: North Carolina | G2: USA
A3: CUST1001 | B3: Eugene Nelson | C3: 26 | D3: Female | E3: Phillipsmouth | F3: North Dakota | G3: USA | H3: Platinum
A4: CUST1002 | B4: dr. Benjamin Price | C4: 29 | D4: Female | E4: Kylebury | F4: Alabama | G4: USA | H4: Platinum
A5: CUST1003 | B5: jeremy harris | C5: 59 | D5: Female | E5: Thomastown | F5: Ohio | G5: USA | H5: Bronze
A6: CUST1004 | B6: Caroline Collins | C6: 64 | D6: Female | E6: Nicholasshire | F6: California | G6: USA | H6: Silver
A7: CUST1005 | B7: Christine Vaughn | C7: 24 | D7: Male | E7: East Amandamouth | F7: Oregon | G7: USA | H7: Bronze
A8: CUST1006 | B8: Amber Jackson | C8: 29 | D8: Female | E8: Deborahborough | F8: South Dakota | G8: USA | H8: Platinum
A9: CUST1007 | B9: Daniel Boyd | C9: 29 | D9: Female | E9: West Pamelafurt | F9: West Virginia | G9: USA | H9: Bronze
A10: CUST1008 | B10: Melissa Howard | C10: 53 | D10: Female | E10: Maynardton | F10: New Hampshire | G10: USA | H10: Gold
A11: CUST1009 | B11: Ms. Maria Leach | C11: 64 | D11: Male | E11: Melissashire | F11: Pennsylvania | G11: USA | H11: Platinum
A12: CUST1010 | B12: Dominic Page | C12: 53 | D12: Male | E12: Port Michaelburgh | F12: Pennsylvania | G12: USA | H12: Bronze
A13: CUST1011 | B13: Brian Lopez | C13: 28 | D13: Female | E13: East Krista | F13: New York | G13: USA | H13: Gold
A14: CUST1012 | B14: Kenneth Lambert | C14: 55 | D14: Female | E14: North Kathryn | F14: Kansas | G14: USA | H14: Platinum
... A19: CUST1017 | B19: Adam Cruz | C19: 60 | D19: Female | E19: Brandonville | F19: Georgia | G19: USA | H19: Platinum
A20: CUST1018 | B20: Rhonda Moss | C20: 43 | D20: Male | E20: South William | F20: Kansas | G20: USA
A21: CUST1019 | B21: Michael Torres | C21: 46 | D21: Female | E21: Gonzalezfort | F21: New Jersey | G21: USA | H21: Platinum
A22: CUST1020 | B22: Bridget Allen | C22: 59 | D22: Male | E22: Lake Shaneburgh | F22: Delaware | G22: USA | H22: Silver
A23: CUST1021 | B23: Jeff Martinez | C23: 36 | D23: Female | E23: Smithburgh | F23: Oklahoma | G23: USA | H23: Gold
A24: CUST1022 | B24: paul fox | C24: 33 | D24: Female | E24: Michaelton | F24: Hawaii | G24: USA | H24: Silver
A25: CUST1023 | B25: Jonathan Steele | C25: 52 | D25: Female | E25: Molinabury | F25: Oregon | G25: USA | H25: Silver
A26: CUST1024 | B26: Heather Collins | C26: 40 | D26: Male | E26: Rogerschester | F26: Idaho | G26: USA | H26: Platinum
A27: CUST1025 | B27: Diana Taylor | C27: 59 | D27: Female | E27: Vasqueztown | F27: California | G27: USA | H27: Bronze
A28: CUST1026 | B28: Amber Carlson | C28: 18 | D28: Female | E28: East Michellemouth | F28: Missouri | G28: USA | H28: Gold
A29: CUST1027 | B29: Leslie Johnson | C29: 31 | D29: Male | E29: Mollyshire | F29: Utah | G29: USA
A30: CUST1028 | B30: Joshua Ryan | C30: 27 | D30: Female | E30: New David | F30: New Jersey | G30: USA | H30: Platinum
A31: CUST1029 | B31: David Arnold | C31: 54 | D31: Female | E31: East Jennifer | F31: California | G31: USA | H31: Silver
A32: CUST1030 | B32: Jessica Acevedo | C32: 64 | D32: Female | E32: Amybury | F32: Pennsylvania | G32: USA | H32: Bronze
A33: CUST1031 | B33: Sarah Vance | C33: 41 | D33: Male | E33: Johnsonville | F33: Oregon | G33: USA | H33: Silver
A34: CUST1032 | B34: Mike Jennings | C34: 48 | D34: Female | E34: Fostermouth | F34: Arizona | G34: USA | H34: Gold
A35: CUST1033 | B35: Robert Jones DDS | C35: 25 | D35: Male | E35: Tristanton | F35: Oklahoma | G35: USA | H35: Platinum
A36: CUST1034 | B36: Christopher Olson | C36: 27 | D36: Female | E36: West Richard | F36: Maryland | G36: USA | H36: Platinum
A37: CUST1035 | B37: Rachel Myers | C37: 52 | D37: Male | E37: Robertberg | F37: North Dakota | G37: USA | H37: Silver
A38: CUST1036 | B38: Thomas Phillips | C38: 20 | D38: Female | E38: Luisfurt | F38: Georgia | G38: USA | H38: Gold
A39: CUST1037 | B39: Christopher Carter | C39: 27 | D39: Female | E39: Brendastad | F39: South Dakota | G39: USA
A40: CUST1038 | B40: Deanna Simpson | C40: 35 | D40: Female | E40: Brownport | F40: North Dakota | G40: USA | H40: Bronze
A41: CUST1039 | B41: Tonya Reynolds | C41: 55 | D41: Female | E41: Darleneton | F41: Michigan | G41: USA | H41: Gold
A42: CUST1040 | B42: Eric Vega | C42: 50 | D42: Male | E42: Williamsonland | F42: Kansas | G42: USA | H42: Gold
A43: CUST1041 | B43: James Gibbs | C43: 21 | D43: Male | E43: Mooneyshire | F43: Alaska | G43: USA | H43: Platinum
A44: CUST1042 | B44: William Martin | C44: 19 | D44: Male | E44: Ryanburgh | F44: Connecticut | G44: USA | H44: Platinum
A45: CUST1043 | B45: Joseph Snow | C45: 45 | D45: Male | E45: South Michaelfort | F45: Vermont | G45: USA | H45: Gold
A46: CUST1044 | B46: Denise Williams | C46: 34 | D46: Male | E46: Christianstad | F46: Hawaii | G46: USA | H46: Bronze
A47: CUST1045 | B47: Jordan Jackson DDS | C47: 54 | D47: Male | E47: North Johnview | F47: Arizona | G47: USA | H47: Gold
A48: CUST1046 | B48: Michelle Garcia DDS | C48: 55 | D48: Female | E48: Perezbury | F48: Ohio | G48: USA | H48: Platinum
A49: CUST1047 | B49: Gina Knight | C49: 54 | D49: Female | E49: Lake Roberthaven | F49: Nevada | G49: USA | H49: Silver
A50: CUST1048 | B50: April Mullins | C50: 54 | D50: Male | E50: Dawsonbury | F50: North Carolina | G50: USA | H50: Platinum
A51: CUST1049 | B51: Timothy Weaver | C51: 45 | D51: Female | E51: New Amy | F51: Ohio | G51: USA | H51: Gold
... A501: C-1499 | B501: Philip Pennington | C501: 27 | D501: Female | E501: East Valerieview | F501: Oregon | G501: USA | H501: Platinum

Sheet Product_Dim
A1: Product_ID | B1: Product_Name | C1: Category | D1: Sub_Category | E1: Brand | F1: Cost | G1: Stock
A2: PROD0 | B2: Brother Laser Printer | C2: Electronics | D2: Computer | E2: Hunt Inc | F2: 112.42 | G2: 416
A3: PROD1 | B3: Men's Graphic T-Shirt | C3: Clothing | D3: Tops | E3: Terry-Moore | F3: 342.56 | G3: 181
A4: PROD2 | B4: Women's Casual Hoodie | C4: Clothing | D4: Outerwear | E4: Sims Inc | G4: 352
A5: P-3 | B5: Men's Running Jacket | C5: Clothing | D5: Outerwear | E5: Pineda Ltd | F5: 364.67 | G5: 452
A6: PROD4 | B6: Women's Yoga Pants | C6: Clothing | D6: Bottoms | E6: Gonzales-Davis | F6: 306.46 | G6: 487
A7: PROD5 | B7: Men's Leather Belt | C7: Clothing | D7: Accessories | E7: Baldwin, Garza and Gonzalez | F7: 261 | G7: 59
A8: PROD6 | B8: Herbal Face Moisturizer | C8: Beauty | D8: Skincare | E8: Davidson PLC | F8: 312.8 | G8: 350
A9: PROD7 | B9: LED Table Lamp | C9: Home | D9: Lighting | E9: Harrell LLC | F9: 218.86 | G9: 170
A10: PROD8 | B10: Wireless Bluetooth Earbuds | C10: Electronics | D10: Audio | E10: Perez-Johnston | F10: 439.07 | G10: 142
A11: PROD9 | B11: Adjustable Dumbbell Set | C11: Sports | D11: Fitness | E11: Hill PLC | F11: 495.72 | G11: 323
A12: PROD10 | B12: Ceramic Kitchen Bowl Set | C12: Home | D12: Kitchen | E12: Hamilton Group | F12: 298.86 | G12: 308
A13: PROD11 | B13: HD Smart TV Stick | C13: Electronics | D13: Accessories | E13: Gibson, Hobbs and Weaver | F13: 449.4
A14: PROD12 | B14: Hair Strengthening Shampoo | C14: Beauty | D14: Haircare | E14: Rice LLC | F14: 115.82 | G14: 460
A15: PROD13 | B15: USB-C Fast Charger | C15: Electronics | D15: Accessories | E15: Dawson-Perkins | F15: 242.23 | G15: 453
A16: PROD14 | B16: Decorative Wall Mirror | C16: Home | D16: Decor | E16: Luna, Anderson and Bowman | F16: 48.01 | G16: 439
A17: PROD15 | B17: 4K Home Projector | C17: Electronics | D17: Appliances | E17: Thomas LLC | F17: 465.34 | G17: 301
A18: P-16 | B18: Beard Grooming Kit | C18: Beauty | D18: Grooming | E18: Erickson-Green | F18: 337.42 | G18: 256
A19: PROD17 | B19: Soccer Training Cone Set | C19: Sports | D19: Accessories | E19: Ford, Murphy and Wilson | F19: 144.53 | G19: 367
A20: PROD18 | B20: Women's Denim Jeans | C20: Clothing | D20: Bottoms | E20: Guerra-Hendrix | G20: 343
A21: PROD19 | B21: Knee Support Brace | C21: Sports | D21: Equipment | E21: May-Reese | F21: 21.34 | G21: 65
A22: PROD20 | B22: Outdoor Sports Water Bottle | C22: Sports | D22: Accessories | E22: Soto-Ellis | F22: 131.51
A23: PROD21 | B23: Multi-Purpose Storage Box | C23: Home | D23: Storage | E23: Gardner-Montes | F23: 123.46 | G23: 76
A24: PROD22 | B24: Carbon Fiber Tennis Racket | C24: Sports | D24: Equipment | E24: Flores, Pineda and Rodriguez | F24: 484.62 | G24: 432
A25: PROD23 | B25: Men's Formal Shirt | C25: Clothing | D25: Tops | E25: Moon, Mora and Santos | G25: 360
A26: PROD24 | B26: Foldable Camping Chair | C26: Sports | D26: Outdoor | E26: Cook Ltd | F26: 166.06 | G26: 340
A27: PROD25 | B27: Women's Scarf Set | C27: Clothing | D27: Accessories | E27: Brown and Sons | F27: 174.02 | G27: 268
A28: PROD26 | B28: Wireless Bluetooth Speaker | C28: Electronics | D28: Audio | E28: Reed-Schmidt | F28: 322.41 | G28: 213
A29: PROD27 | B29: Decorative Floor Vase | C29: Home | D29: Decor | E29: Khan, Jones and Paul | G29: 378
A30: PROD28 | B30: Sports Stopwatch Timer | C30: Sports | D30: Accessories | E30: Burns-Hansen | F30: 38.76 | G30: 137
A31: PROD29 | B31: Fabric Sofa Throw Blanket | C31: Home | D31: Decor | E31: Hoffman Group | F31: 218.48 | G31: 276
A32: PROD30 | B32: Stainless Steel Cutlery Set | C32: Home | D32: Kitchen | E32: Stevens, Fernandez and Martin | F32: 19.52 | G32: 57
A33: PROD31 | B33: Basketball | C33: Sports | D33: Team Sports | E33: Nolan-Snow | F33: 204.39 | G33: 281
A34: PROD32 | B34: Vitamin C Face Serum | C34: Beauty | D34: Skincare | E34: Griffin Ltd | F34: 283.83 | G34: 244
A35: PROD33 | B35: Modern Wall Clock | C35: Home | D35: Decor | E35: Weiss-Watson | F35: 179.77 | G35: 305
A36: PROD34 | B36: Gaming Mechanical Keyboard | C36: Electronics | D36: Computer | E36: Lucero LLC | F36: 419.28 | G36: 86
A37: PROD35 | B37: Bedroom Table Lamp | C37: Home | D37: Lighting | E37: Jones LLC | F37: 382.22 | G37: 329
A38: PROD36 | B38: Women's Summer Dress | C38: Clothing | D38: Tops | E38: Smith-Mills | F38: 223.43 | G38: 154
A39: PROD37 | B39: Men's Casual Sneakers | C39: Clothing | D39: Footwear | E39: Hogan-Lee | F39: 353.47 | G39: 214
A40: PROD38 | B40: Sports Water Hydration Pack | C40: Sports | D40: Outdoor | E40: Sims-Smith | F40: 135.61 | G40: 394
A41: PROD39 | B41: Portable Power Bank | C41: Electronics | D41: Mobile | E41: Cummings and Sons | F41: 326.06 | G41: 301
... A48: PROD46 | B48: Men's Winter Jacket | C48: Clothing | D48: Outerwear | E48: Kelly, Smith and Perez | F48: 167.34 | G48: 296
A49: PROD47 | B49: Makeup Brush Set | C49: Beauty | D49: Makeup | E49: Cook Inc | G49: 431
A50: PROD48 | B50: Car Dashboard Phone Holder | C50: Electronics | D50: Accessories | E50: Byrd, Stewart and Valdez | F50: 177.98 | G50: 103
A51: PROD49 | B51: Men's Roll-On Perfume | C51: Beauty | D51: Fragrance | E51: Sullivan and Sons | F51: 43.29 | G51: 267
A52: PROD50 | B52: Boxing Hand Wraps | C52: Sports | D52: Fitness | E52: Smith-King | F52: 190.29 | G52: 260
A53: PROD51 | B53: HDMI Cable – 2m | C53: Electronics | D53: Accessories | E53: Bautista, Green and Hale | F53: 88.49 | G53: 246
A54: PROD52 | B54: Rugby Ball | C54: Sports | D54: Team Sports | E54: Harris Inc | F54: 212.26 | G54: 82
A55: PROD53 | B55: Men's Track Pants | C55: Clothing | D55: Bottoms | E55: Hamilton, Woods and Walker | F55: 386.56 | G55: 125
A56: PROD54 | B56: Sports Stopwatch Pro | C56: Sports | D56: Accessories | E56: Thompson-French | F56: 434.84 | G56: 185
A57: PROD55 | B57: Ceramic Plant Pot | C57: Home | D57: Decor | E57: Hatfield, Baird and Torres | F57: 81.75
A58: PROD56 | B58: Premium Blanket Throw | C58: Home | D58: Decor | E58: Hernandez, Kennedy and Porter | F58: 461.47 | G58: 190
A59: PROD57 | B59: Foam Roller | C59: Sports | D59: Fitness | E59: Atkinson, Camacho and Oliver | F59: 30.62 | G59: 138
A60: PROD58 | B60: Womens Cotton Scarf | C60: Clothing | D60: Accessories | E60: Shepherd-Gould | F60: 113.83 | G60: 485
A61: PROD59 | B61: Men's Hair Styling Gel | C61: Beauty | D61: Haircare | E61: Cline-Mccarthy | F61: 17.31 | G61: 399
A62: PROD60 | B62: Luxury Perfume Spray | C62: Beauty | D62: Fragrance | E62: Gibson, Green and Lopez | F62: 482.75 | G62: 444
A63: PROD61 | B63: Tennis Ball 3-Pack | C63: Sports | D63: Equipment | E63: Lopez LLC | F63: 103.45 | G63: 465
A64: PROD62 | B64: Laptop Cooling Pad | C64: Electronics | D64: Computer | E64: Murray, Gould and Ware | F64: 86.42 | G64: 222
A65: PROD63 | B65: Organic Sunscreen Lotion | C65: Beauty | D65: Skincare | E65: Anderson-Riley | F65: 266.86 | G65: 458
A66: PROD64 | B66: Matte Lipstick Set | C66: Beauty | D66: Makeup | E66: Zhang Inc | F66: 299.11 | G66: 118
A67: PROD65 | B67: Adjustable Dumbbells 20kg | C67: Sports | D67: Fitness | E67: Montgomery, Benton and Miller | F67: 240.63 | G67: 423
A68: PROD66 | B68: Women's Hair Dryer Brush | C68: Beauty | D68: Haircare | E68: Torres, Spencer and Potter | F68: 340.39 | G68: 177
A69: PROD67 | B69: Smart LED Light Strip | C69: Electronics | D69: Accessories | E69: Flores-Davis | F69: 349.17 | G69: 476
... A84: PROD82 | B84: Fitness Resistance Bands | C84: Sports | D84: Fitness | E84: Reese-Watson | F84: 152.92 | G84: 281
A85: PROD83 | B85: Hydrating Face Cleanser | C85: Beauty | D85: Skincare | E85: Butler Group | G85: 159
A86: PROD84 | B86: Wooden Bookshelf | C86: Home | D86: Furniture | E86: Collins-Stephenson | F86: 388.46 | G86: 208
A87: PROD85 | B87: Women's Beanie Hat | C87: Clothing | D87: Accessories | E87: Richardson-Carrillo | F87: 119.57 | G87: 210
A88: PROD86 | B88: Kitchen Cutting Board | C88: Home | D88: Kitchen | E88: Taylor, Dodson and Johnston | F88: 176.07 | G88: 82
A89: PROD87 | B89: LED Bedside Lamp | C89: Home | D89: Lighting | E89: Aguilar, Horton and Lewis | F89: 371.38 | G89: 220
A90: PROD88 | B90: Sports Wrist Sweatbands | C90: Sports | D90: Accessories | E90: Olsen-Daniels | F90: 131.24 | G90: 232
A91: PROD89 | B91: Face Foundation Kit | C91: Beauty | D91: Makeup | E91: Taylor-Elliott | F91: 183.04 | G91: 457
A92: PROD90 | B92: Gaming Mouse Pad XL | C92: Electronics | D92: Accessories | E92: Sharp, Taylor and Rodriguez | F92: 340.14 | G92: 361
A93: PROD91 | B93: Women's High Heels | C93: Clothing | D93: Footwear | E93: Smith-Charles | F93: 438.25 | G93: 496
A94: PROD92 | B94: Microwave Oven | C94: Home | D94: Appliances | E94: Green, Powell and Palmer | F94: 447.43 | G94: 191
A95: PROD93 | B95: USB-C Laptop Charger | C95: Electronics | D95: Computer | E95: Martin LLC | F95: 377.52 | G95: 485
A96: PROD94 | B96: Vitamin E Body Lotion | C96: Beauty | D96: Skincare | E96: Hoffman-Williams | F96: 358.47 | G96: 213
A97: PROD95 | B97: Sports Stopwatch Basic | C97: Sports | D97: Accessories | E97: Wilson Group | F97: 60.65 | G97: 75
... A101: PROD99 | B101: Stainless Steel Cookware Set | C101: Home | D101: Kitchen | E101: Campbell Ltd | F101: 201.41 | G101: 146

Sheet Sales_Fact
A1: Sales_ID | B1: Order_Date | C1: Customer_ID | D1: Product_ID | E1: Store_ID | F1: Quantity | G1: Unit_Price | H1: Discount | I1: Payment_Type | J1: Total_Amount
A2: SALE0 | B2: 45480 | C2: CUST1409 | D2: PROD0 | E2: STORE3 | F2: 1 | G2: 218.04 | H2: 0.09 | I2: Credit Card | J2: 198.4164
A3: SALE1 | B3: 45285 | C3: CUST1467 | D3: PROD0 | E3: STORE17 | F3: 3 | G3: 104.47 | H3: 0.27 | I3: PayPal | J3: 228.7893
A4: SALE2 | B4: 45446 | C4: CUST1056 | D4: PROD0 | E4: STORE8 | F4: 4 | G4: 914.05 | H4: 0.25 | I4: Credit Card | J4: 2742.15
A5: SALE3 | B5: 45259 | C5: CUST1346 | D5: PROD0 | E5: STORE8 | F5: 1 | G5: 921.51 | H5: 0.16 | I5: COD | J5: 774.0684
A6: SALE4 | B6: 45297 | C6: CUST1493 | D6: PROD0 | E6: STORE5 | F6: 3 | G6: 745.3 | H6: 0.18 | I6: Credit Card | J6: 1833.438
A7: SALE5 | B7: 45499 | C7: CUST1116 | D7: PROD0 | E7: STORE7 | F7: 3 | G7: 147.01 | H7: 0.19 | I7: COD | J7: 357.2343
A8: SALE6 | B8: 45850 | C8: CUST1016 | D8: PROD0 | E8: STORE4 | F8: 2 | G8: 785.31 | H8: 0.15 | I8: PayPal | J8: 1335.027
A9: SALE7 | B9: 45248 | C9: CUST1152 | D9: PROD0 | E9: STORE8 | F9: 4 | G9: 342.39 | H9: 0.23 | I9: PayPal | J9: 1054.5612
A10: SALE8 | B10: 45781 | C10: CUST1187 | D10: PROD0 | E10: STORE5 | G10: 448.25 | H10: 0.07 | I10: PayPal | J10: 1250.6175
A11: SALE9 | B11: 45869 | C11: CUST1464 | D11: PROD0 | E11: STORE0 | F11: 2 | G11: 873.17 | H11: 0.23 | I11: PayPal | J11: 1344.6818
A12: SALE10 | B12: 45335 | C12: CUST1065 | D12: PROD0 | E12: STORE14 | F12: 1 | G12: 278.63 | H12: 0.07 | I12: Credit Card | J12: 259.1259
A13: SALE11 | B13: 45801 | C13: CUST1320 | D13: PROD0 | E13: STORE1 | F13: 4 | G13: 286.92 | H13: 0.17 | I13: Credit Card | J13: 952.5744
A14: SALE12 | B14: 45528 | C14: CUST1237 | D14: PROD0 | E14: STORE4 | F14: 4 | G14: 644.58 | H14: 0.01 | I14: Credit Card | J14: 2552.5368
A15: SALE13 | B15: 45875 | C15: CUST1443 | D15: PROD0 | E15: STORE16 | F15: 2 | G15: 316.9 | H15: 0.3 | I15: PayPal | J15: 443.66
A16: SALE14 | B16: 45829 | C16: CUST1348 | D16: PROD0 | E16: STORE15 | F16: 4 | G16: 403.47 | H16: 0.29 | I16: PayPal | J16: 1145.8548
A17: SALE15 | B17: 45636 | C17: CUST1435 | D17: PROD0 | E17: STORE9 | G17: 871.34 | H17: 0.04 | I17: COD | J17: 2509.4592
A18: SALE16 | B18: 45913 | C18: CUST1276 | D18: PROD1 | E18: STORE19 | F18: 2 | G18: 451.98 | H18: 0.25 | I18: Credit Card | J18: 677.97
A19: SALE17 | B19: 45637 | C19: CUST1079 | D19: PROD1 | E19: STORE4 | F19: 2 | G19: 502.69 | H19: 0.23 | I19: Credit Card | J19: 774.1426
A20: SALE18 | B20: 45517 | C20: CUST1094 | D20: PROD1 | E20: STORE4 | F20: 2 | G20: 559.23 | H20: 0.25 | I20: COD | J20: 838.845
A21: SALE19 | B21: 45369 | C21: CUST1239 | D21: PROD1 | E21: STORE13 | F21: 4 | H21: 0.04 | I21: COD | J21: 1782.4512
A22: SALE20 | B22: 45843 | C22: CUST1144 | D22: PROD1 | E22: STORE17 | F22: 3 | G22: 986.04 | H22: 0.27 | I22: COD | J22: 2159.4276
A23: SALE21 | B23: 45447 | C23: CUST1396 | D23: PROD1 | E23: STORE18 | F23: 1 | G23: 589.56 | H23: 0.22 | I23: Credit Card | J23: 459.8568
A24: SALE22 | B24: 45394 | C24: CUST1476 | D24: PROD1 | E24: STORE10 | F24: 3 | G24: 979.42 | H24: 0.03 | I24: PayPal | J24: 2850.1122
A25: SALE23 | B25: 45466 | C25: CUST1368 | D25: PROD1 | E25: STORE8 | F25: 1 | G25: 719.28 | H25: 0.08 | I25: Credit Card | J25: 661.7376
A26: SALE24 | B26: 45908 | C26: CUST1186 | D26: PROD1 | E26: STORE6 | F26: 3 | G26: 77.6 | H26: 0.07 | I26: Credit Card | J26: 216.504
A27: SALE25 | B27: 45552 | C27: CUST1381 | D27: PROD1 | E27: STORE3 | F27: 4 | G27: 852.71 | H27: 0.14 | I27: PayPal | J27: 2933.3224
A28: SALE26 | B28: 45294 | C28: CUST1213 | D28: PROD1 | E28: STORE8 | F28: 4 | G28: 156.16 | I28: Credit Card | J28: 599.6544
A29: SALE27 | B29: 45710 | C29: CUST1200 | D29: PROD1 | E29: STORE8 | F29: 3 | G29: 815.49 | H29: 0.17 | I29: Credit Card | J29: 2030.5701
A30: SALE28 | B30: 45923 | C30: CUST1148 | D30: PROD1 | E30: STORE2 | F30: 2 | G30: 74.21 | H30: 0.11 | I30: PayPal | J30: 132.0938
A31: SALE29 | B31: 45302 | C31: CUST1348 | D31: PROD1 | E31: STORE3 | G31: 451.67 | H31: 0.15 | I31: Credit Card | J31: 1535.678
A32: SALE30 | B32: 45217 | C32: CUST1028 | D32: PROD1 | E32: STORE19 | F32: 1 | G32: 429.38 | H32: 0.13 | I32: PayPal | J32: 373.5606
A33: SALE31 | B33: 45593 | C33: CUST1412 | D33: PROD10 | E33: STORE12 | F33: 2 | G33: 148.96 | H33: 0.03 | I33: COD | J33: 288.9824
A34: SALE32 | B34: 45597 | C34: CUST1398 | D34: PROD10 | E34: STORE8 | F34: 4 | G34: 313.83 | H34: 0.08 | I34: Credit Card | J34: 1154.8944
A35: SALE33 | B35: 45620 | C35: CUST1453 | D35: PROD10 | E35: STORE6 | F35: 2 | G35: 717.31 | H35: 0.15 | I35: Credit Card | J35: 1219.427
A36: SALE34 | B36: 45215 | C36: CUST1344 | D36: PROD10 | E36: STORE1 | G36: 873.22 | H36: 0.18 | I36: Credit Card | J36: 2148.1212
A37: SALE35 | B37: 45878 | C37: CUST1218 | D37: PROD10 | E37: STORE3 | F37: 4 | G37: 109.36 | H37: 0.19 | I37: COD | J37: 354.3264
A38: SALE36 | B38: 45635 | C38: CUST1086 | D38: PROD10 | E38: STORE7 | F38: 3 | G38: 559.52 | H38: 0.16 | I38: PayPal | J38: 1409.9904
A39: SALE37 | B39: 45329 | C39: CUST1492 | D39: PROD10 | E39: STORE17 | F39: 3 | G39: 121.76 | H39: 0.27 | I39: PayPal | J39: 266.6544
A40: SALE38 | B40: 45378 | C40: CUST1189 | D40: PROD10 | E40: STORE13 | F40: 4 | G40: 735.32 | H40: 0.06 | I40: COD | J40: 2764.8032
A41: SALE39 | B41: 45264 | C41: CUST1431 | D41: PROD10 | E41: STORE3 | F41: 2 | G41: 600.73 | H41: 0.08 | I41: Credit Card | J41: 1105.3432
A42: SALE40 | B42: 45486 | C42: CUST1072 | D42: PROD10 | E42: STORE19 | F42: 2 | G42: 873.86 | H42: 0.07 | I42: COD | J42: 1625.3796
A43: SALE41 | B43: 45241 | C43: CUST1302 | D43: PROD10 | E43: STORE8 | F43: 3 | G43: 342.47 | H43: 0.08 | I43: PayPal | J43: 945.2172
A44: SALE42 | B44: 45649 | C44: CUST1335 | D44: PROD10 | E44: STORE9 | F44: 2 | G44: 915.15 | H44: 0.16 | I44: PayPal | J44: 1537.452
A45: SALE43 | B45: 45677 | C45: CUST1084 | D45: PROD10 | E45: STORE17 | G45: 863.11 | H45: 0.28 | I45: PayPal | J45: 1864.3176
A46: SALE44 | B46: 45538 | C46: CUST1203 | D46: PROD10 | E46: STORE12 | F46: 2 | G46: 209.32 | H46: 0.23 | I46: COD | J46: 322.3528
A47: SALE45 | B47: 45606 | C47: CUST1470 | D47: PROD10 | E47: STORE8 | F47: 4 | G47: 288.6 | H47: 0.09 | I47: PayPal | J47: 1050.504
A48: SALE46 | B48: 45570 | C48: CUST1070 | D48: PROD10 | E48: STORE16 | F48: 1 | G48: 418.69 | H48: 0.06 | I48: PayPal | J48: 393.5686
A49: SALE47 | B49: 45466 | C49: CUST1008 | D49: PROD10 | E49: STORE11 | F49: 1 | G49: 135.78 | H49: 0.14 | I49: PayPal | J49: 116.7708
A50: SALE48 | B50: 45218 | C50: CUST1203 | D50: PROD10 | E50: STORE17 | F50: 1 | G50: 517.13 | H50: 0.28 | I50: Credit Card | J50: 372.3336
A51: SALE49 | B51: 45607 | C51: CUST1420 | D51: PROD10 | E51: STORE16 | F51: 2 | G51: 384.66 | H51: 0.08 | I51: COD | J51: 707.7744
A52: SALE50 | B52: 45291 | C52: CUST1070 | D52: PROD10 | E52: STORE9 | F52: 3 | G52: 83.7 | H52: 0.24 | I52: PayPal | J52: 190.836
A53: SALE51 | B53: 45689 | C53: CUST1142 | D53: PROD10 | E53: STORE7 | F53: 3 | G53: 76.57 | H53: 0.26 | I53: Credit Card | J53: 169.9854
A54: SALE52 | B54: 45894 | C54: CUST1148 | D54: PROD11 | E54: STORE6 | F54: 3 | I54: Credit Card | J54: 486.0633
A55: SALE53 | B55: 45677 | C55: CUST1324 | D55: PROD11 | E55: STORE8 | F55: 1 | G55: 900.35 | H55: 0.13 | I55: COD | J55: 783.3045
A56: SALE54 | B56: 45706 | C56: CUST1095 | D56: PROD11 | E56: STORE10 | F56: 4 | G56: 428.09 | H56: 0.07 | I56: Credit Card | J56: 1592.4948
A57: SALE55 | B57: 45589 | C57: CUST1416 | D57: PROD11 | E57: STORE11 | F57: 2 | G57: 559.71 | H57: 0.3 | I57: COD | J57: 783.594
A58: SALE56 | B58: 45282 | C58: CUST1080 | D58: PROD11 | E58: STORE6 | F58: 2 | G58: 833.7 | H58: 0.06 | I58: PayPal | J58: 1567.356
A59: SALE57 | B59: 45462 | C59: CUST1467 | D59: PROD11 | E59: STORE14 | F59: 2 | G59: 680.16 | H59: 0.28 | I59: Credit Card | J59: 979.4304
A60: SALE58 | B60: 45633 | C60: CUST1404 | D60: PROD11 | E60: STORE7 | F60: 4 | G60: 733.42 | I60: PayPal | J60: 2552.3016
A61: SALE59 | B61: 45257 | C61: CUST1367 | D61: PROD11 | E61: STORE11 | F61: 1 | G61: 996.33 | H61: 0.23 | I61: PayPal | J61: 767.1741
A62: SALE60 | B62: 45854 | C62: CUST1408 | D62: PROD11 | E62: STORE10 | F62: 1 | G62: 198.83 | H62: 0.09 | I62: COD | J62: 180.9353
A63: SALE61 | B63: 45716 | C63: CUST1239 | D63: PROD11 | E63: STORE7 | F63: 1 | G63: 374.92 | H63: 0.18 | I63: PayPal | J63: 307.4344
A64: SALE62 | B64: 45515 | C64: CUST1464 | D64: PROD11 | E64: STORE16 | F64: 1 | G64: 468.94 | H64: 0.12 | I64: Credit Card | J64: 412.6672
A65: SALE63 | B65: 45927 | C65: CUST1126 | D65: PROD11 | E65: STORE12 | F65: 2 | G65: 121.37 | H65: 0.05 | I65: Credit Card | J65: 230.603
A66: SALE64 | B66: 45914 | C66: CUST1255 | D66: PROD11 | E66: STORE10 | F66: 3 | G66: 480.06 | H66: 0.01 | I66: Credit Card
A67: SALE65 | B67: 45290 | C67: CUST1162 | D67: PROD11 | E67: STORE17 | F67: 2 | G67: 856.57 | H67: 0.24 | I67: Credit Card | J67: 1301.9864
A68: SALE66 | B68: 45213 | C68: CUST1269 | D68: PROD11 | E68: STORE2 | F68: 4 | G68: 814.25 | H68: 0.18 | I68: Credit Card | J68: 2670.74
A69: SALE67 | B69: 45255 | C69: CUST1483 | D69: PROD11 | E69: STORE2 | F69: 1 | G69: 989.17 | H69: 0.2 | I69: PayPal | J69: 791.336
A70: SALE68 | B70: 45270 | C70: CUST1372 | D70: PROD11 | E70: STORE10 | F70: 4 | G70: 62.48 | H70: 0.18 | I70: Credit Card | J70: 204.9344
A71: SALE69 | B71: 45897 | C71: CUST1423 | D71: PROD11 | E71: STORE16 | F71: 4 | G71: 561.24 | H71: 0.24 | I71: Credit Card | J71: 1706.1696
A72: SALE70 | B72: 45849 | C72: CUST1058 | D72: PROD11 | E72: STORE5 | F72: 3 | G72: 92.24 | H72: 0.28 | I72: COD
A73: SALE71 | B73: 45889 | C73: CUST1168 | D73: PROD12 | E73: STORE1 | F73: 2 | G73: 668.3 | H73: 0.07 | I73: Credit Card | J73: 1243.038
A74: SALE72 | B74: 45533 | C74: CUST1409 | D74: PROD12 | E74: STORE5 | F74: 1 | G74: 553.82 | H74: 0.09 | I74: Credit Card | J74: 503.9762
A75: SALE73 | B75: 45626 | C75: CUST1037 | D75: PROD12 | E75: STORE11 | F75: 2 | G75: 556.43 | H75: 0.13 | I75: Credit Card | J75: 968.1882
A76: SALE74 | B76: 45942 | C76: CUST1273 | D76: PROD12 | E76: STORE8 | F76: 1 | G76: 184.98 | H76: 0.1 | I76: COD | J76: 166.482
A77: SALE75 | B77: 45500 | C77: CUST1035 | D77: PROD12 | E77: STORE12 | F77: 4 | G77: 700.18 | H77: 0.23 | I77: Credit Card | J77: 2156.5544
A78: SALE76 | B78: 45285 | C78: CUST1019 | D78: PROD12 | E78: STORE10 | F78: 2 | G78: 686.31 | H78: 0.25 | I78: Credit Card | J78: 1029.465
A79: SALE77 | B79: 45800 | C79: CUST1007 | D79: PROD12 | E79: STORE15 | F79: 1 | G79: 687.82 | H79: 0.27 | I79: COD | J79: 502.1086
A80: SALE78 | B80: 45609 | C80: CUST1221 | D80: PROD12 | E80: STORE8 | F80: 2 | G80: 900.55 | H80: 0.16 | I80: Credit Card | J80: 1512.924
A81: SALE79 | B81: 45268 | C81: CUST1115 | D81: PROD12 | E81: STORE2 | F81: 1 | G81: 341.17 | H81: 0.15 | I81: Credit Card | J81: 289.9945
A82: SALE80 | B82: 45885 | C82: CUST1176 | D82: PROD12 | E82: STORE8 | F82: 1 | G82: 442.27 | H82: 0.06 | I82: COD | J82: 415.7338
A83: SALE81 | B83: 45616 | C83: CUST1253 | D83: PROD12 | E83: STORE9 | F83: 1 | G83: 363.73 | H83: 0.25 | I83: PayPal | J83: 272.7975
A84: SALE82 | B84: 45518 | C84: CUST1378 | D84: PROD12 | E84: STORE17 | F84: 2 | G84: 601.33 | H84: 0.16 | I84: PayPal | J84: 1010.2344
A85: SALE83 | B85: 45427 | C85: CUST1403 | D85: PROD12 | E85: STORE18 | F85: 4 | G85: 34.39 | H85: 0.03 | I85: PayPal | J85: 133.4332
A86: SALE84 | B86: 45268 | C86: CUST1423 | D86: PROD12 | E86: STORE17 | F86: 1 | G86: 773.57 | H86: 0.05 | I86: COD
A87: SALE85 | B87: 45282 | C87: CUST1054 | D87: PROD12 | E87: STORE7 | F87: 4 | G87: 127.1 | H87: 0.24 | I87: COD | J87: 386.384
A88: SALE86 | B88: 45545 | C88: CUST1303 | D88: PROD12 | E88: STORE3 | F88: 3 | G88: 899.58 | H88: 0.28 | I88: PayPal | J88: 1943.0928
A89: SALE87 | B89: 45755 | C89: CUST1327 | D89: PROD12 | E89: STORE10 | F89: 3 | G89: 964.39 | H89: 0.04 | I89: Credit Card | J89: 2777.4432
A90: SALE88 | B90: 45588 | C90: CUST1183 | D90: PROD12 | E90: STORE0 | F90: 2 | G90: 217.83 | H90: 0.14 | I90: PayPal | J90: 374.6676
A91: SALE89 | B91: 45848 | C91: CUST1143 | D91: PROD12 | E91: STORE1 | F91: 4 | G91: 187.71 | H91: 0.06 | I91: COD | J91: 705.7896
A92: SALE90 | B92: 45577 | C92: CUST1010 | D92: PROD13 | E92: STORE18 | F92: 2 | G92: 350.12 | H92: 0.12 | I92: COD | J92: 616.2112
A93: SALE91 | B93: 45312 | C93: CUST1406 | D93: PROD13 | E93: STORE1 | F93: 4 | G93: 102.19 | H93: 0.17 | I93: PayPal | J93: 339.2708
A94: SALE92 | B94: 45350 | C94: CUST1007 | D94: PROD13 | E94: STORE4 | F94: 1 | G94: 696.53 | H94: 0.17 | I94: Credit Card | J94: 578.1199
A95: SALE93 | B95: 45657 | C95: CUST1065 | D95: PROD13 | E95: STORE4 | F95: 2 | G95: 327.52 | H95: 0.15 | I95: PayPal | J95: 556.784
A96: SALE94 | B96: 45530 | C96: CUST1298 | D96: PROD13 | E96: STORE19 | F96: 2 | G96: 569.36 | H96: 0.01 | I96: PayPal
A97: SALE95 | B97: 45556 | C97: CUST1321 | D97: PROD13 | E97: STORE6 | F97: 2 | G97: 68.29 | H97: 0.14 | I97: COD | J97: 117.4588
A98: SALE96 | B98: 45523 | C98: CUST1244 | D98: PROD13 | E98: STORE10 | F98: 1 | G98: 842.9 | H98: 0.06 | I98: COD | J98: 792.326
A99: SALE97 | B99: 45587 | C99: CUST1287 | D99: PROD13 | E99: STORE3 | F99: 3 | G99: 751.94 | H99: 0.26 | I99: PayPal | J99: 1669.3068
A100: SALE98 | B100: 45580 | C100: CUST1131 | D100: PROD13 | E100: STORE7 | F100: 4 | G100: 476.28 | H100: 0.17 | I100: Credit Card | J100: 1581.2496
...

Sheet Product_Dim Cleaning
A1: Product_ID | B1: Product_Name | C1: Category | D1: Sub_Category | E1: Brand | F1: Cost | G1: Stock | H1: cost1 | I1: Stock1
A2: PROD0 | B2: Brother Laser Printer | C2: Electronics | D2: Computer | E2: Hunt Inc | F2: 112.42 | G2: 416 | H2: =IF(F2="",AVERAGEIFS($F$2:$F$101,$C$2:$C$101,C2,$D$2:$D$101,D2),F2) -> 112.42 | I2: {=IF(G2="",MEDIAN(IF(($C$2:$C$101=C2)*($D$2:$D$101=D2),$G$2:$G$101)),G2)} -> 416
A3: PROD1 | B3: Men's Graphic T-Shirt | C3: Clothing | D3: Tops | E3: Terry-Moore | F3: 342.56 | G3: 181 | H3: =IF(F3="",AVERAGEIFS($F$2:$F$101,$C$2:$C$101,C3,$D$2:$D$101,D3),F3) -> 342.56 | I3: {=IF(G3="",MEDIAN(IF(($C$2:$C$101=C3)*($D$2:$D$101=D3),$G$2:$G$101)),G3)} -> 181
A4: PROD2 | B4: Women's Casual Hoodie | C4: Clothing | D4: Outerwear | E4: Sims Inc | G4: 352 | H4: =IF(F4="",AVERAGEIFS($F$2:$F$101,$C$2:$C$101,C4,$D$2:$D$101,D4),F4) -> 296.82667 | I4: {=IF(G4="",MEDIAN(IF(($C$2:$C$101=C4)*($D$2:$D$101=D4),$G$2:$G$101)),G4)} -> 352
A5: PROD3 | B5: Men's Running Jacket | C5: Clothing | D5: Outerwear | E5: Pineda Ltd | F5: 364.67 | G5: 452 | H5: =IF(F5="",AVERAGEIFS($F$2:$F$101,$C$2:$C$101,C5,$D$2:$D$101,D5),F5) -> 364.67 | I5: {=IF(G5="",MEDIAN(IF(($C$2:$C$101=C5)*($D$2:$D$101=D5),$G$2:$G$101)),G5)} -> 452
A6: PROD4 | B6: Women's Yoga Pants | C6: Clothing | D6: Bottoms | E6: Gonzales-Davis | F6: 306.46 | G6: 487 | H6: =IF(F6="",AVERAGEIFS($F$2:$F$101,$C$2:$C$101,C6,$D$2:$D$101,D6),F6) -> 306.46 | I6: {=IF(G6="",MEDIAN(IF(($C$2:$C$101=C6)*($D$2:$D$101=D6),$G$2:$G$101)),G6)} -> 487
A7: PROD5 | B7: Men's Leather Belt | C7: Clothing | D7: Accessories | E7: Baldwin, Garza and Gonzalez | F7: 261 | G7: 59 | H7: =IF(F7="",AVERAGEIFS($F$2:$F$101,$C$2:$C$101,C7,$D$2:$D$101,D7),F7) -> 261 | I7: {=IF(G7="",MEDIAN(IF(($C$2:$C$101=C7)*($D$2:$D$101=D7),$G$2:$G$101)),G7)} -> 59
A8: PROD6 | B8: Herbal Face Moisturizer | C8: Beauty | D8: Skincare | E8: Davidson PLC | F8: 312.8 | G8: 350 | H8: =IF(F8="",AVERAGEIFS($F$2:$F$101,$C$2:$C$101,C8,$D$2:$D$101,D8),F8) -> 312.8 | I8: {=IF(G8="",MEDIAN(IF(($C$2:$C$101=C8)*($D$2:$D$101=D8),$G$2:$G$101)),G8)} -> 350
A9: PROD7 | B9: LED Table Lamp | C9: Home | D9: Lighting | E9: Harrell LLC | F9: 218.86 | G9: 170 | H9: =IF(F9="",AVERAGEIFS($F$2:$F$101,$C$2:$C$101,C9,$D$2:$D$101,D9),F9) -> 218.86 | I9: {=IF(G9="",MEDIAN(IF(($C$2:$C$101=C9)*($D$2:$D$101=D9),$G$2:$G$101)),G9)} -> 170
A10: PROD8 | B10: Wireless Bluetooth Earbuds | C10: Electronics | D10: Audio | E10: Perez-Johnston | F10: 439.07 | G10: 142 | H10: =IF(F10="",AVERAGEIFS($F$2:$F$101,$C$2:$C$101,C10,$D$2:$D$101,D10),F10) -> 439.07 | I10: {=IF(G10="",MEDIAN(IF(($C$2:$C$101=C10)*($D$2:$D$101=D10),$G$2:$G$101)),G10)} -> 142
A11: PROD9 | B11: Adjustable Dumbbell Set | C11: Sports | D11: Fitness | E11: Hill PLC | F11: 495.72 | G11: 323 | H11: =IF(F11="",AVERAGEIFS($F$2:$F$101,$C$2:$C$101,C11,$D$2:$D$101,D11),F11) -> 495.72 | I11: {=IF(G11="",MEDIAN(IF(($C$2:$C$101=C11)*($D$2:$D$101=D11),$G$2:$G$101)),G11)} -> 323
A12: PROD10 | B12: Ceramic Kitchen Bowl Set | C12: Home | D12: Kitchen | E12: Hamilton Group | F12: 298.86 | G12: 308 | H12: =IF(F12="",AVERAGEIFS($F$2:$F$101,$C$2:$C$101,C12,$D$2:$D$101,D12),F12) -> 298.86 | I12: {=IF(G12="",MEDIAN(IF(($C$2:$C$101=C12)*($D$2:$D$101=D12),$G$2:$G$101)),G12)} -> 308
A13: PROD11 | B13: HD Smart TV Stick | C13: Electronics | D13: Accessories | E13: Gibson, Hobbs and Weaver | F13: 449.4 | H13: =IF(F13="",AVERAGEIFS($F$2:$F$101,$C$2:$C$101,C13,$D$2:$D$101,D13),F13) -> 449.4 | I13: {=IF(G13="",MEDIAN(IF(($C$2:$C$101=C13)*($D$2:$D$101=D13),$G$2:$G$101)),G13)} -> 361
A14: PROD12 | B14: Hair Strengthening Shampoo | C14: Beauty | D14: Haircare | E14: Rice LLC | F14: 115.82 | G14: 460 | H14: =IF(F14="",AVERAGEIFS($F$2:$F$101,$C$2:$C$101,C14,$D$2:$D$101,D14),F14) -> 115.82 | I14: {=IF(G14="",MEDIAN(IF(($C$2:$C$101=C14)*($D$2:$D$101=D14),$G$2:$G$101)),G14)} -> 460
A15: PROD13 | B15: USB-C Fast Charger | C15: Electronics | D15: Accessories | E15: Dawson-Perkins | F15: 242.23 | G15: 453 | H15: =IF(F15="",AVERAGEIFS($F$2:$F$101,$C$2:$C$101,C15,$D$2:$D$101,D15),F15) -> 242.23 | I15: {=IF(G15="",MEDIAN(IF(($C$2:$C$101=C15)*($D$2:$D$101=D15),$G$2:$G$101)),G15)} -> 453
A16: PROD14 | B16: Decorative Wall Mirror | C16: Home | D16: Decor | E16: Luna, Anderson and Bowman | F16: 48.01 | G16: 439 | H16: =IF(F16="",AVERAGEIFS($F$2:$F$101,$C$2:$C$101,C16,$D$2:$D$101,D16),F16) -> 48.01 | I16: {=IF(G16="",MEDIAN(IF(($C$2:$C$101=C16)*($D$2:$D$101=D16),$G$2:$G$101)),G16)} -> 439
A17: PROD15 | B17: 4K Home Projector | C17: Electronics | D17: Appliances | E17: Thomas LLC | F17: 465.34 | G17: 301 | H17: =IF(F17="",AVERAGEIFS($F$2:$F$101,$C$2:$C$101,C17,$D$2:$D$101,D17),F17) -> 465.34 | I17: {=IF(G17="",MEDIAN(IF(($C$2:$C$101=C17)*($D$2:$D$101=D17),$G$2:$G$101)),G17)} -> 301
A18: PROD16 | B18: Beard Grooming Kit | C18: Beauty | D18: Grooming | E18: Erickson-Green | F18: 337.42 | G18: 256 | H18: =IF(F18="",AVERAGEIFS($F$2:$F$101,$C$2:$C$101,C18,$D$2:$D$101,D18),F18) -> 337.42 | I18: {=IF(G18="",MEDIAN(IF(($C$2:$C$101=C18)*($D$2:$D$101=D18),$G$2:$G$101)),G18)} -> 256
A19: PROD17 | B19: Soccer Training Cone Set | C19: Sports | D19: Accessories | E19: Ford, Murphy and Wilson | F19: 144.53 | G19: 367 | H19: =IF(F19="",AVERAGEIFS($F$2:$F$101,$C$2:$C$101,C19,$D$2:$D$101,D19),F19) -> 144.53 | I19: {=IF(G19="",MEDIAN(IF(($C$2:$C$101=C19)*($D$2:$D$101=D19),$G$2:$G$101)),G19)} -> 367
A20: PROD18 | B20: Women's Denim Jeans | C20: Clothing | D20: Bottoms | E20: Guerra-Hendrix | G20: 343 | H20: =IF(F20="",AVERAGEIFS($F$2:$F$101,$C$2:$C$101,C20,$D$2:$D$101,D20),F20) -> 303.74667 | I20: {=IF(G20="",MEDIAN(IF(($C$2:$C$101=C20)*($D$2:$D$101=D20),$G$2:$G$101)),G20)} -> 343
A21: PROD19 | B21: Knee Support Brace | C21: Sports | D21: Equipment | E21: May-Reese | F21: 21.34 | G21: 65 | H21: =IF(F21="",AVERAGEIFS($F$2:$F$101,$C$2:$C$101,C21,$D$2:$D$101,D21),F21) -> 21.34 | I21: {=IF(G21="",MEDIAN(IF(($C$2:$C$101=C21)*($D$2:$D$101=D21),$G$2:$G$101)),G21)} -> 65
A22: PROD20 | B22: Outdoor Sports Water Bottle | C22: Sports | D22: Accessories | E22: Soto-Ellis | F22: 131.51 | H22: =IF(F22="",AVERAGEIFS($F$2:$F$101,$C$2:$C$101,C22,$D$2:$D$101,D22),F22) -> 131.51 | I22: {=IF(G22="",MEDIAN(IF(($C$2:$C$101=C22)*($D$2:$D$101=D22),$G$2:$G$101)),G22)} -> 161
A23: PROD21 | B23: Multi-Purpose Storage Box | C23: Home | D23: Storage | E23: Gardner-Montes | F23: 123.46 | G23: 76 | H23: =IF(F23="",AVERAGEIFS($F$2:$F$101,$C$2:$C$101,C23,$D$2:$D$101,D23),F23) -> 123.46 | I23: {=IF(G23="",MEDIAN(IF(($C$2:$C$101=C23)*($D$2:$D$101=D23),$G$2:$G$101)),G23)} -> 76
A24: PROD22 | B24: Carbon Fiber Tennis Racket | C24: Sports | D24: Equipment | E24: Flores, Pineda and Rodriguez | F24: 484.62 | G24: 432 | H24: =IF(F24="",AVERAGEIFS($F$2:$F$101,$C$2:$C$101,C24,$D$2:$D$101,D24),F24) -> 484.62 | I24: {=IF(G24="",MEDIAN(IF(($C$2:$C$101=C24)*($D$2:$D$101=D24),$G$2:$G$101)),G24)} -> 432
A25: PROD23 | B25: Men's Formal Shirt | C25: Clothing | D25: Tops | E25: Moon, Mora and Santos | G25: 360 | H25: =IF(F25="",AVERAGEIFS($F$2:$F$101,$C$2:$C$101,C25,$D$2:$D$101,D25),F25) -> 282.995 | I25: {=IF(G25="",MEDIAN(IF(($C$2:$C$101=C25)*($D$2:$D$101=D25),$G$2:$G$101)),G25)} -> 360
A26: PROD24 | B26: Foldable Camping Chair | C26: Sports | D26: Outdoor | E26: Cook Ltd | F26: 166.06 | G26: 340 | H26: =IF(F26="",AVERAGEIFS($F$2:$F$101,$C$2:$C$101,C26,$D$2:$D$101,D26),F26) -> 166.06 | I26: {=IF(G26="",MEDIAN(IF(($C$2:$C$101=C26)*($D$2:$D$101=D26),$G$2:$G$101)),G26)} -> 340
A27: PROD25 | B27: Women's Scarf Set | C27: Clothing | D27: Accessories | E27: Brown and Sons | F27: 174.02 | G27: 268 | H27: =IF(F27="",AVERAGEIFS($F$2:$F$101,$C$2:$C$101,C27,$D$2:$D$101,D27),F27) -> 174.02 | I27: {=IF(G27="",MEDIAN(IF(($C$2:$C$101=C27)*($D$2:$D$101=D27),$G$2:$G$101)),G27)} -> 268
A28: PROD26 | B28: Wireless Bluetooth Speaker | C28: Electronics | D28: Audio | E28: Reed-Schmidt | F28: 322.41 | G28: 213 | H28: =IF(F28="",AVERAGEIFS($F$2:$F$101,$C$2:$C$101,C28,$D$2:$D$101,D28),F28) -> 322.41 | I28: {=IF(G28="",MEDIAN(IF(($C$2:$C$101=C28)*($D$2:$D$101=D28),$G$2:$G$101)),G28)} -> 213
A29: PROD27 | B29: Decorative Floor Vase | C29: Home | D29: Decor | E29: Khan, Jones and Paul | G29: 378 | H29: =IF(F29="",AVERAGEIFS($F$2:$F$101,$C$2:$C$101,C29,$D$2:$D$101,D29),F29) -> 219.12333 | I29: {=IF(G29="",MEDIAN(IF(($C$2:$C$101=C29)*($D$2:$D$101=D29),$G$2:$G$101)),G29)} -> 378
A30: PROD28 | B30: Sports Stopwatch Timer | C30: Sports | D30: Accessories | E30: Burns-Hansen | F30: 38.76 | G30: 137 | H30: =IF(F30="",AVERAGEIFS($F$2:$F$101,$C$2:$C$101,C30,$D$2:$D$101,D30),F30) -> 38.76 | I30: {=IF(G30="",MEDIAN(IF(($C$2:$C$101=C30)*($D$2:$D$101=D30),$G$2:$G$101)),G30)} -> 137
A31: PROD29 | B31: Fabric Sofa Throw Blanket | C31: Home | D31: Decor | E31: Hoffman Group | F31: 218.48 | G31: 276 | H31: =IF(F31="",AVERAGEIFS($F$2:$F$101,$C$2:$C$101,C31,$D$2:$D$101,D31),F31) -> 218.48 | I31: {=IF(G31="",MEDIAN(IF(($C$2:$C$101=C31)*($D$2:$D$101=D31),$G$2:$G$101)),G31)} -> 276
A32: PROD30 | B32: Stainless Steel Cutlery Set | C32: Home | D32: Kitchen | E32: Stevens, Fernandez and Martin | F32: 19.52 | G32: 57 | H32: =IF(F32="",AVERAGEIFS($F$2:$F$101,$C$2:$C$101,C32,$D$2:$D$101,D32),F32) -> 19.52 | I32: {=IF(G32="",MEDIAN(IF(($C$2:$C$101=C32)*($D$2:$D$101=D32),$G$2:$G$101)),G32)} -> 57
A33: PROD31 | B33: Basketball | C33: Sports | D33: Team Sports | E33: Nolan-Snow | F33: 204.39 | G33: 281 | H33: =IF(F33="",AVERAGEIFS($F$2:$F$101,$C$2:$C$101,C33,$D$2:$D$101,D33),F33) -> 204.39 | I33: {=IF(G33="",MEDIAN(IF(($C$2:$C$101=C33)*($D$2:$D$101=D33),$G$2:$G$101)),G33)} -> 281
A34: PROD32 | B34: Vitamin C Face Serum | C34: Beauty | D34: Skincare | E34: Griffin Ltd | F34: 283.83 | G34: 244 | H34: =IF(F34="",AVERAGEIFS($F$2:$F$101,$C$2:$C$101,C34,$D$2:$D$101,D34),F34) -> 283.83 | I34: {=IF(G34="",MEDIAN(IF(($C$2:$C$101=C34)*($D$2:$D$101=D34),$G$2:$G$101)),G34)} -> 244
A35: PROD33 | B35: Modern Wall Clock | C35: Home | D35: Decor | E35: Weiss-Watson | F35: 179.77 | G35: 305 | H35: =IF(F35="",AVERAGEIFS($F$2:$F$101,$C$2:$C$101,C35,$D$2:$D$101,D35),F35) -> 179.77 | I35: {=IF(G35="",MEDIAN(IF(($C$2:$C$101=C35)*($D$2:$D$101=D35),$G$2:$G$101)),G35)} -> 305
A36: PROD34 | B36: Gaming Mechanical Keyboard | C36: Electronics | D36: Computer | E36: Lucero LLC | F36: 419.28 | G36: 86 | H36: =IF(F36="",AVERAGEIFS($F$2:$F$101,$C$2:$C$101,C36,$D$2:$D$101,D36),F36) -> 419.28 | I36: {=IF(G36="",MEDIAN(IF(($C$2:$C$101=C36)*($D$2:$D$101=D36),$G$2:$G$101)),G36)} -> 86
A37: PROD35 | B37: Bedroom Table Lamp | C37: Home | D37: Lighting | E37: Jones LLC | F37: 382.22 | G37: 329 | H37: =IF(F37="",AVERAGEIFS($F$2:$F$101,$C$2:$C$101,C37,$D$2:$D$101,D37),F37) -> 382.22 | I37: {=IF(G37="",MEDIAN(IF(($C$2:$C$101=C37)*($D$2:$D$101=D37),$G$2:$G$101)),G37)} -> 329
A38: PROD36 | B38: Women's Summer Dress | C38: Clothing | D38: Tops | E38: Smith-Mills | F38: 223.43 | G38: 154 | H38: =IF(F38="",AVERAGEIFS($F$2:$F$101,$C$2:$C$101,C38,$D$2:$D$101,D38),F38) -> 223.43 | I38: {=IF(G38="",MEDIAN(IF(($C$2:$C$101=C38)*($D$2:$D$101=D38),$G$2:$G$101)),G38)} -> 154
A39: PROD37 | B39: Men's Casual Sneakers | C39: Clothing | D39: Footwear | E39: Hogan-Lee | F39: 353.47 | G39: 214 | H39: =IF(F39="",AVERAGEIFS($F$2:$F$101,$C$2:$C$101,C39,$D$2:$D$101,D39),F39) -> 353.47 | I39: {=IF(G39="",MEDIAN(IF(($C$2:$C$101=C39)*($D$2:$D$101=D39),$G$2:$G$101)),G39)} -> 214
A40: PROD38 | B40: Sports Water Hydration Pack | C40: Sports | D40: Outdoor | E40: Sims-Smith | F40: 135.61 | G40: 394 | H40: =IF(F40="",AVERAGEIFS($F$2:$F$101,$C$2:$C$101,C40,$D$2:$D$101,D40),F40) -> 135.61 | I40: {=IF(G40="",MEDIAN(IF(($C$2:$C$101=C40)*($D$2:$D$101=D40),$G$2:$G$101)),G40)} -> 394
A41: PROD39 | B41: Portable Power Bank | C41: Electronics | D41: Mobile | E41: Cummings and Sons | F41: 326.06 | G41: 301 | H41: =IF(F41="",AVERAGEIFS($F$2:$F$101,$C$2:$C$101,C41,$D$2:$D$101,D41),F41) -> 326.06 | I41: {=IF(G41="",MEDIAN(IF(($C$2:$C$101=C41)*($D$2:$D$101=D41),$G$2:$G$101)),G41)} -> 301
... A48: PROD46 | B48: Men's Winter Jacket | C48: Clothing | D48: Outerwear | E48: Kelly, Smith and Perez | F48: 167.34 | G48: 296 | H48: =IF(F48="",AVERAGEIFS($F$2:$F$101,$C$2:$C$101,C48,$D$2:$D$101,D48),F48) -> 167.34 | I48: {=IF(G48="",MEDIAN(IF(($C$2:$C$101=C48)*($D$2:$D$101=D48),$G$2:$G$101)),G48)} -> 296
A49: PROD47 | B49: Makeup Brush Set | C49: Beauty | D49: Makeup | E49: Cook Inc | G49: 431 | H49: =IF(F49="",AVERAGEIFS($F$2:$F$101,$C$2:$C$101,C49,$D$2:$D$101,D49),F49) -> 241.075 | I49: {=IF(G49="",MEDIAN(IF(($C$2:$C$101=C49)*($D$2:$D$101=D49),$G$2:$G$101)),G49)} -> 431
A50: PROD48 | B50: Car Dashboard Phone Holder | C50: Electronics | D50: Accessories | E50: Byrd, Stewart and Valdez | F50: 177.98 | G50: 103 | H50: =IF(F50="",AVERAGEIFS($F$2:$F$101,$C$2:$C$101,C50,$D$2:$D$101,D50),F50) -> 177.98 | I50: {=IF(G50="",MEDIAN(IF(($C$2:$C$101=C50)*($D$2:$D$101=D50),$G$2:$G$101)),G50)} -> 103
A51: PROD49 | B51: Men's Roll-On Perfume | C51: Beauty | D51: Fragrance | E51: Sullivan and Sons | F51: 43.29 | G51: 267 | H51: =IF(F51="",AVERAGEIFS($F$2:$F$101,$C$2:$C$101,C51,$D$2:$D$101,D51),F51) -> 43.29 | I51: {=IF(G51="",MEDIAN(IF(($C$2:$C$101=C51)*($D$2:$D$101=D51),$G$2:$G$101)),G51)} -> 267
A52: PROD50 | B52: Boxing Hand Wraps | C52: Sports | D52: Fitness | E52: Smith-King | F52: 190.29 | G52: 260 | H52: =IF(F52="",AVERAGEIFS($F$2:$F$101,$C$2:$C$101,C52,$D$2:$D$101,D52),F52) -> 190.29 | I52: {=IF(G52="",MEDIAN(IF(($C$2:$C$101=C52)*($D$2:$D$101=D52),$G$2:$G$101)),G52)} -> 260
A53: PROD51 | B53: HDMI Cable – 2m | C53: Electronics | D53: Accessories | E53: Bautista, Green and Hale | F53: 88.49 | G53: 246 | H53: =IF(F53="",AVERAGEIFS($F$2:$F$101,$C$2:$C$101,C53,$D$2:$D$101,D53),F53) -> 88.49 | I53: {=IF(G53="",MEDIAN(IF(($C$2:$C$101=C53)*($D$2:$D$101=D53),$G$2:$G$101)),G53)} -> 246
A54: PROD52 | B54: Rugby Ball | C54: Sports | D54: Team Sports | E54: Harris Inc | F54: 212.26 | G54: 82 | H54: =IF(F54="",AVERAGEIFS($F$2:$F$101,$C$2:$C$101,C54,$D$2:$D$101,D54),F54) -> 212.26 | I54: {=IF(G54="",MEDIAN(IF(($C$2:$C$101=C54)*($D$2:$D$101=D54),$G$2:$G$101)),G54)} -> 82
A55: PROD53 | B55: Men's Track Pants | C55: Clothing | D55: Bottoms | E55: Hamilton, Woods and Walker | F55: 386.56 | G55: 125 | H55: =IF(F55="",AVERAGEIFS($F$2:$F$101,$C$2:$C$101,C55,$D$2:$D$101,D55),F55) -> 386.56 | I55: {=IF(G55="",MEDIAN(IF(($C$2:$C$101=C55)*($D$2:$D$101=D55),$G$2:$G$101)),G55)} -> 125
A56: PROD54 | B56: Sports Stopwatch Pro | C56: Sports | D56: Accessories | E56: Thompson-French | F56: 434.84 | G56: 185 | H56: =IF(F56="",AVERAGEIFS($F$2:$F$101,$C$2:$C$101,C56,$D$2:$D$101,D56),F56) -> 434.84 | I56: {=IF(G56="",MEDIAN(IF(($C$2:$C$101=C56)*($D$2:$D$101=D56),$G$2:$G$101)),G56)} -> 185
A57: PROD55 | B57: Ceramic Plant Pot | C57: Home | D57: Decor | E57: Hatfield, Baird and Torres | F57: 81.75 | H57: =IF(F57="",AVERAGEIFS($F$2:$F$101,$C$2:$C$101,C57,$D$2:$D$101,D57),F57) -> 81.75 | I57: {=IF(G57="",MEDIAN(IF(($C$2:$C$101=C57)*($D$2:$D$101=D57),$G$2:$G$101)),G57)} -> 305
A58: PROD56 | B58: Premium Blanket Throw | C58: Home | D58: Decor | E58: Hernandez, Kennedy and Porter | F58: 461.47 | G58: 190 | H58: =IF(F58="",AVERAGEIFS($F$2:$F$101,$C$2:$C$101,C58,$D$2:$D$101,D58),F58) -> 461.47 | I58: {=IF(G58="",MEDIAN(IF(($C$2:$C$101=C58)*($D$2:$D$101=D58),$G$2:$G$101)),G58)} -> 190
A59: PROD57 | B59: Foam Roller | C59: Sports | D59: Fitness | E59: Atkinson, Camacho and Oliver | F59: 30.62 | G59: 138 | H59: =IF(F59="",AVERAGEIFS($F$2:$F$101,$C$2:$C$101,C59,$D$2:$D$101,D59),F59) -> 30.62 | I59: {=IF(G59="",MEDIAN(IF(($C$2:$C$101=C59)*($D$2:$D$101=D59),$G$2:$G$101)),G59)} -> 138
A60: PROD58 | B60: Womens Cotton Scarf | C60: Clothing | D60: Accessories | E60: Shepherd-Gould | F60: 113.83 | G60: 485 | H60: =IF(F60="",AVERAGEIFS($F$2:$F$101,$C$2:$C$101,C60,$D$2:$D$101,D60),F60) -> 113.83 | I60: {=IF(G60="",MEDIAN(IF(($C$2:$C$101=C60)*($D$2:$D$101=D60),$G$2:$G$101)),G60)} -> 485
A61: PROD59 | B61: Men's Hair Styling Gel | C61: Beauty | D61: Haircare | E61: Cline-Mccarthy | F61: 17.31 | G61: 399 | H61: =IF(F61="",AVERAGEIFS($F$2:$F$101,$C$2:$C$101,C61,$D$2:$D$101,D61),F61) -> 17.31 | I61: {=IF(G61="",MEDIAN(IF(($C$2:$C$101=C61)*($D$2:$D$101=D61),$G$2:$G$101)),G61)} -> 399
A62: PROD60 | B62: Luxury Perfume Spray | C62: Beauty | D62: Fragrance | E62: Gibson, Green and Lopez | F62: 482.75 | G62: 444 | H62: =IF(F62="",AVERAGEIFS($F$2:$F$101,$C$2:$C$101,C62,$D$2:$D$101,D62),F62) -> 482.75 | I62: {=IF(G62="",MEDIAN(IF(($C$2:$C$101=C62)*($D$2:$D$101=D62),$G$2:$G$101)),G62)} -> 444
A63: PROD61 | B63: Tennis Ball 3-Pack | C63: Sports | D63: Equipment | E63: Lopez LLC | F63: 103.45 | G63: 465 | H63: =IF(F63="",AVERAGEIFS($F$2:$F$101,$C$2:$C$101,C63,$D$2:$D$101,D63),F63) -> 103.45 | I63: {=IF(G63="",MEDIAN(IF(($C$2:$C$101=C63)*($D$2:$D$101=D63),$G$2:$G$101)),G63)} -> 465
A64: PROD62 | B64: Laptop Cooling Pad | C64: Electronics | D64: Computer | E64: Murray, Gould and Ware | F64: 86.42 | G64: 222 | H64: =IF(F64="",AVERAGEIFS($F$2:$F$101,$C$2:$C$101,C64,$D$2:$D$101,D64),F64) -> 86.42 | I64: {=IF(G64="",MEDIAN(IF(($C$2:$C$101=C64)*($D$2:$D$101=D64),$G$2:$G$101)),G64)} -> 222
A65: PROD63 | B65: Organic Sunscreen Lotion | C65: Beauty | D65: Skincare | E65: Anderson-Riley | F65: 266.86 | G65: 458 | H65: =IF(F65="",AVERAGEIFS($F$2:$F$101,$C$2:$C$101,C65,$D$2:$D$101,D65),F65) -> 266.86 | I65: {=IF(G65="",MEDIAN(IF(($C$2:$C$101=C65)*($D$2:$D$101=D65),$G$2:$G$101)),G65)} -> 458
A66: PROD64 | B66: Matte Lipstick Set | C66: Beauty | D66: Makeup | E66: Zhang Inc | F66: 299.11 | G66: 118 | H66: =IF(F66="",AVERAGEIFS($F$2:$F$101,$C$2:$C$101,C66,$D$2:$D$101,D66),F66) -> 299.11 | I66: {=IF(G66="",MEDIAN(IF(($C$2:$C$101=C66)*($D$2:$D$101=D66),$G$2:$G$101)),G66)} -> 118
A67: PROD65 | B67: Adjustable Dumbbells 20kg | C67: Sports | D67: Fitness | E67: Montgomery, Benton and Miller | F67: 240.63 | G67: 423 | H67: =IF(F67="",AVERAGEIFS($F$2:$F$101,$C$2:$C$101,C67,$D$2:$D$101,D67),F67) -> 240.63 | I67: {=IF(G67="",MEDIAN(IF(($C$2:$C$101=C67)*($D$2:$D$101=D67),$G$2:$G$101)),G67)} -> 423
A68: PROD66 | B68: Women's Hair Dryer Brush | C68: Beauty | D68: Haircare | E68: Torres, Spencer and Potter | F68: 340.39 | G68: 177 | H68: =IF(F68="",AVERAGEIFS($F$2:$F$101,$C$2:$C$101,C68,$D$2:$D$101,D68),F68) -> 340.39 | I68: {=IF(G68="",MEDIAN(IF(($C$2:$C$101=C68)*($D$2:$D$101=D68),$G$2:$G$101)),G68)} -> 177
A69: PROD67 | B69: Smart LED Light Strip | C69: Electronics | D69: Accessories | E69: Flores-Davis | F69: 349.17 | G69: 476 | H69: =IF(F69="",AVERAGEIFS($F$2:$F$101,$C$2:$C$101,C69,$D$2:$D$101,D69),F69) -> 349.17 | I69: {=IF(G69="",MEDIAN(IF(($C$2:$C$101=C69)*($D$2:$D$101=D69),$G$2:$G$101)),G69)} -> 476
... A84: PROD82 | B84: Fitness Resistance Bands | C84: Sports | D84: Fitness | E84: Reese-Watson | F84: 152.92 | G84: 281 | H84: =IF(F84="",AVERAGEIFS($F$2:$F$101,$C$2:$C$101,C84,$D$2:$D$101,D84),F84) -> 152.92 | I84: {=IF(G84="",MEDIAN(IF(($C$2:$C$101=C84)*($D$2:$D$101=D84),$G$2:$G$101)),G84)} -> 281
A85: PROD83 | B85: Hydrating Face Cleanser | C85: Beauty | D85: Skincare | E85: Butler Group | G85: 159 | H85: =IF(F85="",AVERAGEIFS($F$2:$F$101,$C$2:$C$101,C85,$D$2:$D$101,D85),F85) -> 305.49 | I85: {=IF(G85="",MEDIAN(IF(($C$2:$C$101=C85)*($D$2:$D$101=D85),$G$2:$G$101)),G85)} -> 159
A86: PROD84 | B86: Wooden Bookshelf | C86: Home | D86: Furniture | E86: Collins-Stephenson | F86: 388.46 | G86: 208 | H86: =IF(F86="",AVERAGEIFS($F$2:$F$101,$C$2:$C$101,C86,$D$2:$D$101,D86),F86) -> 388.46 | I86: {=IF(G86="",MEDIAN(IF(($C$2:$C$101=C86)*($D$2:$D$101=D86),$G$2:$G$101)),G86)} -> 208
A87: PROD85 | B87: Women's Beanie Hat | C87: Clothing | D87: Accessories | E87: Richardson-Carrillo | F87: 119.57 | G87: 210 | H87: =IF(F87="",AVERAGEIFS($F$2:$F$101,$C$2:$C$101,C87,$D$2:$D$101,D87),F87) -> 119.57 | I87: {=IF(G87="",MEDIAN(IF(($C$2:$C$101=C87)*($D$2:$D$101=D87),$G$2:$G$101)),G87)} -> 210
A88: PROD86 | B88: Kitchen Cutting Board | C88: Home | D88: Kitchen | E88: Taylor, Dodson and Johnston | F88: 176.07 | G88: 82 | H88: =IF(F88="",AVERAGEIFS($F$2:$F$101,$C$2:$C$101,C88,$D$2:$D$101,D88),F88) -> 176.07 | I88: {=IF(G88="",MEDIAN(IF(($C$2:$C$101=C88)*($D$2:$D$101=D88),$G$2:$G$101)),G88)} -> 82
A89: PROD87 | B89: LED Bedside Lamp | C89: Home | D89: Lighting | E89: Aguilar, Horton and Lewis | F89: 371.38 | G89: 220 | H89: =IF(F89="",AVERAGEIFS($F$2:$F$101,$C$2:$C$101,C89,$D$2:$D$101,D89),F89) -> 371.38 | I89: {=IF(G89="",MEDIAN(IF(($C$2:$C$101=C89)*($D$2:$D$101=D89),$G$2:$G$101)),G89)} -> 220
A90: PROD88 | B90: Sports Wrist Sweatbands | C90: Sports | D90: Accessories | E90: Olsen-Daniels | F90: 131.24 | G90: 232 | H90: =IF(F90="",AVERAGEIFS($F$2:$F$101,$C$2:$C$101,C90,$D$2:$D$101,D90),F90) -> 131.24 | I90: {=IF(G90="",MEDIAN(IF(($C$2:$C$101=C90)*($D$2:$D$101=D90),$G$2:$G$101)),G90)} -> 232
A91: PROD89 | B91: Face Foundation Kit | C91: Beauty | D91: Makeup | E91: Taylor-Elliott | F91: 183.04 | G91: 457 | H91: =IF(F91="",AVERAGEIFS($F$2:$F$101,$C$2:$C$101,C91,$D$2:$D$101,D91),F91) -> 183.04 | I91: {=IF(G91="",MEDIAN(IF(($C$2:$C$101=C91)*($D$2:$D$101=D91),$G$2:$G$101)),G91)} -> 457
A92: PROD90 | B92: Gaming Mouse Pad XL | C92: Electronics | D92: Accessories | E92: Sharp, Taylor and Rodriguez | F92: 340.14 | G92: 361 | H92: =IF(F92="",AVERAGEIFS($F$2:$F$101,$C$2:$C$101,C92,$D$2:$D$101,D92),F92) -> 340.14 | I92: {=IF(G92="",MEDIAN(IF(($C$2:$C$101=C92)*($D$2:$D$101=D92),$G$2:$G$101)),G92)} -> 361
A93: PROD91 | B93: Women's High Heels | C93: Clothing | D93: Footwear | E93: Smith-Charles | F93: 438.25 | G93: 496 | H93: =IF(F93="",AVERAGEIFS($F$2:$F$101,$C$2:$C$101,C93,$D$2:$D$101,D93),F93) -> 438.25 | I93: {=IF(G93="",MEDIAN(IF(($C$2:$C$101=C93)*($D$2:$D$101=D93),$G$2:$G$101)),G93)} -> 496
A94: PROD92 | B94: Microwave Oven | C94: Home | D94: Appliances | E94: Green, Powell and Palmer | F94: 447.43 | G94: 191 | H94: =IF(F94="",AVERAGEIFS($F$2:$F$101,$C$2:$C$101,C94,$D$2:$D$101,D94),F94) -> 447.43 | I94: {=IF(G94="",MEDIAN(IF(($C$2:$C$101=C94)*($D$2:$D$101=D94),$G$2:$G$101)),G94)} -> 191
A95: PROD93 | B95: USB-C Laptop Charger | C95: Electronics | D95: Computer | E95: Martin LLC | F95: 377.52 | G95: 485 | H95: =IF(F95="",AVERAGEIFS($F$2:$F$101,$C$2:$C$101,C95,$D$2:$D$101,D95),F95) -> 377.52 | I95: {=IF(G95="",MEDIAN(IF(($C$2:$C$101=C95)*($D$2:$D$101=D95),$G$2:$G$101)),G95)} -> 485
A96: PROD94 | B96: Vitamin E Body Lotion | C96: Beauty | D96: Skincare | E96: Hoffman-Williams | F96: 358.47 | G96: 213 | H96: =IF(F96="",AVERAGEIFS($F$2:$F$101,$C$2:$C$101,C96,$D$2:$D$101,D96),F96) -> 358.47 | I96: {=IF(G96="",MEDIAN(IF(($C$2:$C$101=C96)*($D$2:$D$101=D96),$G$2:$G$101)),G96)} -> 213
A97: PROD95 | B97: Sports Stopwatch Basic | C97: Sports | D97: Accessories | E97: Wilson Group | F97: 60.65 | G97: 75 | H97: =IF(F97="",AVERAGEIFS($F$2:$F$101,$C$2:$C$101,C97,$D$2:$D$101,D97),F97) -> 60.65 | I97: {=IF(G97="",MEDIAN(IF(($C$2:$C$101=C97)*($D$2:$D$101=D97),$G$2:$G$101)),G97)} -> 75
... A101: PROD99 | B101: Stainless Steel Cookware Set | C101: Home | D101: Kitchen | E101: Campbell Ltd | F101: 201.41 | G101: 146 | H101: =IF(F101="",AVERAGEIFS($F$2:$F$101,$C$2:$C$101,C101,$D$2:$D$101,D101),F101) -> 201.41 | I101: {=IF(G101="",MEDIAN(IF(($C$2:$C$101=C101)*($D$2:$D$101=D101),$G$2:$G$101)),G101)} -> 146

Sheet Sales_Fact Cleaning
A1: Sales_ID | B1: Order_Date | C1: Customer_ID | D1: Product_ID | E1: Store_ID | F1: Quantity | G1: Unit_Price | H1: Discount | I1: Payment_Type | J1: Total_Amount | K1: Quantity2 | L1: Unit_Price2 | M1: Discount3 | N1: Total_Amount2
A2: SALE0 | B2: 45480 | C2: CUST1409 | D2: PROD0 | E2: STORE3 | F2: 1 | G2: 218.04 | H2: 0.09 | I2: Credit Card | J2: 198.4164 | K2: =IF(F2="",N2/(G2*(1-H2)),F2) -> 1 | L2: =IF(G2="",Table8[[#This Row],[Total_Amount2]]/(Table8[[#This Row],[Quantity]]*(1-Table8[[#This Row],[Discount]])),G2) -> 218.04 | M2: =IF(H2="",1-(Table8[[#This Row],[Total_Amount2]]/(Table8[[#This Row],[Quantity]]*Table8[[#This Row],[Unit_Price]])),H2) -> 0.09 | N2: =IF(J2="",F2*G2*(1-H2),J2) -> 198.4164
A3: SALE1 | B3: 45285 | C3: CUST1467 | D3: PROD0 | E3: STORE17 | F3: 3 | G3: 104.47 | H3: 0.27 | I3: PayPal | J3: 228.7893 | K3: =IF(F3="",N3/(G3*(1-H3)),F3) -> 3 | L3: =IF(G3="",Table8[[#This Row],[Total_Amount2]]/(Table8[[#This Row],[Quantity]]*(1-Table8[[#This Row],[Discount]])),G3) -> 104.47 | M3: =IF(H3="",1-(Table8[[#This Row],[Total_Amount2]]/(Table8[[#This Row],[Quantity]]*Table8[[#This Row],[Unit_Price]])),H3) -> 0.27 | N3: =IF(J3="",F3*G3*(1-H3),J3) -> 228.7893
A4: SALE2 | B4: 45446 | C4: CUST1056 | D4: PROD0 | E4: STORE8 | F4: 4 | G4: 914.05 | H4: 0.25 | I4: Credit Card | J4: 2742.15 | K4: =IF(F4="",N4/(G4*(1-H4)),F4) -> 4 | L4: =IF(G4="",Table8[[#This Row],[Total_Amount2]]/(Table8[[#This Row],[Quantity]]*(1-Table8[[#This Row],[Discount]])),G4) -> 914.05 | M4: =IF(H4="",1-(Table8[[#This Row],[Total_Amount2]]/(Table8[[#This Row],[Quantity]]*Table8[[#This Row],[Unit_Price]])),H4) -> 0.25 | N4: =IF(J4="",F4*G4*(1-H4),J4) -> 2742.15
A5: SALE3 | B5: 45259 | C5: CUST1346 | D5: PROD0 | E5: STORE8 | F5: 1 | G5: 921.51 | H5: 0.16 | I5: COD | J5: 774.0684 | K5: =IF(F5="",N5/(G5*(1-H5)),F5) -> 1 | L5: =IF(G5="",Table8[[#This Row],[Total_Amount2]]/(Table8[[#This Row],[Quantity]]*(1-Table8[[#This Row],[Discount]])),G5) -> 921.51 | M5: =IF(H5="",1-(Table8[[#This Row],[Total_Amount2]]/(Table8[[#This Row],[Quantity]]*Table8[[#This Row],[Unit_Price]])),H5) -> 0.16 | N5: =IF(J5="",F5*G5*(1-H5),J5) -> 774.0684
A6: SALE4 | B6: 45297 | C6: CUST1493 | D6: PROD0 | E6: STORE5 | F6: 3 | G6: 745.3 | H6: 0.18 | I6: Credit Card | J6: 1833.438 | K6: =IF(F6="",N6/(G6*(1-H6)),F6) -> 3 | L6: =IF(G6="",Table8[[#This Row],[Total_Amount2]]/(Table8[[#This Row],[Quantity]]*(1-Table8[[#This Row],[Discount]])),G6) -> 745.3 | M6: =IF(H6="",1-(Table8[[#This Row],[Total_Amount2]]/(Table8[[#This Row],[Quantity]]*Table8[[#This Row],[Unit_Price]])),H6) -> 0.18 | N6: =IF(J6="",F6*G6*(1-H6),J6) -> 1833.438
A7: SALE5 | B7: 45499 | C7: CUST1116 | D7: PROD0 | E7: STORE7 | F7: 3 | G7: 147.01 | H7: 0.19 | I7: COD | J7: 357.2343 | K7: =IF(F7="",N7/(G7*(1-H7)),F7) -> 3 | L7: =IF(G7="",Table8[[#This Row],[Total_Amount2]]/(Table8[[#This Row],[Quantity]]*(1-Table8[[#This Row],[Discount]])),G7) -> 147.01 | M7: =IF(H7="",1-(Table8[[#This Row],[Total_Amount2]]/(Table8[[#This Row],[Quantity]]*Table8[[#This Row],[Unit_Price]])),H7) -> 0.19 | N7: =IF(J7="",F7*G7*(1-H7),J7) -> 357.2343
A8: SALE6 | B8: 45850 | C8: CUST1016 | D8: PROD0 | E8: STORE4 | F8: 2 | G8: 785.31 | H8: 0.15 | I8: PayPal | J8: 1335.027 | K8: =IF(F8="",N8/(G8*(1-H8)),F8) -> 2 | L8: =IF(G8="",Table8[[#This Row],[Total_Amount2]]/(Table8[[#This Row],[Quantity]]*(1-Table8[[#This Row],[Discount]])),G8) -> 785.31 | M8: =IF(H8="",1-(Table8[[#This Row],[Total_Amount2]]/(Table8[[#This Row],[Quantity]]*Table8[[#This Row],[Unit_Price]])),H8) -> 0.15 | N8: =IF(J8="",F8*G8*(1-H8),J8) -> 1335.027
A9: SALE7 | B9: 45248 | C9: CUST1152 | D9: PROD0 | E9: STORE8 | F9: 4 | G9: 342.39 | H9: 0.23 | I9: PayPal | J9: 1054.5612 | K9: =IF(F9="",N9/(G9*(1-H9)),F9) -> 4 | L9: =IF(G9="",Table8[[#This Row],[Total_Amount2]]/(Table8[[#This Row],[Quantity]]*(1-Table8[[#This Row],[Discount]])),G9) -> 342.39 | M9: =IF(H9="",1-(Table8[[#This Row],[Total_Amount2]]/(Table8[[#This Row],[Quantity]]*Table8[[#This Row],[Unit_Price]])),H9) -> 0.23 | N9: =IF(J9="",F9*G9*(1-H9),J9) -> 1054.5612
A10: SALE8 | B10: 45781 | C10: CUST1187 | D10: PROD0 | E10: STORE5 | G10: 448.25 | H10: 0.07 | I10: PayPal | J10: 1250.6175 | K10: =IF(F10="",N10/(G10*(1-H10)),F10) -> 3 | L10: =IF(G10="",Table8[[#This Row],[Total_Amount2]]/(Table8[[#This Row],[Quantity]]*(1-Table8[[#This Row],[Discount]])),G10) -> 448.25 | M10: =IF(H10="",1-(Table8[[#This Row],[Total_Amount2]]/(Table8[[#This Row],[Quantity]]*Table8[[#This Row],[Unit_Price]])),H10) -> 0.07 | N10: =IF(J10="",F10*G10*(1-H10),J10) -> 1250.6175
A11: SALE9 | B11: 45869 | C11: CUST1464 | D11: PROD0 | E11: STORE0 | F11: 2 | G11: 873.17 | H11: 0.23 | I11: PayPal | J11: 1344.6818 | K11: =IF(F11="",N11/(G11*(1-H11)),F11) -> 2 | L11: =IF(G11="",Table8[[#This Row],[Total_Amount2]]/(Table8[[#This Row],[Quantity]]*(1-Table8[[#This Row],[Discount]])),G11) -> 873.17 | M11: =IF(H11="",1-(Table8[[#This Row],[Total_Amount2]]/(Table8[[#This Row],[Quantity]]*Table8[[#This Row],[Unit_Price]])),H11) -> 0.23 | N11: =IF(J11="",F11*G11*(1-H11),J11) -> 1344.6818
A12: SALE10 | B12: 45335 | C12: CUST1065 | D12: PROD0 | E12: STORE14 | F12: 1 | G12: 278.63 | H12: 0.07 | I12: Credit Card | J12: 259.1259 | K12: =IF(F12="",N12/(G12*(1-H12)),F12) -> 1 | L12: =IF(G12="",Table8[[#This Row],[Total_Amount2]]/(Table8[[#This Row],[Quantity]]*(1-Table8[[#This Row],[Discount]])),G12) -> 278.63 | M12: =IF(H12="",1-(Table8[[#This Row],[Total_Amount2]]/(Table8[[#This Row],[Quantity]]*Table8[[#This Row],[Unit_Price]])),H12) -> 0.07 | N12: =IF(J12="",F12*G12*(1-H12),J12) -> 259.1259
A13: SALE11 | B13: 45801 | C13: CUST1320 | D13: PROD0 | E13: STORE1 | F13: 4 | G13: 286.92 | H13: 0.17 | I13: Credit Card | J13: 952.5744 | K13: =IF(F13="",N13/(G13*(1-H13)),F13) -> 4 | L13: =IF(G13="",Table8[[#This Row],[Total_Amount2]]/(Table8[[#This Row],[Quantity]]*(1-Table8[[#This Row],[Discount]])),G13) -> 286.92 | M13: =IF(H13="",1-(Table8[[#This Row],[Total_Amount2]]/(Table8[[#This Row],[Quantity]]*Table8[[#This Row],[Unit_Price]])),H13) -> 0.17 | N13: =IF(J13="",F13*G13*(1-H13),J13) -> 952.5744
A14: SALE12 | B14: 45528 | C14: CUST1237 | D14: PROD0 | E14: STORE4 | F14: 4 | G14: 644.58 | H14: 0.01 | I14: Credit Card | J14: 2552.5368 | K14: =IF(F14="",N14/(G14*(1-H14)),F14) -> 4 | L14: =IF(G14="",Table8[[#This Row],[Total_Amount2]]/(Table8[[#This Row],[Quantity]]*(1-Table8[[#This Row],[Discount]])),G14) -> 644.58 | M14: =IF(H14="",1-(Table8[[#This Row],[Total_Amount2]]/(Table8[[#This Row],[Quantity]]*Table8[[#This Row],[Unit_Price]])),H14) -> 0.01 | N14: =IF(J14="",F14*G14*(1-H14),J14) -> 2552.5368
A15: SALE13 | B15: 45875 | C15: CUST1443 | D15: PROD0 | E15: STORE16 | F15: 2 | G15: 316.9 | H15: 0.3 | I15: PayPal | J15: 443.66 | K15: =IF(F15="",N15/(G15*(1-H15)),F15) -> 2 | L15: =IF(G15="",Table8[[#This Row],[Total_Amount2]]/(Table8[[#This Row],[Quantity]]*(1-Table8[[#This Row],[Discount]])),G15) -> 316.9 | M15: =IF(H15="",1-(Table8[[#This Row],[Total_Amount2]]/(Table8[[#This Row],[Quantity]]*Table8[[#This Row],[Unit_Price]])),H15) -> 0.3 | N15: =IF(J15="",F15*G15*(1-H15),J15) -> 443.66
A16: SALE14 | B16: 45829 | C16: CUST1348 | D16: PROD0 | E16: STORE15 | F16: 4 | G16: 403.47 | H16: 0.29 | I16: PayPal | J16: 1145.8548 | K16: =IF(F16="",N16/(G16*(1-H16)),F16) -> 4 | L16: =IF(G16="",Table8[[#This Row],[Total_Amount2]]/(Table8[[#This Row],[Quantity]]*(1-Table8[[#This Row],[Discount]])),G16) -> 403.47 | M16: =IF(H16="",1-(Table8[[#This Row],[Total_Amount2]]/(Table8[[#This Row],[Quantity]]*Table8[[#This Row],[Unit_Price]])),H16) -> 0.29 | N16: =IF(J16="",F16*G16*(1-H16),J16) -> 1145.8548
A17: SALE15 | B17: 45636 | C17: CUST1435 | D17: PROD0 | E17: STORE9 | G17: 871.34 | H17: 0.04 | I17: COD | J17: 2509.4592 | K17: =IF(F17="",N17/(G17*(1-H17)),F17) -> 3 | L17: =IF(G17="",Table8[[#This Row],[Total_Amount2]]/(Table8[[#This Row],[Quantity]]*(1-Table8[[#This Row],[Discount]])),G17) -> 871.34 | M17: =IF(H17="",1-(Table8[[#This Row],[Total_Amount2]]/(Table8[[#This Row],[Quantity]]*Table8[[#This Row],[Unit_Price]])),H17) -> 0.04 | N17: =IF(J17="",F17*G17*(1-H17),J17) -> 2509.4592
A18: SALE16 | B18: 45913 | C18: CUST1276 | D18: PROD1 | E18: STORE19 | F18: 2 | G18: 451.98 | H18: 0.25 | I18: Credit Card | J18: 677.97 | K18: =IF(F18="",N18/(G18*(1-H18)),F18) -> 2 | L18: =IF(G18="",Table8[[#This Row],[Total_Amount2]]/(Table8[[#This Row],[Quantity]]*(1-Table8[[#This Row],[Discount]])),G18) -> 451.98 | M18: =IF(H18="",1-(Table8[[#This Row],[Total_Amount2]]/(Table8[[#This Row],[Quantity]]*Table8[[#This Row],[Unit_Price]])),H18) -> 0.25 | N18: =IF(J18="",F18*G18*(1-H18),J18) -> 677.97
A19: SALE17 | B19: 45637 | C19: CUST1079 | D19: PROD1 | E19: STORE4 | F19: 2 | G19: 502.69 | H19: 0.23 | I19: Credit Card | J19: 774.1426 | K19: =IF(F19="",N19/(G19*(1-H19)),F19) -> 2 | L19: =IF(G19="",Table8[[#This Row],[Total_Amount2]]/(Table8[[#This Row],[Quantity]]*(1-Table8[[#This Row],[Discount]])),G19) -> 502.69 | M19: =IF(H19="",1-(Table8[[#This Row],[Total_Amount2]]/(Table8[[#This Row],[Quantity]]*Table8[[#This Row],[Unit_Price]])),H19) -> 0.23 | N19: =IF(J19="",F19*G19*(1-H19),J19) -> 774.1426
A20: SALE18 | B20: 45517 | C20: CUST1094 | D20: PROD1 | E20: STORE4 | F20: 2 | G20: 559.23 | H20: 0.25 | I20: COD | J20: 838.845 | K20: =IF(F20="",N20/(G20*(1-H20)),F20) -> 2 | L20: =IF(G20="",Table8[[#This Row],[Total_Amount2]]/(Table8[[#This Row],[Quantity]]*(1-Table8[[#This Row],[Discount]])),G20) -> 559.23 | M20: =IF(H20="",1-(Table8[[#This Row],[Total_Amount2]]/(Table8[[#This Row],[Quantity]]*Table8[[#This Row],[Unit_Price]])),H20) -> 0.25 | N20: =IF(J20="",F20*G20*(1-H20),J20) -> 838.845
A21: SALE19 | B21: 45369 | C21: CUST1239 | D21: PROD1 | E21: STORE13 | F21: 4 | H21: 0.04 | I21: COD | J21: 1782.4512 | K21: =IF(F21="",N21/(G21*(1-H21)),F21) -> 4 | L21: =IF(G21="",Table8[[#This Row],[Total_Amount2]]/(Table8[[#This Row],[Quantity]]*(1-Table8[[#This Row],[Discount]])),G21) -> 464.18 | M21: =IF(H21="",1-(Table8[[#This Row],[Total_Amount2]]/(Table8[[#This Row],[Quantity]]*Table8[[#This Row],[Unit_Price]])),H21) -> 0.04 | N21: =IF(J21="",F21*G21*(1-H21),J21) -> 1782.4512
A22: SALE20 | B22: 45843 | C22: CUST1144 | D22: PROD1 | E22: STORE17 | F22: 3 | G22: 986.04 | H22: 0.27 | I22: COD | J22: 2159.4276 | K22: =IF(F22="",N22/(G22*(1-H22)),F22) -> 3 | L22: =IF(G22="",Table8[[#This Row],[Total_Amount2]]/(Table8[[#This Row],[Quantity]]*(1-Table8[[#This Row],[Discount]])),G22) -> 986.04 | M22: =IF(H22="",1-(Table8[[#This Row],[Total_Amount2]]/(Table8[[#This Row],[Quantity]]*Table8[[#This Row],[Unit_Price]])),H22) -> 0.27 | N22: =IF(J22="",F22*G22*(1-H22),J22) -> 2159.4276
A23: SALE21 | B23: 45447 | C23: CUST1396 | D23: PROD1 | E23: STORE18 | F23: 1 | G23: 589.56 | H23: 0.22 | I23: Credit Card | J23: 459.8568 | K23: =IF(F23="",N23/(G23*(1-H23)),F23) -> 1 | L23: =IF(G23="",Table8[[#This Row],[Total_Amount2]]/(Table8[[#This Row],[Quantity]]*(1-Table8[[#This Row],[Discount]])),G23) -> 589.56 | M23: =IF(H23="",1-(Table8[[#This Row],[Total_Amount2]]/(Table8[[#This Row],[Quantity]]*Table8[[#This Row],[Unit_Price]])),H23) -> 0.22 | N23: =IF(J23="",F23*G23*(1-H23),J23) -> 459.8568
A24: SALE22 | B24: 45394 | C24: CUST1476 | D24: PROD1 | E24: STORE10 | F24: 3 | G24: 979.42 | H24: 0.03 | I24: PayPal | J24: 2850.1122 | K24: =IF(F24="",N24/(G24*(1-H24)),F24) -> 3 | L24: =IF(G24="",Table8[[#This Row],[Total_Amount2]]/(Table8[[#This Row],[Quantity]]*(1-Table8[[#This Row],[Discount]])),G24) -> 979.42 | M24: =IF(H24="",1-(Table8[[#This Row],[Total_Amount2]]/(Table8[[#This Row],[Quantity]]*Table8[[#This Row],[Unit_Price]])),H24) -> 0.03 | N24: =IF(J24="",F24*G24*(1-H24),J24) -> 2850.1122
A25: SALE23 | B25: 45466 | C25: CUST1368 | D25: PROD1 | E25: STORE8 | F25: 1 | G25: 719.28 | H25: 0.08 | I25: Credit Card | J25: 661.7376 | K25: =IF(F25="",N25/(G25*(1-H25)),F25) -> 1 | L25: =IF(G25="",Table8[[#This Row],[Total_Amount2]]/(Table8[[#This Row],[Quantity]]*(1-Table8[[#This Row],[Discount]])),G25) -> 719.28 | M25: =IF(H25="",1-(Table8[[#This Row],[Total_Amount2]]/(Table8[[#This Row],[Quantity]]*Table8[[#This Row],[Unit_Price]])),H25) -> 0.08 | N25: =IF(J25="",F25*G25*(1-H25),J25) -> 661.7376
A26: SALE24 | B26: 45908 | C26: CUST1186 | D26: PROD1 | E26: STORE6 | F26: 3 | G26: 77.6 | H26: 0.07 | I26: Credit Card | J26: 216.504 | K26: =IF(F26="",N26/(G26*(1-H26)),F26) -> 3 | L26: =IF(G26="",Table8[[#This Row],[Total_Amount2]]/(Table8[[#This Row],[Quantity]]*(1-Table8[[#This Row],[Discount]])),G26) -> 77.6 | M26: =IF(H26="",1-(Table8[[#This Row],[Total_Amount2]]/(Table8[[#This Row],[Quantity]]*Table8[[#This Row],[Unit_Price]])),H26) -> 0.07 | N26: =IF(J26="",F26*G26*(1-H26),J26) -> 216.504
A27: SALE25 | B27: 45552 | C27: CUST1381 | D27: PROD1 | E27: STORE3 | F27: 4 | G27: 852.71 | H27: 0.14 | I27: PayPal | J27: 2933.3224 | K27: =IF(F27="",N27/(G27*(1-H27)),F27) -> 4 | L27: =IF(G27="",Table8[[#This Row],[Total_Amount2]]/(Table8[[#This Row],[Quantity]]*(1-Table8[[#This Row],[Discount]])),G27) -> 852.71 | M27: =IF(H27="",1-(Table8[[#This Row],[Total_Amount2]]/(Table8[[#This Row],[Quantity]]*Table8[[#This Row],[Unit_Price]])),H27) -> 0.14 | N27: =IF(J27="",F27*G27*(1-H27),J27) -> 2933.3224
A28: SALE26 | B28: 45294 | C28: CUST1213 | D28: PROD1 | E28: STORE8 | F28: 4 | G28: 156.16 | I28: Credit Card | J28: 599.6544 | K28: =IF(F28="",N28/(G28*(1-H28)),F28) -> 4 | L28: =IF(G28="",Table8[[#This Row],[Total_Amount2]]/(Table8[[#This Row],[Quantity]]*(1-Table8[[#This Row],[Discount]])),G28) -> 156.16 | M28: =IF(H28="",1-(Table8[[#This Row],[Total_Amount2]]/(Table8[[#This Row],[Quantity]]*Table8[[#This Row],[Unit_Price]])),H28) -> 0.04 | N28: =IF(J28="",F28*G28*(1-H28),J28) -> 599.6544
A29: SALE27 | B29: 45710 | C29: CUST1200 | D29: PROD1 | E29: STORE8 | F29: 3 | G29: 815.49 | H29: 0.17 | I29: Credit Card | J29: 2030.5701 | K29: =IF(F29="",N29/(G29*(1-H29)),F29) -> 3 | L29: =IF(G29="",Table8[[#This Row],[Total_Amount2]]/(Table8[[#This Row],[Quantity]]*(1-Table8[[#This Row],[Discount]])),G29) -> 815.49 | M29: =IF(H29="",1-(Table8[[#This Row],[Total_Amount2]]/(Table8[[#This Row],[Quantity]]*Table8[[#This Row],[Unit_Price]])),H29) -> 0.17 | N29: =IF(J29="",F29*G29*(1-H29),J29) -> 2030.5701
A30: SALE28 | B30: 45923 | C30: CUST1148 | D30: PROD1 | E30: STORE2 | F30: 2 | G30: 74.21 | H30: 0.11 | I30: PayPal | J30: 132.0938 | K30: =IF(F30="",N30/(G30*(1-H30)),F30) -> 2 | L30: =IF(G30="",Table8[[#This Row],[Total_Amount2]]/(Table8[[#This Row],[Quantity]]*(1-Table8[[#This Row],[Discount]])),G30) -> 74.21 | M30: =IF(H30="",1-(Table8[[#This Row],[Total_Amount2]]/(Table8[[#This Row],[Quantity]]*Table8[[#This Row],[Unit_Price]])),H30) -> 0.11 | N30: =IF(J30="",F30*G30*(1-H30),J30) -> 132.0938
A31: SALE29 | B31: 45302 | C31: CUST1348 | D31: PROD1 | E31: STORE3 | G31: 451.67 | H31: 0.15 | I31: Credit Card | J31: 1535.678 | K31: =IF(F31="",N31/(G31*(1-H31)),F31) -> 4 | L31: =IF(G31="",Table8[[#This Row],[Total_Amount2]]/(Table8[[#This Row],[Quantity]]*(1-Table8[[#This Row],[Discount]])),G31) -> 451.67 | M31: =IF(H31="",1-(Table8[[#This Row],[Total_Amount2]]/(Table8[[#This Row],[Quantity]]*Table8[[#This Row],[Unit_Price]])),H31) -> 0.15 | N31: =IF(J31="",F31*G31*(1-H31),J31) -> 1535.678
A32: SALE30 | B32: 45217 | C32: CUST1028 | D32: PROD1 | E32: STORE19 | F32: 1 | G32: 429.38 | H32: 0.13 | I32: PayPal | J32: 373.5606 | K32: =IF(F32="",N32/(G32*(1-H32)),F32) -> 1 | L32: =IF(G32="",Table8[[#This Row],[Total_Amount2]]/(Table8[[#This Row],[Quantity]]*(1-Table8[[#This Row],[Discount]])),G32) -> 429.38 | M32: =IF(H32="",1-(Table8[[#This Row],[Total_Amount2]]/(Table8[[#This Row],[Quantity]]*Table8[[#This Row],[Unit_Price]])),H32) -> 0.13 | N32: =IF(J32="",F32*G32*(1-H32),J32) -> 373.5606
A33: SALE31 | B33: 45593 | C33: CUST1412 | D33: PROD10 | E33: STORE12 | F33: 2 | G33: 148.96 | H33: 0.03 | I33: COD | J33: 288.9824 | K33: =IF(F33="",N33/(G33*(1-H33)),F33) -> 2 | L33: =IF(G33="",Table8[[#This Row],[Total_Amount2]]/(Table8[[#This Row],[Quantity]]*(1-Table8[[#This Row],[Discount]])),G33) -> 148.96 | M33: =IF(H33="",1-(Table8[[#This Row],[Total_Amount2]]/(Table8[[#This Row],[Quantity]]*Table8[[#This Row],[Unit_Price]])),H33) -> 0.03 | N33: =IF(J33="",F33*G33*(1-H33),J33) -> 288.9824
A34: SALE32 | B34: 45597 | C34: CUST1398 | D34: PROD10 | E34: STORE8 | F34: 4 | G34: 313.83 | H34: 0.08 | I34: Credit Card | J34: 1154.8944 | K34: =IF(F34="",N34/(G34*(1-H34)),F34) -> 4 | L34: =IF(G34="",Table8[[#This Row],[Total_Amount2]]/(Table8[[#This Row],[Quantity]]*(1-Table8[[#This Row],[Discount]])),G34) -> 313.83 | M34: =IF(H34="",1-(Table8[[#This Row],[Total_Amount2]]/(Table8[[#This Row],[Quantity]]*Table8[[#This Row],[Unit_Price]])),H34) -> 0.08 | N34: =IF(J34="",F34*G34*(1-H34),J34) -> 1154.8944
A35: SALE33 | B35: 45620 | C35: CUST1453 | D35: PROD10 | E35: STORE6 | F35: 2 | G35: 717.31 | H35: 0.15 | I35: Credit Card | J35: 1219.427 | K35: =IF(F35="",N35/(G35*(1-H35)),F35) -> 2 | L35: =IF(G35="",Table8[[#This Row],[Total_Amount2]]/(Table8[[#This Row],[Quantity]]*(1-Table8[[#This Row],[Discount]])),G35) -> 717.31 | M35: =IF(H35="",1-(Table8[[#This Row],[Total_Amount2]]/(Table8[[#This Row],[Quantity]]*Table8[[#This Row],[Unit_Price]])),H35) -> 0.15 | N35: =IF(J35="",F35*G35*(1-H35),J35) -> 1219.427
A36: SALE34 | B36: 45215 | C36: CUST1344 | D36: PROD10 | E36: STORE1 | G36: 873.22 | H36: 0.18 | I36: Credit Card | J36: 2148.1212 | K36: =IF(F36="",N36/(G36*(1-H36)),F36) -> 3 | L36: =IF(G36="",Table8[[#This Row],[Total_Amount2]]/(Table8[[#This Row],[Quantity]]*(1-Table8[[#This Row],[Discount]])),G36) -> 873.22 | M36: =IF(H36="",1-(Table8[[#This Row],[Total_Amount2]]/(Table8[[#This Row],[Quantity]]*Table8[[#This Row],[Unit_Price]])),H36) -> 0.18 | N36: =IF(J36="",F36*G36*(1-H36),J36) -> 2148.1212
A37: SALE35 | B37: 45878 | C37: CUST1218 | D37: PROD10 | E37: STORE3 | F37: 4 | G37: 109.36 | H37: 0.19 | I37: COD | J37: 354.3264 | K37: =IF(F37="",N37/(G37*(1-H37)),F37) -> 4 | L37: =IF(G37="",Table8[[#This Row],[Total_Amount2]]/(Table8[[#This Row],[Quantity]]*(1-Table8[[#This Row],[Discount]])),G37) -> 109.36 | M37: =IF(H37="",1-(Table8[[#This Row],[Total_Amount2]]/(Table8[[#This Row],[Quantity]]*Table8[[#This Row],[Unit_Price]])),H37) -> 0.19 | N37: =IF(J37="",F37*G37*(1-H37),J37) -> 354.3264
A38: SALE36 | B38: 45635 | C38: CUST1086 | D38: PROD10 | E38: STORE7 | F38: 3 | G38: 559.52 | H38: 0.16 | I38: PayPal | J38: 1409.9904 | K38: =IF(F38="",N38/(G38*(1-H38)),F38) -> 3 | L38: =IF(G38="",Table8[[#This Row],[Total_Amount2]]/(Table8[[#This Row],[Quantity]]*(1-Table8[[#This Row],[Discount]])),G38) -> 559.52 | M38: =IF(H38="",1-(Table8[[#This Row],[Total_Amount2]]/(Table8[[#This Row],[Quantity]]*Table8[[#This Row],[Unit_Price]])),H38) -> 0.16 | N38: =IF(J38="",F38*G38*(1-H38),J38) -> 1409.9904
A39: SALE37 | B39: 45329 | C39: CUST1492 | D39: PROD10 | E39: STORE17 | F39: 3 | G39: 121.76 | H39: 0.27 | I39: PayPal | J39: 266.6544 | K39: =IF(F39="",N39/(G39*(1-H39)),F39) -> 3 | L39: =IF(G39="",Table8[[#This Row],[Total_Amount2]]/(Table8[[#This Row],[Quantity]]*(1-Table8[[#This Row],[Discount]])),G39) -> 121.76 | M39: =IF(H39="",1-(Table8[[#This Row],[Total_Amount2]]/(Table8[[#This Row],[Quantity]]*Table8[[#This Row],[Unit_Price]])),H39) -> 0.27 | N39: =IF(J39="",F39*G39*(1-H39),J39) -> 266.6544
A40: SALE38 | B40: 45378 | C40: CUST1189 | D40: PROD10 | E40: STORE13 | F40: 4 | G40: 735.32 | H40: 0.06 | I40: COD | J40: 2764.8032 | K40: =IF(F40="",N40/(G40*(1-H40)),F40) -> 4 | L40: =IF(G40="",Table8[[#This Row],[Total_Amount2]]/(Table8[[#This Row],[Quantity]]*(1-Table8[[#This Row],[Discount]])),G40) -> 735.32 | M40: =IF(H40="",1-(Table8[[#This Row],[Total_Amount2]]/(Table8[[#This Row],[Quantity]]*Table8[[#This Row],[Unit_Price]])),H40) -> 0.06 | N40: =IF(J40="",F40*G40*(1-H40),J40) -> 2764.8032
A41: SALE39 | B41: 45264 | C41: CUST1431 | D41: PROD10 | E41: STORE3 | F41: 2 | G41: 600.73 | H41: 0.08 | I41: Credit Card | J41: 1105.3432 | K41: =IF(F41="",N41/(G41*(1-H41)),F41) -> 2 | L41: =IF(G41="",Table8[[#This Row],[Total_Amount2]]/(Table8[[#This Row],[Quantity]]*(1-Table8[[#This Row],[Discount]])),G41) -> 600.73 | M41: =IF(H41="",1-(Table8[[#This Row],[Total_Amount2]]/(Table8[[#This Row],[Quantity]]*Table8[[#This Row],[Unit_Price]])),H41) -> 0.08 | N41: =IF(J41="",F41*G41*(1-H41),J41) -> 1105.3432
A42: SALE40 | B42: 45486 | C42: CUST1072 | D42: PROD10 | E42: STORE19 | F42: 2 | G42: 873.86 | H42: 0.07 | I42: COD | J42: 1625.3796 | K42: =IF(F42="",N42/(G42*(1-H42)),F42) -> 2 | L42: =IF(G42="",Table8[[#This Row],[Total_Amount2]]/(Table8[[#This Row],[Quantity]]*(1-Table8[[#This Row],[Discount]])),G42) -> 873.86 | M42: =IF(H42="",1-(Table8[[#This Row],[Total_Amount2]]/(Table8[[#This Row],[Quantity]]*Table8[[#This Row],[Unit_Price]])),H42) -> 0.07 | N42: =IF(J42="",F42*G42*(1-H42),J42) -> 1625.3796
A43: SALE41 | B43: 45241 | C43: CUST1302 | D43: PROD10 | E43: STORE8 | F43: 3 | G43: 342.47 | H43: 0.08 | I43: PayPal | J43: 945.2172 | K43: =IF(F43="",N43/(G43*(1-H43)),F43) -> 3 | L43: =IF(G43="",Table8[[#This Row],[Total_Amount2]]/(Table8[[#This Row],[Quantity]]*(1-Table8[[#This Row],[Discount]])),G43) -> 342.47 | M43: =IF(H43="",1-(Table8[[#This Row],[Total_Amount2]]/(Table8[[#This Row],[Quantity]]*Table8[[#This Row],[Unit_Price]])),H43) -> 0.08 | N43: =IF(J43="",F43*G43*(1-H43),J43) -> 945.2172
A44: SALE42 | B44: 45649 | C44: CUST1335 | D44: PROD10 | E44: STORE9 | F44: 2 | G44: 915.15 | H44: 0.16 | I44: PayPal | J44: 1537.452 | K44: =IF(F44="",N44/(G44*(1-H44)),F44) -> 2 | L44: =IF(G44="",Table8[[#This Row],[Total_Amount2]]/(Table8[[#This Row],[Quantity]]*(1-Table8[[#This Row],[Discount]])),G44) -> 915.15 | M44: =IF(H44="",1-(Table8[[#This Row],[Total_Amount2]]/(Table8[[#This Row],[Quantity]]*Table8[[#This Row],[Unit_Price]])),H44) -> 0.16 | N44: =IF(J44="",F44*G44*(1-H44),J44) -> 1537.452
A45: SALE43 | B45: 45677 | C45: CUST1084 | D45: PROD10 | E45: STORE17 | G45: 863.11 | H45: 0.28 | I45: PayPal | J45: 1864.3176 | K45: =IF(F45="",N45/(G45*(1-H45)),F45) -> 3 | L45: =IF(G45="",Table8[[#This Row],[Total_Amount2]]/(Table8[[#This Row],[Quantity]]*(1-Table8[[#This Row],[Discount]])),G45) -> 863.11 | M45: =IF(H45="",1-(Table8[[#This Row],[Total_Amount2]]/(Table8[[#This Row],[Quantity]]*Table8[[#This Row],[Unit_Price]])),H45) -> 0.28 | N45: =IF(J45="",F45*G45*(1-H45),J45) -> 1864.3176
A46: SALE44 | B46: 45538 | C46: CUST1203 | D46: PROD10 | E46: STORE12 | F46: 2 | G46: 209.32 | H46: 0.23 | I46: COD | J46: 322.3528 | K46: =IF(F46="",N46/(G46*(1-H46)),F46) -> 2 | L46: =IF(G46="",Table8[[#This Row],[Total_Amount2]]/(Table8[[#This Row],[Quantity]]*(1-Table8[[#This Row],[Discount]])),G46) -> 209.32 | M46: =IF(H46="",1-(Table8[[#This Row],[Total_Amount2]]/(Table8[[#This Row],[Quantity]]*Table8[[#This Row],[Unit_Price]])),H46) -> 0.23 | N46: =IF(J46="",F46*G46*(1-H46),J46) -> 322.3528
A47: SALE45 | B47: 45606 | C47: CUST1470 | D47: PROD10 | E47: STORE8 | F47: 4 | G47: 288.6 | H47: 0.09 | I47: PayPal | J47: 1050.504 | K47: =IF(F47="",N47/(G47*(1-H47)),F47) -> 4 | L47: =IF(G47="",Table8[[#This Row],[Total_Amount2]]/(Table8[[#This Row],[Quantity]]*(1-Table8[[#This Row],[Discount]])),G47) -> 288.6 | M47: =IF(H47="",1-(Table8[[#This Row],[Total_Amount2]]/(Table8[[#This Row],[Quantity]]*Table8[[#This Row],[Unit_Price]])),H47) -> 0.09 | N47: =IF(J47="",F47*G47*(1-H47),J47) -> 1050.504
A48: SALE46 | B48: 45570 | C48: CUST1070 | D48: PROD10 | E48: STORE16 | F48: 1 | G48: 418.69 | H48: 0.06 | I48: PayPal | J48: 393.5686 | K48: =IF(F48="",N48/(G48*(1-H48)),F48) -> 1 | L48: =IF(G48="",Table8[[#This Row],[Total_Amount2]]/(Table8[[#This Row],[Quantity]]*(1-Table8[[#This Row],[Discount]])),G48) -> 418.69 | M48: =IF(H48="",1-(Table8[[#This Row],[Total_Amount2]]/(Table8[[#This Row],[Quantity]]*Table8[[#This Row],[Unit_Price]])),H48) -> 0.06 | N48: =IF(J48="",F48*G48*(1-H48),J48) -> 393.5686
A49: SALE47 | B49: 45466 | C49: CUST1008 | D49: PROD10 | E49: STORE11 | F49: 1 | G49: 135.78 | H49: 0.14 | I49: PayPal | J49: 116.7708 | K49: =IF(F49="",N49/(G49*(1-H49)),F49) -> 1 | L49: =IF(G49="",Table8[[#This Row],[Total_Amount2]]/(Table8[[#This Row],[Quantity]]*(1-Table8[[#This Row],[Discount]])),G49) -> 135.78 | M49: =IF(H49="",1-(Table8[[#This Row],[Total_Amount2]]/(Table8[[#This Row],[Quantity]]*Table8[[#This Row],[Unit_Price]])),H49) -> 0.14 | N49: =IF(J49="",F49*G49*(1-H49),J49) -> 116.7708
A50: SALE48 | B50: 45218 | C50: CUST1203 | D50: PROD10 | E50: STORE17 | F50: 1 | G50: 517.13 | H50: 0.28 | I50: Credit Card | J50: 372.3336 | K50: =IF(F50="",N50/(G50*(1-H50)),F50) -> 1 | L50: =IF(G50="",Table8[[#This Row],[Total_Amount2]]/(Table8[[#This Row],[Quantity]]*(1-Table8[[#This Row],[Discount]])),G50) -> 517.13 | M50: =IF(H50="",1-(Table8[[#This Row],[Total_Amount2]]/(Table8[[#This Row],[Quantity]]*Table8[[#This Row],[Unit_Price]])),H50) -> 0.28 | N50: =IF(J50="",F50*G50*(1-H50),J50) -> 372.3336
A51: SALE49 | B51: 45607 | C51: CUST1420 | D51: PROD10 | E51: STORE16 | F51: 2 | G51: 384.66 | H51: 0.08 | I51: COD | J51: 707.7744 | K51: =IF(F51="",N51/(G51*(1-H51)),F51) -> 2 | L51: =IF(G51="",Table8[[#This Row],[Total_Amount2]]/(Table8[[#This Row],[Quantity]]*(1-Table8[[#This Row],[Discount]])),G51) -> 384.66 | M51: =IF(H51="",1-(Table8[[#This Row],[Total_Amount2]]/(Table8[[#This Row],[Quantity]]*Table8[[#This Row],[Unit_Price]])),H51) -> 0.08 | N51: =IF(J51="",F51*G51*(1-H51),J51) -> 707.7744
A52: SALE50 | B52: 45291 | C52: CUST1070 | D52: PROD10 | E52: STORE9 | F52: 3 | G52: 83.7 | H52: 0.24 | I52: PayPal | J52: 190.836 | K52: =IF(F52="",N52/(G52*(1-H52)),F52) -> 3 | L52: =IF(G52="",Table8[[#This Row],[Total_Amount2]]/(Table8[[#This Row],[Quantity]]*(1-Table8[[#This Row],[Discount]])),G52) -> 83.7 | M52: =IF(H52="",1-(Table8[[#This Row],[Total_Amount2]]/(Table8[[#This Row],[Quantity]]*Table8[[#This Row],[Unit_Price]])),H52) -> 0.24 | N52: =IF(J52="",F52*G52*(1-H52),J52) -> 190.836
A53: SALE51 | B53: 45689 | C53: CUST1142 | D53: PROD10 | E53: STORE7 | F53: 3 | G53: 76.57 | H53: 0.26 | I53: Credit Card | J53: 169.9854 | K53: =IF(F53="",N53/(G53*(1-H53)),F53) -> 3 | L53: =IF(G53="",Table8[[#This Row],[Total_Amount2]]/(Table8[[#This Row],[Quantity]]*(1-Table8[[#This Row],[Discount]])),G53) -> 76.57 | M53: =IF(H53="",1-(Table8[[#This Row],[Total_Amount2]]/(Table8[[#This Row],[Quantity]]*Table8[[#This Row],[Unit_Price]])),H53) -> 0.26 | N53: =IF(J53="",F53*G53*(1-H53),J53) -> 169.9854
A54: SALE52 | B54: 45894 | C54: CUST1148 | D54: PROD11 | E54: STORE6 | F54: 3 | I54: Credit Card | J54: 486.0633 | K54: =IF(F54="",N54/(G54*(1-H54)),F54) -> 3 | L54: =IF(G54="",Table8[[#This Row],[Total_Amount2]]/(Table8[[#This Row],[Quantity]]*(1-Table8[[#This Row],[Discount]])),G54) -> 162.0211 | M54: =IF(H54="",1-(Table8[[#This Row],[Total_Amount2]]/(Table8[[#This Row],[Quantity]]*Table8[[#This Row],[Unit_Price]])),H54) -> #DIV/0! | N54: =IF(J54="",F54*G54*(1-H54),J54) -> 486.0633
A55: SALE53 | B55: 45677 | C55: CUST1324 | D55: PROD11 | E55: STORE8 | F55: 1 | G55: 900.35 | H55: 0.13 | I55: COD | J55: 783.3045 | K55: =IF(F55="",N55/(G55*(1-H55)),F55) -> 1 | L55: =IF(G55="",Table8[[#This Row],[Total_Amount2]]/(Table8[[#This Row],[Quantity]]*(1-Table8[[#This Row],[Discount]])),G55) -> 900.35 | M55: =IF(H55="",1-(Table8[[#This Row],[Total_Amount2]]/(Table8[[#This Row],[Quantity]]*Table8[[#This Row],[Unit_Price]])),H55) -> 0.13 | N55: =IF(J55="",F55*G55*(1-H55),J55) -> 783.3045
A56: SALE54 | B56: 45706 | C56: CUST1095 | D56: PROD11 | E56: STORE10 | F56: 4 | G56: 428.09 | H56: 0.07 | I56: Credit Card | J56: 1592.4948 | K56: =IF(F56="",N56/(G56*(1-H56)),F56) -> 4 | L56: =IF(G56="",Table8[[#This Row],[Total_Amount2]]/(Table8[[#This Row],[Quantity]]*(1-Table8[[#This Row],[Discount]])),G56) -> 428.09 | M56: =IF(H56="",1-(Table8[[#This Row],[Total_Amount2]]/(Table8[[#This Row],[Quantity]]*Table8[[#This Row],[Unit_Price]])),H56) -> 0.07 | N56: =IF(J56="",F56*G56*(1-H56),J56) -> 1592.4948
A57: SALE55 | B57: 45589 | C57: CUST1416 | D57: PROD11 | E57: STORE11 | F57: 2 | G57: 559.71 | H57: 0.3 | I57: COD | J57: 783.594 | K57: =IF(F57="",N57/(G57*(1-H57)),F57) -> 2 | L57: =IF(G57="",Table8[[#This Row],[Total_Amount2]]/(Table8[[#This Row],[Quantity]]*(1-Table8[[#This Row],[Discount]])),G57) -> 559.71 | M57: =IF(H57="",1-(Table8[[#This Row],[Total_Amount2]]/(Table8[[#This Row],[Quantity]]*Table8[[#This Row],[Unit_Price]])),H57) -> 0.3 | N57: =IF(J57="",F57*G57*(1-H57),J57) -> 783.594
A58: SALE56 | B58: 45282 | C58: CUST1080 | D58: PROD11 | E58: STORE6 | F58: 2 | G58: 833.7 | H58: 0.06 | I58: PayPal | J58: 1567.356 | K58: =IF(F58="",N58/(G58*(1-H58)),F58) -> 2 | L58: =IF(G58="",Table8[[#This Row],[Total_Amount2]]/(Table8[[#This Row],[Quantity]]*(1-Table8[[#This Row],[Discount]])),G58) -> 833.7 | M58: =IF(H58="",1-(Table8[[#This Row],[Total_Amount2]]/(Table8[[#This Row],[Quantity]]*Table8[[#This Row],[Unit_Price]])),H58) -> 0.06 | N58: =IF(J58="",F58*G58*(1-H58),J58) -> 1567.356
A59: SALE57 | B59: 45462 | C59: CUST1467 | D59: PROD11 | E59: STORE14 | F59: 2 | G59: 680.16 | H59: 0.28 | I59: Credit Card | J59: 979.4304 | K59: =IF(F59="",N59/(G59*(1-H59)),F59) -> 2 | L59: =IF(G59="",Table8[[#This Row],[Total_Amount2]]/(Table8[[#This Row],[Quantity]]*(1-Table8[[#This Row],[Discount]])),G59) -> 680.16 | M59: =IF(H59="",1-(Table8[[#This Row],[Total_Amount2]]/(Table8[[#This Row],[Quantity]]*Table8[[#This Row],[Unit_Price]])),H59) -> 0.28 | N59: =IF(J59="",F59*G59*(1-H59),J59) -> 979.4304
A60: SALE58 | B60: 45633 | C60: CUST1404 | D60: PROD11 | E60: STORE7 | F60: 4 | G60: 733.42 | I60: PayPal | J60: 2552.3016 | K60: =IF(F60="",N60/(G60*(1-H60)),F60) -> 4 | L60: =IF(G60="",Table8[[#This Row],[Total_Amount2]]/(Table8[[#This Row],[Quantity]]*(1-Table8[[#This Row],[Discount]])),G60) -> 733.42 | M60: =IF(H60="",1-(Table8[[#This Row],[Total_Amount2]]/(Table8[[#This Row],[Quantity]]*Table8[[#This Row],[Unit_Price]])),H60) -> 0.13 | N60: =IF(J60="",F60*G60*(1-H60),J60) -> 2552.3016
A61: SALE59 | B61: 45257 | C61: CUST1367 | D61: PROD11 | E61: STORE11 | F61: 1 | G61: 996.33 | H61: 0.23 | I61: PayPal | J61: 767.1741 | K61: =IF(F61="",N61/(G61*(1-H61)),F61) -> 1 | L61: =IF(G61="",Table8[[#This Row],[Total_Amount2]]/(Table8[[#This Row],[Quantity]]*(1-Table8[[#This Row],[Discount]])),G61) -> 996.33 | M61: =IF(H61="",1-(Table8[[#This Row],[Total_Amount2]]/(Table8[[#This Row],[Quantity]]*Table8[[#This Row],[Unit_Price]])),H61) -> 0.23 | N61: =IF(J61="",F61*G61*(1-H61),J61) -> 767.1741
A62: SALE60 | B62: 45854 | C62: CUST1408 | D62: PROD11 | E62: STORE10 | F62: 1 | G62: 198.83 | H62: 0.09 | I62: COD | J62: 180.9353 | K62: =IF(F62="",N62/(G62*(1-H62)),F62) -> 1 | L62: =IF(G62="",Table8[[#This Row],[Total_Amount2]]/(Table8[[#This Row],[Quantity]]*(1-Table8[[#This Row],[Discount]])),G62) -> 198.83 | M62: =IF(H62="",1-(Table8[[#This Row],[Total_Amount2]]/(Table8[[#This Row],[Quantity]]*Table8[[#This Row],[Unit_Price]])),H62) -> 0.09 | N62: =IF(J62="",F62*G62*(1-H62),J62) -> 180.9353
A63: SALE61 | B63: 45716 | C63: CUST1239 | D63: PROD11 | E63: STORE7 | F63: 1 | G63: 374.92 | H63: 0.18 | I63: PayPal | J63: 307.4344 | K63: =IF(F63="",N63/(G63*(1-H63)),F63) -> 1 | L63: =IF(G63="",Table8[[#This Row],[Total_Amount2]]/(Table8[[#This Row],[Quantity]]*(1-Table8[[#This Row],[Discount]])),G63) -> 374.92 | M63: =IF(H63="",1-(Table8[[#This Row],[Total_Amount2]]/(Table8[[#This Row],[Quantity]]*Table8[[#This Row],[Unit_Price]])),H63) -> 0.18 | N63: =IF(J63="",F63*G63*(1-H63),J63) -> 307.4344
A64: SALE62 | B64: 45515 | C64: CUST1464 | D64: PROD11 | E64: STORE16 | F64: 1 | G64: 468.94 | H64: 0.12 | I64: Credit Card | J64: 412.6672 | K64: =IF(F64="",N64/(G64*(1-H64)),F64) -> 1 | L64: =IF(G64="",Table8[[#This Row],[Total_Amount2]]/(Table8[[#This Row],[Quantity]]*(1-Table8[[#This Row],[Discount]])),G64) -> 468.94 | M64: =IF(H64="",1-(Table8[[#This Row],[Total_Amount2]]/(Table8[[#This Row],[Quantity]]*Table8[[#This Row],[Unit_Price]])),H64) -> 0.12 | N64: =IF(J64="",F64*G64*(1-H64),J64) -> 412.6672
A65: SALE63 | B65: 45927 | C65: CUST1126 | D65: PROD11 | E65: STORE12 | F65: 2 | G65: 121.37 | H65: 0.05 | I65: Credit Card | J65: 230.603 | K65: =IF(F65="",N65/(G65*(1-H65)),F65) -> 2 | L65: =IF(G65="",Table8[[#This Row],[Total_Amount2]]/(Table8[[#This Row],[Quantity]]*(1-Table8[[#This Row],[Discount]])),G65) -> 121.37 | M65: =IF(H65="",1-(Table8[[#This Row],[Total_Amount2]]/(Table8[[#This Row],[Quantity]]*Table8[[#This Row],[Unit_Price]])),H65) -> 0.05 | N65: =IF(J65="",F65*G65*(1-H65),J65) -> 230.603
A66: SALE64 | B66: 45914 | C66: CUST1255 | D66: PROD11 | E66: STORE10 | F66: 3 | G66: 480.06 | H66: 0.01 | I66: Credit Card | K66: =IF(F66="",N66/(G66*(1-H66)),F66) -> 3 | L66: =IF(G66="",Table8[[#This Row],[Total_Amount2]]/(Table8[[#This Row],[Quantity]]*(1-Table8[[#This Row],[Discount]])),G66) -> 480.06 | M66: =IF(H66="",1-(Table8[[#This Row],[Total_Amount2]]/(Table8[[#This Row],[Quantity]]*Table8[[#This Row],[Unit_Price]])),H66) -> 0.01 | N66: =IF(J66="",F66*G66*(1-H66),J66) -> 1425.7782
A67: SALE65 | B67: 45290 | C67: CUST1162 | D67: PROD11 | E67: STORE17 | F67: 2 | G67: 856.57 | H67: 0.24 | I67: Credit Card | J67: 1301.9864 | K67: =IF(F67="",N67/(G67*(1-H67)),F67) -> 2 | L67: =IF(G67="",Table8[[#This Row],[Total_Amount2]]/(Table8[[#This Row],[Quantity]]*(1-Table8[[#This Row],[Discount]])),G67) -> 856.57 | M67: =IF(H67="",1-(Table8[[#This Row],[Total_Amount2]]/(Table8[[#This Row],[Quantity]]*Table8[[#This Row],[Unit_Price]])),H67) -> 0.24 | N67: =IF(J67="",F67*G67*(1-H67),J67) -> 1301.9864
A68: SALE66 | B68: 45213 | C68: CUST1269 | D68: PROD11 | E68: STORE2 | F68: 4 | G68: 814.25 | H68: 0.18 | I68: Credit Card | J68: 2670.74 | K68: =IF(F68="",N68/(G68*(1-H68)),F68) -> 4 | L68: =IF(G68="",Table8[[#This Row],[Total_Amount2]]/(Table8[[#This Row],[Quantity]]*(1-Table8[[#This Row],[Discount]])),G68) -> 814.25 | M68: =IF(H68="",1-(Table8[[#This Row],[Total_Amount2]]/(Table8[[#This Row],[Quantity]]*Table8[[#This Row],[Unit_Price]])),H68) -> 0.18 | N68: =IF(J68="",F68*G68*(1-H68),J68) -> 2670.74
A69: SALE67 | B69: 45255 | C69: CUST1483 | D69: PROD11 | E69: STORE2 | F69: 1 | G69: 989.17 | H69: 0.2 | I69: PayPal | J69: 791.336 | K69: =IF(F69="",N69/(G69*(1-H69)),F69) -> 1 | L69: =IF(G69="",Table8[[#This Row],[Total_Amount2]]/(Table8[[#This Row],[Quantity]]*(1-Table8[[#This Row],[Discount]])),G69) -> 989.17 | M69: =IF(H69="",1-(Table8[[#This Row],[Total_Amount2]]/(Table8[[#This Row],[Quantity]]*Table8[[#This Row],[Unit_Price]])),H69) -> 0.2 | N69: =IF(J69="",F69*G69*(1-H69),J69) -> 791.336
A70: SALE68 | B70: 45270 | C70: CUST1372 | D70: PROD11 | E70: STORE10 | F70: 4 | G70: 62.48 | H70: 0.18 | I70: Credit Card | J70: 204.9344 | K70: =IF(F70="",N70/(G70*(1-H70)),F70) -> 4 | L70: =IF(G70="",Table8[[#This Row],[Total_Amount2]]/(Table8[[#This Row],[Quantity]]*(1-Table8[[#This Row],[Discount]])),G70) -> 62.48 | M70: =IF(H70="",1-(Table8[[#This Row],[Total_Amount2]]/(Table8[[#This Row],[Quantity]]*Table8[[#This Row],[Unit_Price]])),H70) -> 0.18 | N70: =IF(J70="",F70*G70*(1-H70),J70) -> 204.9344
A71: SALE69 | B71: 45897 | C71: CUST1423 | D71: PROD11 | E71: STORE16 | F71: 4 | G71: 561.24 | H71: 0.24 | I71: Credit Card | J71: 1706.1696 | K71: =IF(F71="",N71/(G71*(1-H71)),F71) -> 4 | L71: =IF(G71="",Table8[[#This Row],[Total_Amount2]]/(Table8[[#This Row],[Quantity]]*(1-Table8[[#This Row],[Discount]])),G71) -> 561.24 | M71: =IF(H71="",1-(Table8[[#This Row],[Total_Amount2]]/(Table8[[#This Row],[Quantity]]*Table8[[#This Row],[Unit_Price]])),H71) -> 0.24 | N71: =IF(J71="",F71*G71*(1-H71),J71) -> 1706.1696
A72: SALE70 | B72: 45849 | C72: CUST1058 | D72: PROD11 | E72: STORE5 | F72: 3 | G72: 92.24 | H72: 0.28 | I72: COD | K72: =IF(F72="",N72/(G72*(1-H72)),F72) -> 3 | L72: =IF(G72="",Table8[[#This Row],[Total_Amount2]]/(Table8[[#This Row],[Quantity]]*(1-Table8[[#This Row],[Discount]])),G72) -> 92.24 | M72: =IF(H72="",1-(Table8[[#This Row],[Total_Amount2]]/(Table8[[#This Row],[Quantity]]*Table8[[#This Row],[Unit_Price]])),H72) -> 0.28 | N72: =IF(J72="",F72*G72*(1-H72),J72) -> 199.2384
A73: SALE71 | B73: 45889 | C73: CUST1168 | D73: PROD12 | E73: STORE1 | F73: 2 | G73: 668.3 | H73: 0.07 | I73: Credit Card | J73: 1243.038 | K73: =IF(F73="",N73/(G73*(1-H73)),F73) -> 2 | L73: =IF(G73="",Table8[[#This Row],[Total_Amount2]]/(Table8[[#This Row],[Quantity]]*(1-Table8[[#This Row],[Discount]])),G73) -> 668.3 | M73: =IF(H73="",1-(Table8[[#This Row],[Total_Amount2]]/(Table8[[#This Row],[Quantity]]*Table8[[#This Row],[Unit_Price]])),H73) -> 0.07 | N73: =IF(J73="",F73*G73*(1-H73),J73) -> 1243.038
A74: SALE72 | B74: 45533 | C74: CUST1409 | D74: PROD12 | E74: STORE5 | F74: 1 | G74: 553.82 | H74: 0.09 | I74: Credit Card | J74: 503.9762 | K74: =IF(F74="",N74/(G74*(1-H74)),F74) -> 1 | L74: =IF(G74="",Table8[[#This Row],[Total_Amount2]]/(Table8[[#This Row],[Quantity]]*(1-Table8[[#This Row],[Discount]])),G74) -> 553.82 | M74: =IF(H74="",1-(Table8[[#This Row],[Total_Amount2]]/(Table8[[#This Row],[Quantity]]*Table8[[#This Row],[Unit_Price]])),H74) -> 0.09 | N74: =IF(J74="",F74*G74*(1-H74),J74) -> 503.9762
A75: SALE73 | B75: 45626 | C75: CUST1037 | D75: PROD12 | E75: STORE11 | F75: 2 | G75: 556.43 | H75: 0.13 | I75: Credit Card | J75: 968.1882 | K75: =IF(F75="",N75/(G75*(1-H75)),F75) -> 2 | L75: =IF(G75="",Table8[[#This Row],[Total_Amount2]]/(Table8[[#This Row],[Quantity]]*(1-Table8[[#This Row],[Discount]])),G75) -> 556.43 | M75: =IF(H75="",1-(Table8[[#This Row],[Total_Amount2]]/(Table8[[#This Row],[Quantity]]*Table8[[#This Row],[Unit_Price]])),H75) -> 0.13 | N75: =IF(J75="",F75*G75*(1-H75),J75) -> 968.1882
A76: SALE74 | B76: 45942 | C76: CUST1273 | D76: PROD12 | E76: STORE8 | F76: 1 | G76: 184.98 | H76: 0.1 | I76: COD | J76: 166.482 | K76: =IF(F76="",N76/(G76*(1-H76)),F76) -> 1 | L76: =IF(G76="",Table8[[#This Row],[Total_Amount2]]/(Table8[[#This Row],[Quantity]]*(1-Table8[[#This Row],[Discount]])),G76) -> 184.98 | M76: =IF(H76="",1-(Table8[[#This Row],[Total_Amount2]]/(Table8[[#This Row],[Quantity]]*Table8[[#This Row],[Unit_Price]])),H76) -> 0.1 | N76: =IF(J76="",F76*G76*(1-H76),J76) -> 166.482
A77: SALE75 | B77: 45500 | C77: CUST1035 | D77: PROD12 | E77: STORE12 | F77: 4 | G77: 700.18 | H77: 0.23 | I77: Credit Card | J77: 2156.5544 | K77: =IF(F77="",N77/(G77*(1-H77)),F77) -> 4 | L77: =IF(G77="",Table8[[#This Row],[Total_Amount2]]/(Table8[[#This Row],[Quantity]]*(1-Table8[[#This Row],[Discount]])),G77) -> 700.18 | M77: =IF(H77="",1-(Table8[[#This Row],[Total_Amount2]]/(Table8[[#This Row],[Quantity]]*Table8[[#This Row],[Unit_Price]])),H77) -> 0.23 | N77: =IF(J77="",F77*G77*(1-H77),J77) -> 2156.5544
A78: SALE76 | B78: 45285 | C78: CUST1019 | D78: PROD12 | E78: STORE10 | F78: 2 | G78: 686.31 | H78: 0.25 | I78: Credit Card | J78: 1029.465 | K78: =IF(F78="",N78/(G78*(1-H78)),F78) -> 2 | L78: =IF(G78="",Table8[[#This Row],[Total_Amount2]]/(Table8[[#This Row],[Quantity]]*(1-Table8[[#This Row],[Discount]])),G78) -> 686.31 | M78: =IF(H78="",1-(Table8[[#This Row],[Total_Amount2]]/(Table8[[#This Row],[Quantity]]*Table8[[#This Row],[Unit_Price]])),H78) -> 0.25 | N78: =IF(J78="",F78*G78*(1-H78),J78) -> 1029.465
A79: SALE77 | B79: 45800 | C79: CUST1007 | D79: PROD12 | E79: STORE15 | F79: 1 | G79: 687.82 | H79: 0.27 | I79: COD | J79: 502.1086 | K79: =IF(F79="",N79/(G79*(1-H79)),F79) -> 1 | L79: =IF(G79="",Table8[[#This Row],[Total_Amount2]]/(Table8[[#This Row],[Quantity]]*(1-Table8[[#This Row],[Discount]])),G79) -> 687.82 | M79: =IF(H79="",1-(Table8[[#This Row],[Total_Amount2]]/(Table8[[#This Row],[Quantity]]*Table8[[#This Row],[Unit_Price]])),H79) -> 0.27 | N79: =IF(J79="",F79*G79*(1-H79),J79) -> 502.1086
A80: SALE78 | B80: 45609 | C80: CUST1221 | D80: PROD12 | E80: STORE8 | F80: 2 | G80: 900.55 | H80: 0.16 | I80: Credit Card | J80: 1512.924 | K80: =IF(F80="",N80/(G80*(1-H80)),F80) -> 2 | L80: =IF(G80="",Table8[[#This Row],[Total_Amount2]]/(Table8[[#This Row],[Quantity]]*(1-Table8[[#This Row],[Discount]])),G80) -> 900.55 | M80: =IF(H80="",1-(Table8[[#This Row],[Total_Amount2]]/(Table8[[#This Row],[Quantity]]*Table8[[#This Row],[Unit_Price]])),H80) -> 0.16 | N80: =IF(J80="",F80*G80*(1-H80),J80) -> 1512.924
A81: SALE79 | B81: 45268 | C81: CUST1115 | D81: PROD12 | E81: STORE2 | F81: 1 | G81: 341.17 | H81: 0.15 | I81: Credit Card | J81: 289.9945 | K81: =IF(F81="",N81/(G81*(1-H81)),F81) -> 1 | L81: =IF(G81="",Table8[[#This Row],[Total_Amount2]]/(Table8[[#This Row],[Quantity]]*(1-Table8[[#This Row],[Discount]])),G81) -> 341.17 | M81: =IF(H81="",1-(Table8[[#This Row],[Total_Amount2]]/(Table8[[#This Row],[Quantity]]*Table8[[#This Row],[Unit_Price]])),H81) -> 0.15 | N81: =IF(J81="",F81*G81*(1-H81),J81) -> 289.9945
A82: SALE80 | B82: 45885 | C82: CUST1176 | D82: PROD12 | E82: STORE8 | F82: 1 | G82: 442.27 | H82: 0.06 | I82: COD | J82: 415.7338 | K82: =IF(F82="",N82/(G82*(1-H82)),F82) -> 1 | L82: =IF(G82="",Table8[[#This Row],[Total_Amount2]]/(Table8[[#This Row],[Quantity]]*(1-Table8[[#This Row],[Discount]])),G82) -> 442.27 | M82: =IF(H82="",1-(Table8[[#This Row],[Total_Amount2]]/(Table8[[#This Row],[Quantity]]*Table8[[#This Row],[Unit_Price]])),H82) -> 0.06 | N82: =IF(J82="",F82*G82*(1-H82),J82) -> 415.7338
A83: SALE81 | B83: 45616 | C83: CUST1253 | D83: PROD12 | E83: STORE9 | F83: 1 | G83: 363.73 | H83: 0.25 | I83: PayPal | J83: 272.7975 | K83: =IF(F83="",N83/(G83*(1-H83)),F83) -> 1 | L83: =IF(G83="",Table8[[#This Row],[Total_Amount2]]/(Table8[[#This Row],[Quantity]]*(1-Table8[[#This Row],[Discount]])),G83) -> 363.73 | M83: =IF(H83="",1-(Table8[[#This Row],[Total_Amount2]]/(Table8[[#This Row],[Quantity]]*Table8[[#This Row],[Unit_Price]])),H83) -> 0.25 | N83: =IF(J83="",F83*G83*(1-H83),J83) -> 272.7975
A84: SALE82 | B84: 45518 | C84: CUST1378 | D84: PROD12 | E84: STORE17 | F84: 2 | G84: 601.33 | H84: 0.16 | I84: PayPal | J84: 1010.2344 | K84: =IF(F84="",N84/(G84*(1-H84)),F84) -> 2 | L84: =IF(G84="",Table8[[#This Row],[Total_Amount2]]/(Table8[[#This Row],[Quantity]]*(1-Table8[[#This Row],[Discount]])),G84) -> 601.33 | M84: =IF(H84="",1-(Table8[[#This Row],[Total_Amount2]]/(Table8[[#This Row],[Quantity]]*Table8[[#This Row],[Unit_Price]])),H84) -> 0.16 | N84: =IF(J84="",F84*G84*(1-H84),J84) -> 1010.2344
A85: SALE83 | B85: 45427 | C85: CUST1403 | D85: PROD12 | E85: STORE18 | F85: 4 | G85: 34.39 | H85: 0.03 | I85: PayPal | J85: 133.4332 | K85: =IF(F85="",N85/(G85*(1-H85)),F85) -> 4 | L85: =IF(G85="",Table8[[#This Row],[Total_Amount2]]/(Table8[[#This Row],[Quantity]]*(1-Table8[[#This Row],[Discount]])),G85) -> 34.39 | M85: =IF(H85="",1-(Table8[[#This Row],[Total_Amount2]]/(Table8[[#This Row],[Quantity]]*Table8[[#This Row],[Unit_Price]])),H85) -> 0.03 | N85: =IF(J85="",F85*G85*(1-H85),J85) -> 133.4332
A86: SALE84 | B86: 45268 | C86: CUST1423 | D86: PROD12 | E86: STORE17 | F86: 1 | G86: 773.57 | H86: 0.05 | I86: COD | K86: =IF(F86="",N86/(G86*(1-H86)),F86) -> 1 | L86: =IF(G86="",Table8[[#This Row],[Total_Amount2]]/(Table8[[#This Row],[Quantity]]*(1-Table8[[#This Row],[Discount]])),G86) -> 773.57 | M86: =IF(H86="",1-(Table8[[#This Row],[Total_Amount2]]/(Table8[[#This Row],[Quantity]]*Table8[[#This Row],[Unit_Price]])),H86) -> 0.05 | N86: =IF(J86="",F86*G86*(1-H86),J86) -> 734.8915
A87: SALE85 | B87: 45282 | C87: CUST1054 | D87: PROD12 | E87: STORE7 | F87: 4 | G87: 127.1 | H87: 0.24 | I87: COD | J87: 386.384 | K87: =IF(F87="",N87/(G87*(1-H87)),F87) -> 4 | L87: =IF(G87="",Table8[[#This Row],[Total_Amount2]]/(Table8[[#This Row],[Quantity]]*(1-Table8[[#This Row],[Discount]])),G87) -> 127.1 | M87: =IF(H87="",1-(Table8[[#This Row],[Total_Amount2]]/(Table8[[#This Row],[Quantity]]*Table8[[#This Row],[Unit_Price]])),H87) -> 0.24 | N87: =IF(J87="",F87*G87*(1-H87),J87) -> 386.384
A88: SALE86 | B88: 45545 | C88: CUST1303 | D88: PROD12 | E88: STORE3 | F88: 3 | G88: 899.58 | H88: 0.28 | I88: PayPal | J88: 1943.0928 | K88: =IF(F88="",N88/(G88*(1-H88)),F88) -> 3 | L88: =IF(G88="",Table8[[#This Row],[Total_Amount2]]/(Table8[[#This Row],[Quantity]]*(1-Table8[[#This Row],[Discount]])),G88) -> 899.58 | M88: =IF(H88="",1-(Table8[[#This Row],[Total_Amount2]]/(Table8[[#This Row],[Quantity]]*Table8[[#This Row],[Unit_Price]])),H88) -> 0.28 | N88: =IF(J88="",F88*G88*(1-H88),J88) -> 1943.0928
A89: SALE87 | B89: 45755 | C89: CUST1327 | D89: PROD12 | E89: STORE10 | F89: 3 | G89: 964.39 | H89: 0.04 | I89: Credit Card | J89: 2777.4432 | K89: =IF(F89="",N89/(G89*(1-H89)),F89) -> 3 | L89: =IF(G89="",Table8[[#This Row],[Total_Amount2]]/(Table8[[#This Row],[Quantity]]*(1-Table8[[#This Row],[Discount]])),G89) -> 964.39 | M89: =IF(H89="",1-(Table8[[#This Row],[Total_Amount2]]/(Table8[[#This Row],[Quantity]]*Table8[[#This Row],[Unit_Price]])),H89) -> 0.04 | N89: =IF(J89="",F89*G89*(1-H89),J89) -> 2777.4432
A90: SALE88 | B90: 45588 | C90: CUST1183 | D90: PROD12 | E90: STORE0 | F90: 2 | G90: 217.83 | H90: 0.14 | I90: PayPal | J90: 374.6676 | K90: =IF(F90="",N90/(G90*(1-H90)),F90) -> 2 | L90: =IF(G90="",Table8[[#This Row],[Total_Amount2]]/(Table8[[#This Row],[Quantity]]*(1-Table8[[#This Row],[Discount]])),G90) -> 217.83 | M90: =IF(H90="",1-(Table8[[#This Row],[Total_Amount2]]/(Table8[[#This Row],[Quantity]]*Table8[[#This Row],[Unit_Price]])),H90) -> 0.14 | N90: =IF(J90="",F90*G90*(1-H90),J90) -> 374.6676
A91: SALE89 | B91: 45848 | C91: CUST1143 | D91: PROD12 | E91: STORE1 | F91: 4 | G91: 187.71 | H91: 0.06 | I91: COD | J91: 705.7896 | K91: =IF(F91="",N91/(G91*(1-H91)),F91) -> 4 | L91: =IF(G91="",Table8[[#This Row],[Total_Amount2]]/(Table8[[#This Row],[Quantity]]*(1-Table8[[#This Row],[Discount]])),G91) -> 187.71 | M91: =IF(H91="",1-(Table8[[#This Row],[Total_Amount2]]/(Table8[[#This Row],[Quantity]]*Table8[[#This Row],[Unit_Price]])),H91) -> 0.06 | N91: =IF(J91="",F91*G91*(1-H91),J91) -> 705.7896
A92: SALE90 | B92: 45577 | C92: CUST1010 | D92: PROD13 | E92: STORE18 | F92: 2 | G92: 350.12 | H92: 0.12 | I92: COD | J92: 616.2112 | K92: =IF(F92="",N92/(G92*(1-H92)),F92) -> 2 | L92: =IF(G92="",Table8[[#This Row],[Total_Amount2]]/(Table8[[#This Row],[Quantity]]*(1-Table8[[#This Row],[Discount]])),G92) -> 350.12 | M92: =IF(H92="",1-(Table8[[#This Row],[Total_Amount2]]/(Table8[[#This Row],[Quantity]]*Table8[[#This Row],[Unit_Price]])),H92) -> 0.12 | N92: =IF(J92="",F92*G92*(1-H92),J92) -> 616.2112
A93: SALE91 | B93: 45312 | C93: CUST1406 | D93: PROD13 | E93: STORE1 | F93: 4 | G93: 102.19 | H93: 0.17 | I93: PayPal | J93: 339.2708 | K93: =IF(F93="",N93/(G93*(1-H93)),F93) -> 4 | L93: =IF(G93="",Table8[[#This Row],[Total_Amount2]]/(Table8[[#This Row],[Quantity]]*(1-Table8[[#This Row],[Discount]])),G93) -> 102.19 | M93: =IF(H93="",1-(Table8[[#This Row],[Total_Amount2]]/(Table8[[#This Row],[Quantity]]*Table8[[#This Row],[Unit_Price]])),H93) -> 0.17 | N93: =IF(J93="",F93*G93*(1-H93),J93) -> 339.2708
A94: SALE92 | B94: 45350 | C94: CUST1007 | D94: PROD13 | E94: STORE4 | F94: 1 | G94: 696.53 | H94: 0.17 | I94: Credit Card | J94: 578.1199 | K94: =IF(F94="",N94/(G94*(1-H94)),F94) -> 1 | L94: =IF(G94="",Table8[[#This Row],[Total_Amount2]]/(Table8[[#This Row],[Quantity]]*(1-Table8[[#This Row],[Discount]])),G94) -> 696.53 | M94: =IF(H94="",1-(Table8[[#This Row],[Total_Amount2]]/(Table8[[#This Row],[Quantity]]*Table8[[#This Row],[Unit_Price]])),H94) -> 0.17 | N94: =IF(J94="",F94*G94*(1-H94),J94) -> 578.1199
A95: SALE93 | B95: 45657 | C95: CUST1065 | D95: PROD13 | E95: STORE4 | F95: 2 | G95: 327.52 | H95: 0.15 | I95: PayPal | J95: 556.784 | K95: =IF(F95="",N95/(G95*(1-H95)),F95) -> 2 | L95: =IF(G95="",Table8[[#This Row],[Total_Amount2]]/(Table8[[#This Row],[Quantity]]*(1-Table8[[#This Row],[Discount]])),G95) -> 327.52 | M95: =IF(H95="",1-(Table8[[#This Row],[Total_Amount2]]/(Table8[[#This Row],[Quantity]]*Table8[[#This Row],[Unit_Price]])),H95) -> 0.15 | N95: =IF(J95="",F95*G95*(1-H95),J95) -> 556.784
A96: SALE94 | B96: 45530 | C96: CUST1298 | D96: PROD13 | E96: STORE19 | F96: 2 | G96: 569.36 | H96: 0.01 | I96: PayPal | K96: =IF(F96="",N96/(G96*(1-H96)),F96) -> 2 | L96: =IF(G96="",Table8[[#This Row],[Total_Amount2]]/(Table8[[#This Row],[Quantity]]*(1-Table8[[#This Row],[Discount]])),G96) -> 569.36 | M96: =IF(H96="",1-(Table8[[#This Row],[Total_Amount2]]/(Table8[[#This Row],[Quantity]]*Table8[[#This Row],[Unit_Price]])),H96) -> 0.01 | N96: =IF(J96="",F96*G96*(1-H96),J96) -> 1127.3328
A97: SALE95 | B97: 45556 | C97: CUST1321 | D97: PROD13 | E97: STORE6 | F97: 2 | G97: 68.29 | H97: 0.14 | I97: COD | J97: 117.4588 | K97: =IF(F97="",N97/(G97*(1-H97)),F97) -> 2 | L97: =IF(G97="",Table8[[#This Row],[Total_Amount2]]/(Table8[[#This Row],[Quantity]]*(1-Table8[[#This Row],[Discount]])),G97) -> 68.29 | M97: =IF(H97="",1-(Table8[[#This Row],[Total_Amount2]]/(Table8[[#This Row],[Quantity]]*Table8[[#This Row],[Unit_Price]])),H97) -> 0.14 | N97: =IF(J97="",F97*G97*(1-H97),J97) -> 117.4588
A98: SALE96 | B98: 45523 | C98: CUST1244 | D98: PROD13 | E98: STORE10 | F98: 1 | G98: 842.9 | H98: 0.06 | I98: COD | J98: 792.326 | K98: =IF(F98="",N98/(G98*(1-H98)),F98) -> 1 | L98: =IF(G98="",Table8[[#This Row],[Total_Amount2]]/(Table8[[#This Row],[Quantity]]*(1-Table8[[#This Row],[Discount]])),G98) -> 842.9 | M98: =IF(H98="",1-(Table8[[#This Row],[Total_Amount2]]/(Table8[[#This Row],[Quantity]]*Table8[[#This Row],[Unit_Price]])),H98) -> 0.06 | N98: =IF(J98="",F98*G98*(1-H98),J98) -> 792.326
A99: SALE97 | B99: 45587 | C99: CUST1287 | D99: PROD13 | E99: STORE3 | F99: 3 | G99: 751.94 | H99: 0.26 | I99: PayPal | J99: 1669.3068 | K99: =IF(F99="",N99/(G99*(1-H99)),F99) -> 3 | L99: =IF(G99="",Table8[[#This Row],[Total_Amount2]]/(Table8[[#This Row],[Quantity]]*(1-Table8[[#This Row],[Discount]])),G99) -> 751.94 | M99: =IF(H99="",1-(Table8[[#This Row],[Total_Amount2]]/(Table8[[#This Row],[Quantity]]*Table8[[#This Row],[Unit_Price]])),H99) -> 0.26 | N99: =IF(J99="",F99*G99*(1-H99),J99) -> 1669.3068
A100: SALE98 | B100: 45580 | C100: CUST1131 | D100: PROD13 | E100: STORE7 | F100: 4 | G100: 476.28 | H100: 0.17 | I100: Credit Card | J100: 1581.2496 | K100: =IF(F100="",N100/(G100*(1-H100)),F100) -> 4 | L100: =IF(G100="",Table8[[#This Row],[Total_Amount2]]/(Table8[[#This Row],[Quantity]]*(1-Table8[[#This Row],[Discount]])),G100) -> 476.28 | M100: =IF(H100="",1-(Table8[[#This Row],[Total_Amount2]]/(Table8[[#This Row],[Quantity]]*Table8[[#This Row],[Unit_Price]])),H100) -> 0.17 | N100: =IF(J100="",F100*G100*(1-H100),J100) -> 1581.2496
...

Sheet Customer_Dim Cleaned
A1: Customer_ID | B1: Name | C1: Age | D1: Gender | E1: City | F1: State | G1: Country | H1: Loyalty_Level | J1: Cleaning Process
A2: CUST1000 | B2: Sheena Bonilla | C2: 55 | D2: Male | E2: Donaldton | F2: North Carolina | G2: USA | H2: Platinum | J2: 1.There are some inconsistencies found in Customer_ID and Name column that are corrected.
A3: CUST1001 | B3: Eugene Nelson | C3: 26 | D3: Female | E3: Phillipsmouth | F3: North Dakota | G3: USA | H3: Platinum | J3: 2.Missing values in Loyality_Level column has imputed by Mode function.
A4: CUST1002 | B4: Dr. Benjamin Price | C4: 29 | D4: Female | E4: Kylebury | F4: Alabama | G4: USA | H4: Platinum
A5: CUST1003 | B5: Jeremy Harris | C5: 59 | D5: Female | E5: Thomastown | F5: Ohio | G5: USA | H5: Bronze
A6: CUST1004 | B6: Caroline Collins | C6: 64 | D6: Female | E6: Nicholasshire | F6: California | G6: USA | H6: Silver
A7: CUST1005 | B7: Christine Vaughn | C7: 24 | D7: Male | E7: East Amandamouth | F7: Oregon | G7: USA | H7: Bronze
A8: CUST1006 | B8: Amber Jackson | C8: 29 | D8: Female | E8: Deborahborough | F8: South Dakota | G8: USA | H8: Platinum
A9: CUST1007 | B9: Daniel Boyd | C9: 29 | D9: Female | E9: West Pamelafurt | F9: West Virginia | G9: USA | H9: Bronze
A10: CUST1008 | B10: Melissa Howard | C10: 53 | D10: Female | E10: Maynardton | F10: New Hampshire | G10: USA | H10: Gold
A11: CUST1009 | B11: Ms. Maria Leach | C11: 64 | D11: Male | E11: Melissashire | F11: Pennsylvania | G11: USA | H11: Platinum
A12: CUST1010 | B12: Dominic Page | C12: 53 | D12: Male | E12: Port Michaelburgh | F12: Pennsylvania | G12: USA | H12: Bronze
A13: CUST1011 | B13: Brian Lopez | C13: 28 | D13: Female | E13: East Krista | F13: New York | G13: USA | H13: Gold
A14: CUST1012 | B14: Kenneth Lambert | C14: 55 | D14: Female | E14: North Kathryn | F14: Kansas | G14: USA | H14: Platinum
A15: CUST1013 | B15: Nathan Hernandez | C15: 32 | D15: Female | E15: New Becky | F15: Montana | G15: USA | H15: Silver
... A501: CUST1499 | B501: Philip Pennington | C501: 27 | D501: Female | E501: East Valerieview | F501: Oregon | G501: USA | H501: Platinum

Sheet Product_Dim Cleaned
A1: Product_ID | B1: Product_Name | C1: Category | D1: Sub_Category | E1: Brand | F1: Cost | G1: Stock | J1: Cleaning Process
A2: PROD0 | B2: Brother Laser Printer | C2: Electronics | D2: Computer | E2: Hunt Inc | F2: 112.42 | G2: 416 | J2: 1.Inconsistency found in Product_ID column and that are corrected.
A3: PROD1 | B3: Men's Graphic T-Shirt | C3: Clothing | D3: Tops | E3: Terry-Moore | F3: 342.56 | G3: 181 | J3: 2.Some values are Missing in Cost and Stock column that are imputed by
A4: PROD2 | B4: Women's Casual Hoodie | C4: Clothing | D4: Outerwear | E4: Sims Inc | F4: 296.82667 | G4: 352 | J4: COST=IF(F2="",AVERAGEIFS($F$2:$F$101,$C$2:$C$101,C2,$D$2:$D$101,D2),F2)
A5: PROD3 | B5: Men's Running Jacket | C5: Clothing | D5: Outerwear | E5: Pineda Ltd | F5: 364.67 | G5: 452
A6: PROD4 | B6: Women's Yoga Pants | C6: Clothing | D6: Bottoms | E6: Gonzales-Davis | F6: 306.46 | G6: 487 | J6: STOCK=IF(G2="",MEDIAN(IF(($C$2:$C$101=C2)*($D$2:$D$101=D2),$G$2:$G$101)),G2)
A7: PROD5 | B7: Men's Leather Belt | C7: Clothing | D7: Accessories | E7: Baldwin, Garza and Gonzalez | F7: 261 | G7: 59
A8: PROD6 | B8: Herbal Face Moisturizer | C8: Beauty | D8: Skincare | E8: Davidson PLC | F8: 312.8 | G8: 350
A9: PROD7 | B9: LED Table Lamp | C9: Home | D9: Lighting | E9: Harrell LLC | F9: 218.86 | G9: 170
A10: PROD8 | B10: Wireless Bluetooth Earbuds | C10: Electronics | D10: Audio | E10: Perez-Johnston | F10: 439.07 | G10: 142
A11: PROD9 | B11: Adjustable Dumbbell Set | C11: Sports | D11: Fitness | E11: Hill PLC | F11: 495.72 | G11: 323
A12: PROD10 | B12: Ceramic Kitchen Bowl Set | C12: Home | D12: Kitchen | E12: Hamilton Group | F12: 298.86 | G12: 308
A13: PROD11 | B13: HD Smart TV Stick | C13: Electronics | D13: Accessories | E13: Gibson, Hobbs and Weaver | F13: 449.4 | G13: 361
A14: PROD12 | B14: Hair Strengthening Shampoo | C14: Beauty | D14: Haircare | E14: Rice LLC | F14: 115.82 | G14: 460
A15: PROD13 | B15: USB-C Fast Charger | C15: Electronics | D15: Accessories | E15: Dawson-Perkins | F15: 242.23 | G15: 453
A16: PROD14 | B16: Decorative Wall Mirror | C16: Home | D16: Decor | E16: Luna, Anderson and Bowman | F16: 48.01 | G16: 439
A17: PROD15 | B17: 4K Home Projector | C17: Electronics | D17: Appliances | E17: Thomas LLC | F17: 465.34 | G17: 301
A18: PROD16 | B18: Beard Grooming Kit | C18: Beauty | D18: Grooming | E18: Erickson-Green | F18: 337.42 | G18: 256
... A101: PROD99 | B101: Stainless Steel Cookware Set | C101: Home | D101: Kitchen | E101: Campbell Ltd | F101: 201.41 | G101: 146

Sheet Store_Dim
A1: Store_ID | B1: Store_Name | C1: Region | D1: City | E1: Store_Type | G1: Cleaning Process
A2: STORE0 | B2: Rivera-Warner | C2: East | D2: Washingtonfurt | E2: Flagship | G2: 1.There is no inconsistency found.
A3: STORE1 | B3: Martinez, Adkins and Johnson | C3: North | D3: Danielmouth | E3: Flagship | G3: 2.Tables created and text formatting done
A4: STORE2 | B4: Black-Horn | C4: South | D4: North Nancyview | E4: Outlet
A5: STORE3 | B5: Johnson-Wright | C5: North | D5: Hoodberg | E5: Outlet
A6: STORE4 | B6: Alexander Group | C6: South | D6: Port Sharon | E6: Online
A7: STORE5 | B7: Gray Ltd | C7: North | D7: New Michaelchester | E7: Outlet
A8: STORE6 | B8: Benson-Elliott | C8: East | D8: Port Josephberg | E8: Online
A9: STORE7 | B9: Martinez-Mullins | C9: South | D9: Williamsfurt | E9: Online
A10: STORE8 | B10: Bean, Jones and Park | C10: West | D10: Thompsonborough | E10: Online
A11: STORE9 | B11: Moore, Padilla and Butler | C11: South | D11: East Johnstad | E11: Flagship
A12: STORE10 | B12: Hill, Wagner and Ballard | C12: East | D12: East Davidville | E12: Online
A13: STORE11 | B13: Aguirre-Keller | C13: South | D13: Lake Michael | E13: Online
A14: STORE12 | B14: Thomas, Bridges and Harris | C14: North | D14: Sabrinatown | E14: Online
A15: STORE13 | B15: Gardner, Humphrey and Contreras | C15: East | D15: Johnsonville | E15: Flagship
... A21: STORE19 | B21: Mann-Austin | C21: East | D21: Vasquezborough | E21: Online

Sheet Sales_Fact Cleaned
A1: Sales_ID | B1: Order_Date | C1: Customer_ID | D1: Gender | E1: City | F1: State | G1: Product_ID | H1: Product_Name | I1: Category | J1: Sub_Category | K1: Store_ID | L1: Quantity | M1: Unit_Price | N1: Discount | O1: Payment_Type | P1: Total_Amount | S1: Cleaning Process
A2: SALE0 | B2: 45480 | C2: CUST1409 | D2: =VLOOKUP($C2,'Customer_Dim Cleaned'!$A$1:$H$501,4,FALSE) -> Male | E2: =VLOOKUP($C2,'Customer_Dim Cleaned'!$A$1:$H$501,5,FALSE) -> Kathleenport | F2: =VLOOKUP($C2,'Customer_Dim Cleaned'!$A$1:$H$501,6,FALSE) -> Wyoming | G2: PROD0 | H2: =VLOOKUP($G2,'Product_Dim Cleaned'!$A$1:$G$101,2,FALSE) -> Brother Laser Printer | I2: =VLOOKUP($G2,'Product_Dim Cleaned'!$A$1:$G$101,3,FALSE) -> Electronics | J2: =VLOOKUP($G2,'Product_Dim Cleaned'!$A$1:$G$101,4,FALSE) -> Computer | K2: STORE3 | L2: 1 | M2: 218.04 | N2: 0.09 | O2: Credit Card | P2: 198.4164 | R2: 1 | S2: Order_Date column datatype changed.
A3: SALE1 | B3: 45285 | C3: CUST1467 | D3: =VLOOKUP($C3,'Customer_Dim Cleaned'!$A$1:$H$501,4,FALSE) -> Female | E3: =VLOOKUP($C3,'Customer_Dim Cleaned'!$A$1:$H$501,5,FALSE) -> Oneillfurt | F3: =VLOOKUP($C3,'Customer_Dim Cleaned'!$A$1:$H$501,6,FALSE) -> Vermont | G3: PROD0 | H3: =VLOOKUP($G3,'Product_Dim Cleaned'!$A$1:$G$101,2,FALSE) -> Brother Laser Printer | I3: =VLOOKUP($G3,'Product_Dim Cleaned'!$A$1:$G$101,3,FALSE) -> Electronics | J3: =VLOOKUP($G3,'Product_Dim Cleaned'!$A$1:$G$101,4,FALSE) -> Computer | K3: STORE17 | L3: 3 | M3: 104.47 | N3: 0.27 | O3: PayPal | P3: 228.7893 | R3: 2 | S3: Numerical column missing values are imputed by
A4: SALE2 | B4: 45446 | C4: CUST1056 | D4: =VLOOKUP($C4,'Customer_Dim Cleaned'!$A$1:$H$501,4,FALSE) -> Female | E4: =VLOOKUP($C4,'Customer_Dim Cleaned'!$A$1:$H$501,5,FALSE) -> Deborahberg | F4: =VLOOKUP($C4,'Customer_Dim Cleaned'!$A$1:$H$501,6,FALSE) -> Pennsylvania | G4: PROD0 | H4: =VLOOKUP($G4,'Product_Dim Cleaned'!$A$1:$G$101,2,FALSE) -> Brother Laser Printer | I4: =VLOOKUP($G4,'Product_Dim Cleaned'!$A$1:$G$101,3,FALSE) -> Electronics | J4: =VLOOKUP($G4,'Product_Dim Cleaned'!$A$1:$G$101,4,FALSE) -> Computer | K4: STORE8 | L4: 4 | M4: 914.05 | N4: 0.25 | O4: Credit Card | P4: 2742.15
A5: SALE3 | B5: 45259 | C5: CUST1346 | D5: =VLOOKUP($C5,'Customer_Dim Cleaned'!$A$1:$H$501,4,FALSE) -> Female | E5: =VLOOKUP($C5,'Customer_Dim Cleaned'!$A$1:$H$501,5,FALSE) -> Port Crystalberg | F5: =VLOOKUP($C5,'Customer_Dim Cleaned'!$A$1:$H$501,6,FALSE) -> Tennessee | G5: PROD0 | H5: =VLOOKUP($G5,'Product_Dim Cleaned'!$A$1:$G$101,2,FALSE) -> Brother Laser Printer | I5: =VLOOKUP($G5,'Product_Dim Cleaned'!$A$1:$G$101,3,FALSE) -> Electronics | J5: =VLOOKUP($G5,'Product_Dim Cleaned'!$A$1:$G$101,4,FALSE) -> Computer | K5: STORE8 | L5: 1 | M5: 921.51 | N5: 0.16 | O5: COD | P5: 774.0684 | S5: Quantity=IF(F2="",N2/(G2*(1-H2)),F2)
A6: SALE4 | B6: 45297 | C6: CUST1493 | D6: =VLOOKUP($C6,'Customer_Dim Cleaned'!$A$1:$H$501,4,FALSE) -> Male | E6: =VLOOKUP($C6,'Customer_Dim Cleaned'!$A$1:$H$501,5,FALSE) -> South William | F6: =VLOOKUP($C6,'Customer_Dim Cleaned'!$A$1:$H$501,6,FALSE) -> Alabama | G6: PROD0 | H6: =VLOOKUP($G6,'Product_Dim Cleaned'!$A$1:$G$101,2,FALSE) -> Brother Laser Printer | I6: =VLOOKUP($G6,'Product_Dim Cleaned'!$A$1:$G$101,3,FALSE) -> Electronics | J6: =VLOOKUP($G6,'Product_Dim Cleaned'!$A$1:$G$101,4,FALSE) -> Computer | K6: STORE5 | L6: 3 | M6: 745.3 | N6: 0.18 | O6: Credit Card | P6: 1833.438 | S6: Unit_Price=IF(G2="",[@[Total_Amount2]]/([@Quantity]*(1-[@Discount])),G2)
A7: SALE5 | B7: 45499 | C7: CUST1116 | D7: =VLOOKUP($C7,'Customer_Dim Cleaned'!$A$1:$H$501,4,FALSE) -> Female | E7: =VLOOKUP($C7,'Customer_Dim Cleaned'!$A$1:$H$501,5,FALSE) -> North Davidport | F7: =VLOOKUP($C7,'Customer_Dim Cleaned'!$A$1:$H$501,6,FALSE) -> Rhode Island | G7: PROD0 | H7: =VLOOKUP($G7,'Product_Dim Cleaned'!$A$1:$G$101,2,FALSE) -> Brother Laser Printer | I7: =VLOOKUP($G7,'Product_Dim Cleaned'!$A$1:$G$101,3,FALSE) -> Electronics | J7: =VLOOKUP($G7,'Product_Dim Cleaned'!$A$1:$G$101,4,FALSE) -> Computer | K7: STORE7 | L7: 3 | M7: 147.01 | N7: 0.19 | O7: COD | P7: 357.2343 | S7: Discount=IF(H2="",1-([@[Total_Amount2]]/([@Quantity]*[@[Unit_Price]])),H2)
A8: SALE6 | B8: 45850 | C8: CUST1016 | D8: =VLOOKUP($C8,'Customer_Dim Cleaned'!$A$1:$H$501,4,FALSE) -> Female | E8: =VLOOKUP($C8,'Customer_Dim Cleaned'!$A$1:$H$501,5,FALSE) -> South Christopher | F8: =VLOOKUP($C8,'Customer_Dim Cleaned'!$A$1:$H$501,6,FALSE) -> Pennsylvania | G8: PROD0 | H8: =VLOOKUP($G8,'Product_Dim Cleaned'!$A$1:$G$101,2,FALSE) -> Brother Laser Printer | I8: =VLOOKUP($G8,'Product_Dim Cleaned'!$A$1:$G$101,3,FALSE) -> Electronics | J8: =VLOOKUP($G8,'Product_Dim Cleaned'!$A$1:$G$101,4,FALSE) -> Computer | K8: STORE4 | L8: 2 | M8: 785.31 | N8: 0.15 | O8: PayPal | P8: 1335.027 | S8: Total_Amount=IF(J2="",F2*G2*(1-H2),J2)
A9: SALE7 | B9: 45248 | C9: CUST1152 | D9: =VLOOKUP($C9,'Customer_Dim Cleaned'!$A$1:$H$501,4,FALSE) -> Female | E9: =VLOOKUP($C9,'Customer_Dim Cleaned'!$A$1:$H$501,5,FALSE) -> Jaredville | F9: =VLOOKUP($C9,'Customer_Dim Cleaned'!$A$1:$H$501,6,FALSE) -> Missouri | G9: PROD0 | H9: =VLOOKUP($G9,'Product_Dim Cleaned'!$A$1:$G$101,2,FALSE) -> Brother Laser Printer | I9: =VLOOKUP($G9,'Product_Dim Cleaned'!$A$1:$G$101,3,FALSE) -> Electronics | J9: =VLOOKUP($G9,'Product_Dim Cleaned'!$A$1:$G$101,4,FALSE) -> Computer | K9: STORE8 | L9: 4 | M9: 342.39 | N9: 0.23 | O9: PayPal | P9: 1054.5612
A10: SALE8 | B10: 45781 | C10: CUST1187 | D10: =VLOOKUP($C10,'Customer_Dim Cleaned'!$A$1:$H$501,4,FALSE) -> Female | E10: =VLOOKUP($C10,'Customer_Dim Cleaned'!$A$1:$H$501,5,FALSE) -> Lake Blaketon | F10: =VLOOKUP($C10,'Customer_Dim Cleaned'!$A$1:$H$501,6,FALSE) -> Alabama | G10: PROD0 | H10: =VLOOKUP($G10,'Product_Dim Cleaned'!$A$1:$G$101,2,FALSE) -> Brother Laser Printer | I10: =VLOOKUP($G10,'Product_Dim Cleaned'!$A$1:$G$101,3,FALSE) -> Electronics | J10: =VLOOKUP($G10,'Product_Dim Cleaned'!$A$1:$G$101,4,FALSE) -> Computer | K10: STORE5 | L10: 3 | M10: 448.25 | N10: 0.07 | O10: PayPal | P10: 1250.6175 | R10: 3 | S10: Conditional formatting applied as follows
A11: SALE9 | B11: 45869 | C11: CUST1464 | D11: =VLOOKUP($C11,'Customer_Dim Cleaned'!$A$1:$H$501,4,FALSE) -> Female | E11: =VLOOKUP($C11,'Customer_Dim Cleaned'!$A$1:$H$501,5,FALSE) -> Grayland | F11: =VLOOKUP($C11,'Customer_Dim Cleaned'!$A$1:$H$501,6,FALSE) -> Washington | G11: PROD0 | H11: =VLOOKUP($G11,'Product_Dim Cleaned'!$A$1:$G$101,2,FALSE) -> Brother Laser Printer | I11: =VLOOKUP($G11,'Product_Dim Cleaned'!$A$1:$G$101,3,FALSE) -> Electronics | J11: =VLOOKUP($G11,'Product_Dim Cleaned'!$A$1:$G$101,4,FALSE) -> Computer | K11: STORE0 | L11: 2 | M11: 873.17 | N11: 0.23 | O11: PayPal | P11: 1344.6818 | S11: color scales applied on Unit_Price
A12: SALE10 | B12: 45335 | C12: CUST1065 | D12: =VLOOKUP($C12,'Customer_Dim Cleaned'!$A$1:$H$501,4,FALSE) -> Female | E12: =VLOOKUP($C12,'Customer_Dim Cleaned'!$A$1:$H$501,5,FALSE) -> Woodmouth | F12: =VLOOKUP($C12,'Customer_Dim Cleaned'!$A$1:$H$501,6,FALSE) -> Nevada | G12: PROD0 | H12: =VLOOKUP($G12,'Product_Dim Cleaned'!$A$1:$G$101,2,FALSE) -> Brother Laser Printer | I12: =VLOOKUP($G12,'Product_Dim Cleaned'!$A$1:$G$101,3,FALSE) -> Electronics | J12: =VLOOKUP($G12,'Product_Dim Cleaned'!$A$1:$G$101,4,FALSE) -> Computer | K12: STORE14 | L12: 1 | M12: 278.63 | N12: 0.07 | O12: Credit Card | P12: 259.1259 | S12: Top 10 discount % highlighted in Discount column
A13: SALE11 | B13: 45801 | C13: CUST1320 | D13: =VLOOKUP($C13,'Customer_Dim Cleaned'!$A$1:$H$501,4,FALSE) -> Female | E13: =VLOOKUP($C13,'Customer_Dim Cleaned'!$A$1:$H$501,5,FALSE) -> South Darrenland | F13: =VLOOKUP($C13,'Customer_Dim Cleaned'!$A$1:$H$501,6,FALSE) -> Iowa | G13: PROD0 | H13: =VLOOKUP($G13,'Product_Dim Cleaned'!$A$1:$G$101,2,FALSE) -> Brother Laser Printer | I13: =VLOOKUP($G13,'Product_Dim Cleaned'!$A$1:$G$101,3,FALSE) -> Electronics | J13: =VLOOKUP($G13,'Product_Dim Cleaned'!$A$1:$G$101,4,FALSE) -> Computer | K13: STORE1 | L13: 4 | M13: 286.92 | N13: 0.17 | O13: Credit Card | P13: 952.5744 | S13: Data Bars applied on Total_Amount column
A14: SALE12 | B14: 45528 | C14: CUST1237 | D14: =VLOOKUP($C14,'Customer_Dim Cleaned'!$A$1:$H$501,4,FALSE) -> Female | E14: =VLOOKUP($C14,'Customer_Dim Cleaned'!$A$1:$H$501,5,FALSE) -> Susanstad | F14: =VLOOKUP($C14,'Customer_Dim Cleaned'!$A$1:$H$501,6,FALSE) -> Montana | G14: PROD0 | H14: =VLOOKUP($G14,'Product_Dim Cleaned'!$A$1:$G$101,2,FALSE) -> Brother Laser Printer | I14: =VLOOKUP($G14,'Product_Dim Cleaned'!$A$1:$G$101,3,FALSE) -> Electronics | J14: =VLOOKUP($G14,'Product_Dim Cleaned'!$A$1:$G$101,4,FALSE) -> Computer | K14: STORE4 | L14: 4 | M14: 644.58 | N14: 0.01 | O14: Credit Card | P14: 2552.5368 | S14: Highlighted the cells where quantity >=3.
A15: SALE13 | B15: 45875 | C15: CUST1443 | D15: =VLOOKUP($C15,'Customer_Dim Cleaned'!$A$1:$H$501,4,FALSE) -> Male | E15: =VLOOKUP($C15,'Customer_Dim Cleaned'!$A$1:$H$501,5,FALSE) -> New Donnabury | F15: =VLOOKUP($C15,'Customer_Dim Cleaned'!$A$1:$H$501,6,FALSE) -> Texas | G15: PROD0 | H15: =VLOOKUP($G15,'Product_Dim Cleaned'!$A$1:$G$101,2,FALSE) -> Brother Laser Printer | I15: =VLOOKUP($G15,'Product_Dim Cleaned'!$A$1:$G$101,3,FALSE) -> Electronics | J15: =VLOOKUP($G15,'Product_Dim Cleaned'!$A$1:$G$101,4,FALSE) -> Computer | K15: STORE16 | L15: 2 | M15: 316.9 | N15: 0.3 | O15: PayPal | P15: 443.66
A16: SALE14 | B16: 45829 | C16: CUST1348 | D16: =VLOOKUP($C16,'Customer_Dim Cleaned'!$A$1:$H$501,4,FALSE) -> Male | E16: =VLOOKUP($C16,'Customer_Dim Cleaned'!$A$1:$H$501,5,FALSE) -> Shannonview | F16: =VLOOKUP($C16,'Customer_Dim Cleaned'!$A$1:$H$501,6,FALSE) -> Pennsylvania | G16: PROD0 | H16: =VLOOKUP($G16,'Product_Dim Cleaned'!$A$1:$G$101,2,FALSE) -> Brother Laser Printer | I16: =VLOOKUP($G16,'Product_Dim Cleaned'!$A$1:$G$101,3,FALSE) -> Electronics | J16: =VLOOKUP($G16,'Product_Dim Cleaned'!$A$1:$G$101,4,FALSE) -> Computer | K16: STORE15 | L16: 4 | M16: 403.47 | N16: 0.29 | O16: PayPal | P16: 1145.8548
A17: SALE15 | B17: 45636 | C17: CUST1435 | D17: =VLOOKUP($C17,'Customer_Dim Cleaned'!$A$1:$H$501,4,FALSE) -> Female | E17: =VLOOKUP($C17,'Customer_Dim Cleaned'!$A$1:$H$501,5,FALSE) -> Wesleyhaven | F17: =VLOOKUP($C17,'Customer_Dim Cleaned'!$A$1:$H$501,6,FALSE) -> Idaho | G17: PROD0 | H17: =VLOOKUP($G17,'Product_Dim Cleaned'!$A$1:$G$101,2,FALSE) -> Brother Laser Printer | I17: =VLOOKUP($G17,'Product_Dim Cleaned'!$A$1:$G$101,3,FALSE) -> Electronics | J17: =VLOOKUP($G17,'Product_Dim Cleaned'!$A$1:$G$101,4,FALSE) -> Computer | K17: STORE9 | L17: 3 | M17: 871.34 | N17: 0.04 | O17: COD | P17: 2509.4592
A18: SALE16 | B18: 45913 | C18: CUST1276 | D18: =VLOOKUP($C18,'Customer_Dim Cleaned'!$A$1:$H$501,4,FALSE) -> Male | E18: =VLOOKUP($C18,'Customer_Dim Cleaned'!$A$1:$H$501,5,FALSE) -> Ericshire | F18: =VLOOKUP($C18,'Customer_Dim Cleaned'!$A$1:$H$501,6,FALSE) -> Nevada | G18: PROD1 | H18: =VLOOKUP($G18,'Product_Dim Cleaned'!$A$1:$G$101,2,FALSE) -> Men's Graphic T-Shirt | I18: =VLOOKUP($G18,'Product_Dim Cleaned'!$A$1:$G$101,3,FALSE) -> Clothing | J18: =VLOOKUP($G18,'Product_Dim Cleaned'!$A$1:$G$101,4,FALSE) -> Tops | K18: STORE19 | L18: 2 | M18: 451.98 | N18: 0.25 | O18: Credit Card | P18: 677.97
A19: SALE17 | B19: 45637 | C19: CUST1079 | D19: =VLOOKUP($C19,'Customer_Dim Cleaned'!$A$1:$H$501,4,FALSE) -> Female | E19: =VLOOKUP($C19,'Customer_Dim Cleaned'!$A$1:$H$501,5,FALSE) -> Nicoleborough | F19: =VLOOKUP($C19,'Customer_Dim Cleaned'!$A$1:$H$501,6,FALSE) -> Arkansas | G19: PROD1 | H19: =VLOOKUP($G19,'Product_Dim Cleaned'!$A$1:$G$101,2,FALSE) -> Men's Graphic T-Shirt | I19: =VLOOKUP($G19,'Product_Dim Cleaned'!$A$1:$G$101,3,FALSE) -> Clothing | J19: =VLOOKUP($G19,'Product_Dim Cleaned'!$A$1:$G$101,4,FALSE) -> Tops | K19: STORE4 | L19: 2 | M19: 502.69 | N19: 0.23 | O19: Credit Card | P19: 774.1426 | S19: Discriptive Statistics using Analysis Toolpak
A20: SALE18 | B20: 45517 | C20: CUST1094 | D20: =VLOOKUP($C20,'Customer_Dim Cleaned'!$A$1:$H$501,4,FALSE) -> Female | E20: =VLOOKUP($C20,'Customer_Dim Cleaned'!$A$1:$H$501,5,FALSE) -> New Amyport | F20: =VLOOKUP($C20,'Customer_Dim Cleaned'!$A$1:$H$501,6,FALSE) -> Nevada | G20: PROD1 | H20: =VLOOKUP($G20,'Product_Dim Cleaned'!$A$1:$G$101,2,FALSE) -> Men's Graphic T-Shirt | I20: =VLOOKUP($G20,'Product_Dim Cleaned'!$A$1:$G$101,3,FALSE) -> Clothing | J20: =VLOOKUP($G20,'Product_Dim Cleaned'!$A$1:$G$101,4,FALSE) -> Tops | K20: STORE4 | L20: 2 | M20: 559.23 | N20: 0.25 | O20: COD | P20: 838.845
A21: SALE19 | B21: 45369 | C21: CUST1239 | D21: =VLOOKUP($C21,'Customer_Dim Cleaned'!$A$1:$H$501,4,FALSE) -> Female | E21: =VLOOKUP($C21,'Customer_Dim Cleaned'!$A$1:$H$501,5,FALSE) -> Zamoraborough | F21: =VLOOKUP($C21,'Customer_Dim Cleaned'!$A$1:$H$501,6,FALSE) -> Nevada | G21: PROD1 | H21: =VLOOKUP($G21,'Product_Dim Cleaned'!$A$1:$G$101,2,FALSE) -> Men's Graphic T-Shirt | I21: =VLOOKUP($G21,'Product_Dim Cleaned'!$A$1:$G$101,3,FALSE) -> Clothing | J21: =VLOOKUP($G21,'Product_Dim Cleaned'!$A$1:$G$101,4,FALSE) -> Tops | K21: STORE13 | L21: 4 | M21: 464.18 | N21: 0.04 | O21: COD | P21: 1782.4512 | S21: Quantity | U21: Unit_Price | W21: Discount | Y21: Total_Amount
A22: SALE20 | B22: 45843 | C22: CUST1144 | D22: =VLOOKUP($C22,'Customer_Dim Cleaned'!$A$1:$H$501,4,FALSE) -> Female | E22: =VLOOKUP($C22,'Customer_Dim Cleaned'!$A$1:$H$501,5,FALSE) -> North Anthonychester | F22: =VLOOKUP($C22,'Customer_Dim Cleaned'!$A$1:$H$501,6,FALSE) -> Nevada | G22: PROD1 | H22: =VLOOKUP($G22,'Product_Dim Cleaned'!$A$1:$G$101,2,FALSE) -> Men's Graphic T-Shirt | I22: =VLOOKUP($G22,'Product_Dim Cleaned'!$A$1:$G$101,3,FALSE) -> Clothing | J22: =VLOOKUP($G22,'Product_Dim Cleaned'!$A$1:$G$101,4,FALSE) -> Tops | K22: STORE17 | L22: 3 | M22: 986.04 | N22: 0.27 | O22: COD | P22: 2159.4276
A23: SALE21 | B23: 45447 | C23: CUST1396 | D23: =VLOOKUP($C23,'Customer_Dim Cleaned'!$A$1:$H$501,4,FALSE) -> Female | E23: =VLOOKUP($C23,'Customer_Dim Cleaned'!$A$1:$H$501,5,FALSE) -> Parkerview | F23: =VLOOKUP($C23,'Customer_Dim Cleaned'!$A$1:$H$501,6,FALSE) -> New York | G23: PROD1 | H23: =VLOOKUP($G23,'Product_Dim Cleaned'!$A$1:$G$101,2,FALSE) -> Men's Graphic T-Shirt | I23: =VLOOKUP($G23,'Product_Dim Cleaned'!$A$1:$G$101,3,FALSE) -> Clothing | J23: =VLOOKUP($G23,'Product_Dim Cleaned'!$A$1:$G$101,4,FALSE) -> Tops | K23: STORE18 | L23: 1 | M23: 589.56 | N23: 0.22 | O23: Credit Card | P23: 459.8568 | S23: Mean | T23: 2.482 | U23: Mean | V23: 513.58279 | W23: Mean | X23: 0.14796 | Y23: Mean | Z23: 1087.1973
A24: SALE22 | B24: 45394 | C24: CUST1476 | D24: =VLOOKUP($C24,'Customer_Dim Cleaned'!$A$1:$H$501,4,FALSE) -> Female | E24: =VLOOKUP($C24,'Customer_Dim Cleaned'!$A$1:$H$501,5,FALSE) -> Anthonymouth | F24: =VLOOKUP($C24,'Customer_Dim Cleaned'!$A$1:$H$501,6,FALSE) -> Oklahoma | G24: PROD1 | H24: =VLOOKUP($G24,'Product_Dim Cleaned'!$A$1:$G$101,2,FALSE) -> Men's Graphic T-Shirt | I24: =VLOOKUP($G24,'Product_Dim Cleaned'!$A$1:$G$101,3,FALSE) -> Clothing | J24: =VLOOKUP($G24,'Product_Dim Cleaned'!$A$1:$G$101,4,FALSE) -> Tops | K24: STORE10 | L24: 3 | M24: 979.42 | N24: 0.03 | O24: PayPal | P24: 2850.1122 | S24: Standard Error | T24: 0.024852501 | U24: Standard Error | V24: 6.3134988 | W24: Standard Error | X24: 0.0019598571 | Y24: Standard Error | Z24: 18.327237
A25: SALE23 | B25: 45466 | C25: CUST1368 | D25: =VLOOKUP($C25,'Customer_Dim Cleaned'!$A$1:$H$501,4,FALSE) -> Female | E25: =VLOOKUP($C25,'Customer_Dim Cleaned'!$A$1:$H$501,5,FALSE) -> West Mathew | F25: =VLOOKUP($C25,'Customer_Dim Cleaned'!$A$1:$H$501,6,FALSE) -> New York | G25: PROD1 | H25: =VLOOKUP($G25,'Product_Dim Cleaned'!$A$1:$G$101,2,FALSE) -> Men's Graphic T-Shirt | I25: =VLOOKUP($G25,'Product_Dim Cleaned'!$A$1:$G$101,3,FALSE) -> Clothing | J25: =VLOOKUP($G25,'Product_Dim Cleaned'!$A$1:$G$101,4,FALSE) -> Tops | K25: STORE8 | L25: 1 | M25: 719.28 | N25: 0.08 | O25: Credit Card | P25: 661.7376 | S25: Median | T25: 2 | U25: Median | V25: 522.43 | W25: Median | X25: 0.14 | Y25: Median | Z25: 868.7182
A26: SALE24 | B26: 45908 | C26: CUST1186 | D26: =VLOOKUP($C26,'Customer_Dim Cleaned'!$A$1:$H$501,4,FALSE) -> Male | E26: =VLOOKUP($C26,'Customer_Dim Cleaned'!$A$1:$H$501,5,FALSE) -> East Justin | F26: =VLOOKUP($C26,'Customer_Dim Cleaned'!$A$1:$H$501,6,FALSE) -> Missouri | G26: PROD1 | H26: =VLOOKUP($G26,'Product_Dim Cleaned'!$A$1:$G$101,2,FALSE) -> Men's Graphic T-Shirt | I26: =VLOOKUP($G26,'Product_Dim Cleaned'!$A$1:$G$101,3,FALSE) -> Clothing | J26: =VLOOKUP($G26,'Product_Dim Cleaned'!$A$1:$G$101,4,FALSE) -> Tops | K26: STORE6 | L26: 3 | M26: 77.6 | N26: 0.07 | O26: Credit Card | P26: 216.504 | S26: Mode | T26: 2 | U26: Mode | V26: 871.34 | W26: Mode | X26: 0.1 | Y26: Mode | Z26: #N/A
A27: SALE25 | B27: 45552 | C27: CUST1381 | D27: =VLOOKUP($C27,'Customer_Dim Cleaned'!$A$1:$H$501,4,FALSE) -> Male | E27: =VLOOKUP($C27,'Customer_Dim Cleaned'!$A$1:$H$501,5,FALSE) -> Andrewsland | F27: =VLOOKUP($C27,'Customer_Dim Cleaned'!$A$1:$H$501,6,FALSE) -> Alabama | G27: PROD1 | H27: =VLOOKUP($G27,'Product_Dim Cleaned'!$A$1:$G$101,2,FALSE) -> Men's Graphic T-Shirt | I27: =VLOOKUP($G27,'Product_Dim Cleaned'!$A$1:$G$101,3,FALSE) -> Clothing | J27: =VLOOKUP($G27,'Product_Dim Cleaned'!$A$1:$G$101,4,FALSE) -> Tops | K27: STORE3 | L27: 4 | M27: 852.71 | N27: 0.14 | O27: PayPal | P27: 2933.3224 | S27: Standard Deviation | T27: 1.1114376 | U27: Standard Deviation | V27: 282.34825 | W27: Standard Deviation | X27: 0.087647473 | Y27: Standard Deviation | Z27: 819.61896
A28: SALE26 | B28: 45294 | C28: CUST1213 | D28: =VLOOKUP($C28,'Customer_Dim Cleaned'!$A$1:$H$501,4,FALSE) -> Female | E28: =VLOOKUP($C28,'Customer_Dim Cleaned'!$A$1:$H$501,5,FALSE) -> West Markport | F28: =VLOOKUP($C28,'Customer_Dim Cleaned'!$A$1:$H$501,6,FALSE) -> North Dakota | G28: PROD1 | H28: =VLOOKUP($G28,'Product_Dim Cleaned'!$A$1:$G$101,2,FALSE) -> Men's Graphic T-Shirt | I28: =VLOOKUP($G28,'Product_Dim Cleaned'!$A$1:$G$101,3,FALSE) -> Clothing | J28: =VLOOKUP($G28,'Product_Dim Cleaned'!$A$1:$G$101,4,FALSE) -> Tops | K28: STORE8 | L28: 4 | M28: 156.16 | N28: 0.04 | O28: Credit Card | P28: 599.6544 | S28: Sample Variance | T28: 1.2352936 | U28: Sample Variance | V28: 79720.534 | W28: Sample Variance | X28: 0.0076820794 | Y28: Sample Variance | Z28: 671775.25
A29: SALE27 | B29: 45710 | C29: CUST1200 | D29: =VLOOKUP($C29,'Customer_Dim Cleaned'!$A$1:$H$501,4,FALSE) -> Male | E29: =VLOOKUP($C29,'Customer_Dim Cleaned'!$A$1:$H$501,5,FALSE) -> South Jerry | F29: =VLOOKUP($C29,'Customer_Dim Cleaned'!$A$1:$H$501,6,FALSE) -> Maine | G29: PROD1 | H29: =VLOOKUP($G29,'Product_Dim Cleaned'!$A$1:$G$101,2,FALSE) -> Men's Graphic T-Shirt | I29: =VLOOKUP($G29,'Product_Dim Cleaned'!$A$1:$G$101,3,FALSE) -> Clothing | J29: =VLOOKUP($G29,'Product_Dim Cleaned'!$A$1:$G$101,4,FALSE) -> Tops | K29: STORE8 | L29: 3 | M29: 815.49 | N29: 0.17 | O29: Credit Card | P29: 2030.5701 | S29: Kurtosis | T29: -1.3441226 | U29: Kurtosis | V29: -1.1931883 | W29: Kurtosis | X29: -1.208024 | Y29: Kurtosis | Z29: 0.045826153
A30: SALE28 | B30: 45923 | C30: CUST1148 | D30: =VLOOKUP($C30,'Customer_Dim Cleaned'!$A$1:$H$501,4,FALSE) -> Female | E30: =VLOOKUP($C30,'Customer_Dim Cleaned'!$A$1:$H$501,5,FALSE) -> New Brian | F30: =VLOOKUP($C30,'Customer_Dim Cleaned'!$A$1:$H$501,6,FALSE) -> Wisconsin | G30: PROD1 | H30: =VLOOKUP($G30,'Product_Dim Cleaned'!$A$1:$G$101,2,FALSE) -> Men's Graphic T-Shirt | I30: =VLOOKUP($G30,'Product_Dim Cleaned'!$A$1:$G$101,3,FALSE) -> Clothing | J30: =VLOOKUP($G30,'Product_Dim Cleaned'!$A$1:$G$101,4,FALSE) -> Tops | K30: STORE2 | L30: 2 | M30: 74.21 | N30: 0.11 | O30: PayPal | P30: 132.0938 | S30: Skewness | T30: 0.022378357 | U30: Skewness | V30: -0.034813907 | W30: Skewness | X30: 0.062951035 | Y30: Skewness | Z30: 0.87904704
A31: SALE29 | B31: 45302 | C31: CUST1348 | D31: =VLOOKUP($C31,'Customer_Dim Cleaned'!$A$1:$H$501,4,FALSE) -> Male | E31: =VLOOKUP($C31,'Customer_Dim Cleaned'!$A$1:$H$501,5,FALSE) -> Shannonview | F31: =VLOOKUP($C31,'Customer_Dim Cleaned'!$A$1:$H$501,6,FALSE) -> Pennsylvania | G31: PROD1 | H31: =VLOOKUP($G31,'Product_Dim Cleaned'!$A$1:$G$101,2,FALSE) -> Men's Graphic T-Shirt | I31: =VLOOKUP($G31,'Product_Dim Cleaned'!$A$1:$G$101,3,FALSE) -> Clothing | J31: =VLOOKUP($G31,'Product_Dim Cleaned'!$A$1:$G$101,4,FALSE) -> Tops | K31: STORE3 | L31: 4 | M31: 451.67 | N31: 0.15 | O31: Credit Card | P31: 1535.678 | S31: Range | T31: 3 | U31: Range | V31: 979.8 | W31: Range | X31: 0.3 | Y31: Range | Z31: 3889.7838
A32: SALE30 | B32: 45217 | C32: CUST1028 | D32: =VLOOKUP($C32,'Customer_Dim Cleaned'!$A$1:$H$501,4,FALSE) -> Female | E32: =VLOOKUP($C32,'Customer_Dim Cleaned'!$A$1:$H$501,5,FALSE) -> New David | F32: =VLOOKUP($C32,'Customer_Dim Cleaned'!$A$1:$H$501,6,FALSE) -> New Jersey | G32: PROD1 | H32: =VLOOKUP($G32,'Product_Dim Cleaned'!$A$1:$G$101,2,FALSE) -> Men's Graphic T-Shirt | I32: =VLOOKUP($G32,'Product_Dim Cleaned'!$A$1:$G$101,3,FALSE) -> Clothing | J32: =VLOOKUP($G32,'Product_Dim Cleaned'!$A$1:$G$101,4,FALSE) -> Tops | K32: STORE19 | L32: 1 | M32: 429.38 | N32: 0.13 | O32: PayPal | P32: 373.5606 | S32: Minimum | T32: 1 | U32: Minimum | V32: 20.09 | W32: Minimum | X32: 0 | Y32: Minimum | Z32: 18.459
A33: SALE31 | B33: 45593 | C33: CUST1412 | D33: =VLOOKUP($C33,'Customer_Dim Cleaned'!$A$1:$H$501,4,FALSE) -> Female | E33: =VLOOKUP($C33,'Customer_Dim Cleaned'!$A$1:$H$501,5,FALSE) -> East Andrea | F33: =VLOOKUP($C33,'Customer_Dim Cleaned'!$A$1:$H$501,6,FALSE) -> Michigan | G33: PROD10 | H33: =VLOOKUP($G33,'Product_Dim Cleaned'!$A$1:$G$101,2,FALSE) -> Ceramic Kitchen Bowl Set | I33: =VLOOKUP($G33,'Product_Dim Cleaned'!$A$1:$G$101,3,FALSE) -> Home | J33: =VLOOKUP($G33,'Product_Dim Cleaned'!$A$1:$G$101,4,FALSE) -> Kitchen | K33: STORE12 | L33: 2 | M33: 148.96 | N33: 0.03 | O33: COD | P33: 288.9824 | S33: Maximum | T33: 4 | U33: Maximum | V33: 999.89 | W33: Maximum | X33: 0.3 | Y33: Maximum | Z33: 3908.2428
A34: SALE32 | B34: 45597 | C34: CUST1398 | D34: =VLOOKUP($C34,'Customer_Dim Cleaned'!$A$1:$H$501,4,FALSE) -> Male | E34: =VLOOKUP($C34,'Customer_Dim Cleaned'!$A$1:$H$501,5,FALSE) -> Cheyenneborough | F34: =VLOOKUP($C34,'Customer_Dim Cleaned'!$A$1:$H$501,6,FALSE) -> New Hampshire | G34: PROD10 | H34: =VLOOKUP($G34,'Product_Dim Cleaned'!$A$1:$G$101,2,FALSE) -> Ceramic Kitchen Bowl Set | I34: =VLOOKUP($G34,'Product_Dim Cleaned'!$A$1:$G$101,3,FALSE) -> Home | J34: =VLOOKUP($G34,'Product_Dim Cleaned'!$A$1:$G$101,4,FALSE) -> Kitchen | K34: STORE8 | L34: 4 | M34: 313.83 | N34: 0.08 | O34: Credit Card | P34: 1154.8944 | S34: Sum | T34: 4964 | U34: Sum | V34: 1027165.6 | W34: Sum | X34: 295.92 | Y34: Sum | Z34: 2174394.7
A35: SALE33 | B35: 45620 | C35: CUST1453 | D35: =VLOOKUP($C35,'Customer_Dim Cleaned'!$A$1:$H$501,4,FALSE) -> Female | E35: =VLOOKUP($C35,'Customer_Dim Cleaned'!$A$1:$H$501,5,FALSE) -> Lake Carolyn | F35: =VLOOKUP($C35,'Customer_Dim Cleaned'!$A$1:$H$501,6,FALSE) -> Hawaii | G35: PROD10 | H35: =VLOOKUP($G35,'Product_Dim Cleaned'!$A$1:$G$101,2,FALSE) -> Ceramic Kitchen Bowl Set | I35: =VLOOKUP($G35,'Product_Dim Cleaned'!$A$1:$G$101,3,FALSE) -> Home | J35: =VLOOKUP($G35,'Product_Dim Cleaned'!$A$1:$G$101,4,FALSE) -> Kitchen | K35: STORE6 | L35: 2 | M35: 717.31 | N35: 0.15 | O35: Credit Card | P35: 1219.427 | S35: Count | T35: 2000 | U35: Count | V35: 2000 | W35: Count | X35: 2000 | Y35: Count | Z35: 2000
A36: SALE34 | B36: 45215 | C36: CUST1344 | D36: =VLOOKUP($C36,'Customer_Dim Cleaned'!$A$1:$H$501,4,FALSE) -> Male | E36: =VLOOKUP($C36,'Customer_Dim Cleaned'!$A$1:$H$501,5,FALSE) -> West Victoriaborough | F36: =VLOOKUP($C36,'Customer_Dim Cleaned'!$A$1:$H$501,6,FALSE) -> New Mexico | G36: PROD10 | H36: =VLOOKUP($G36,'Product_Dim Cleaned'!$A$1:$G$101,2,FALSE) -> Ceramic Kitchen Bowl Set | I36: =VLOOKUP($G36,'Product_Dim Cleaned'!$A$1:$G$101,3,FALSE) -> Home | J36: =VLOOKUP($G36,'Product_Dim Cleaned'!$A$1:$G$101,4,FALSE) -> Kitchen | K36: STORE1 | L36: 3 | M36: 873.22 | N36: 0.18 | O36: Credit Card | P36: 2148.1212
A37: SALE35 | B37: 45878 | C37: CUST1218 | D37: =VLOOKUP($C37,'Customer_Dim Cleaned'!$A$1:$H$501,4,FALSE) -> Male | E37: =VLOOKUP($C37,'Customer_Dim Cleaned'!$A$1:$H$501,5,FALSE) -> Edwardland | F37: =VLOOKUP($C37,'Customer_Dim Cleaned'!$A$1:$H$501,6,FALSE) -> California | G37: PROD10 | H37: =VLOOKUP($G37,'Product_Dim Cleaned'!$A$1:$G$101,2,FALSE) -> Ceramic Kitchen Bowl Set | I37: =VLOOKUP($G37,'Product_Dim Cleaned'!$A$1:$G$101,3,FALSE) -> Home | J37: =VLOOKUP($G37,'Product_Dim Cleaned'!$A$1:$G$101,4,FALSE) -> Kitchen | K37: STORE3 | L37: 4 | M37: 109.36 | N37: 0.19 | O37: COD | P37: 354.3264
A38: SALE36 | B38: 45635 | C38: CUST1086 | D38: =VLOOKUP($C38,'Customer_Dim Cleaned'!$A$1:$H$501,4,FALSE) -> Female | E38: =VLOOKUP($C38,'Customer_Dim Cleaned'!$A$1:$H$501,5,FALSE) -> Austinfurt | F38: =VLOOKUP($C38,'Customer_Dim Cleaned'!$A$1:$H$501,6,FALSE) -> Mississippi | G38: PROD10 | H38: =VLOOKUP($G38,'Product_Dim Cleaned'!$A$1:$G$101,2,FALSE) -> Ceramic Kitchen Bowl Set | I38: =VLOOKUP($G38,'Product_Dim Cleaned'!$A$1:$G$101,3,FALSE) -> Home | J38: =VLOOKUP($G38,'Product_Dim Cleaned'!$A$1:$G$101,4,FALSE) -> Kitchen | K38: STORE7 | L38: 3 | M38: 559.52 | N38: 0.16 | O38: PayPal | P38: 1409.9904
A39: SALE37 | B39: 45329 | C39: CUST1492 | D39: =VLOOKUP($C39,'Customer_Dim Cleaned'!$A$1:$H$501,4,FALSE) -> Female | E39: =VLOOKUP($C39,'Customer_Dim Cleaned'!$A$1:$H$501,5,FALSE) -> Port Carol | F39: =VLOOKUP($C39,'Customer_Dim Cleaned'!$A$1:$H$501,6,FALSE) -> Florida | G39: PROD10 | H39: =VLOOKUP($G39,'Product_Dim Cleaned'!$A$1:$G$101,2,FALSE) -> Ceramic Kitchen Bowl Set | I39: =VLOOKUP($G39,'Product_Dim Cleaned'!$A$1:$G$101,3,FALSE) -> Home | J39: =VLOOKUP($G39,'Product_Dim Cleaned'!$A$1:$G$101,4,FALSE) -> Kitchen | K39: STORE17 | L39: 3 | M39: 121.76 | N39: 0.27 | O39: PayPal | P39: 266.6544
A40: SALE38 | B40: 45378 | C40: CUST1189 | D40: =VLOOKUP($C40,'Customer_Dim Cleaned'!$A$1:$H$501,4,FALSE) -> Male | E40: =VLOOKUP($C40,'Customer_Dim Cleaned'!$A$1:$H$501,5,FALSE) -> Lake Howardberg | F40: =VLOOKUP($C40,'Customer_Dim Cleaned'!$A$1:$H$501,6,FALSE) -> Kentucky | G40: PROD10 | H40: =VLOOKUP($G40,'Product_Dim Cleaned'!$A$1:$G$101,2,FALSE) -> Ceramic Kitchen Bowl Set | I40: =VLOOKUP($G40,'Product_Dim Cleaned'!$A$1:$G$101,3,FALSE) -> Home | J40: =VLOOKUP($G40,'Product_Dim Cleaned'!$A$1:$G$101,4,FALSE) -> Kitchen | K40: STORE13 | L40: 4 | M40: 735.32 | N40: 0.06 | O40: COD | P40: 2764.8032
A41: SALE39 | B41: 45264 | C41: CUST1431 | D41: =VLOOKUP($C41,'Customer_Dim Cleaned'!$A$1:$H$501,4,FALSE) -> Male | E41: =VLOOKUP($C41,'Customer_Dim Cleaned'!$A$1:$H$501,5,FALSE) -> South Andrewport | F41: =VLOOKUP($C41,'Customer_Dim Cleaned'!$A$1:$H$501,6,FALSE) -> California | G41: PROD10 | H41: =VLOOKUP($G41,'Product_Dim Cleaned'!$A$1:$G$101,2,FALSE) -> Ceramic Kitchen Bowl Set | I41: =VLOOKUP($G41,'Product_Dim Cleaned'!$A$1:$G$101,3,FALSE) -> Home | J41: =VLOOKUP($G41,'Product_Dim Cleaned'!$A$1:$G$101,4,FALSE) -> Kitchen | K41: STORE3 | L41: 2 | M41: 600.73 | N41: 0.08 | O41: Credit Card | P41: 1105.3432
A42: SALE40 | B42: 45486 | C42: CUST1072 | D42: =VLOOKUP($C42,'Customer_Dim Cleaned'!$A$1:$H$501,4,FALSE) -> Female | E42: =VLOOKUP($C42,'Customer_Dim Cleaned'!$A$1:$H$501,5,FALSE) -> Olsonhaven | F42: =VLOOKUP($C42,'Customer_Dim Cleaned'!$A$1:$H$501,6,FALSE) -> Iowa | G42: PROD10 | H42: =VLOOKUP($G42,'Product_Dim Cleaned'!$A$1:$G$101,2,FALSE) -> Ceramic Kitchen Bowl Set | I42: =VLOOKUP($G42,'Product_Dim Cleaned'!$A$1:$G$101,3,FALSE) -> Home | J42: =VLOOKUP($G42,'Product_Dim Cleaned'!$A$1:$G$101,4,FALSE) -> Kitchen | K42: STORE19 | L42: 2 | M42: 873.86 | N42: 0.07 | O42: COD | P42: 1625.3796
A43: SALE41 | B43: 45241 | C43: CUST1302 | D43: =VLOOKUP($C43,'Customer_Dim Cleaned'!$A$1:$H$501,4,FALSE) -> Male | E43: =VLOOKUP($C43,'Customer_Dim Cleaned'!$A$1:$H$501,5,FALSE) -> Lake Charlotte | F43: =VLOOKUP($C43,'Customer_Dim Cleaned'!$A$1:$H$501,6,FALSE) -> Arizona | G43: PROD10 | H43: =VLOOKUP($G43,'Product_Dim Cleaned'!$A$1:$G$101,2,FALSE) -> Ceramic Kitchen Bowl Set | I43: =VLOOKUP($G43,'Product_Dim Cleaned'!$A$1:$G$101,3,FALSE) -> Home | J43: =VLOOKUP($G43,'Product_Dim Cleaned'!$A$1:$G$101,4,FALSE) -> Kitchen | K43: STORE8 | L43: 3 | M43: 342.47 | N43: 0.08 | O43: PayPal | P43: 945.2172
A44: SALE42 | B44: 45649 | C44: CUST1335 | D44: =VLOOKUP($C44,'Customer_Dim Cleaned'!$A$1:$H$501,4,FALSE) -> Male | E44: =VLOOKUP($C44,'Customer_Dim Cleaned'!$A$1:$H$501,5,FALSE) -> West Brendamouth | F44: =VLOOKUP($C44,'Customer_Dim Cleaned'!$A$1:$H$501,6,FALSE) -> North Carolina | G44: PROD10 | H44: =VLOOKUP($G44,'Product_Dim Cleaned'!$A$1:$G$101,2,FALSE) -> Ceramic Kitchen Bowl Set | I44: =VLOOKUP($G44,'Product_Dim Cleaned'!$A$1:$G$101,3,FALSE) -> Home | J44: =VLOOKUP($G44,'Product_Dim Cleaned'!$A$1:$G$101,4,FALSE) -> Kitchen | K44: STORE9 | L44: 2 | M44: 915.15 | N44: 0.16 | O44: PayPal | P44: 1537.452
A45: SALE43 | B45: 45677 | C45: CUST1084 | D45: =VLOOKUP($C45,'Customer_Dim Cleaned'!$A$1:$H$501,4,FALSE) -> Female | E45: =VLOOKUP($C45,'Customer_Dim Cleaned'!$A$1:$H$501,5,FALSE) -> Garyberg | F45: =VLOOKUP($C45,'Customer_Dim Cleaned'!$A$1:$H$501,6,FALSE) -> Indiana | G45: PROD10 | H45: =VLOOKUP($G45,'Product_Dim Cleaned'!$A$1:$G$101,2,FALSE) -> Ceramic Kitchen Bowl Set | I45: =VLOOKUP($G45,'Product_Dim Cleaned'!$A$1:$G$101,3,FALSE) -> Home | J45: =VLOOKUP($G45,'Product_Dim Cleaned'!$A$1:$G$101,4,FALSE) -> Kitchen | K45: STORE17 | L45: 3 | M45: 863.11 | N45: 0.28 | O45: PayPal | P45: 1864.3176
A46: SALE44 | B46: 45538 | C46: CUST1203 | D46: =VLOOKUP($C46,'Customer_Dim Cleaned'!$A$1:$H$501,4,FALSE) -> Male | E46: =VLOOKUP($C46,'Customer_Dim Cleaned'!$A$1:$H$501,5,FALSE) -> Johnsonland | F46: =VLOOKUP($C46,'Customer_Dim Cleaned'!$A$1:$H$501,6,FALSE) -> Iowa | G46: PROD10 | H46: =VLOOKUP($G46,'Product_Dim Cleaned'!$A$1:$G$101,2,FALSE) -> Ceramic Kitchen Bowl Set | I46: =VLOOKUP($G46,'Product_Dim Cleaned'!$A$1:$G$101,3,FALSE) -> Home | J46: =VLOOKUP($G46,'Product_Dim Cleaned'!$A$1:$G$101,4,FALSE) -> Kitchen | K46: STORE12 | L46: 2 | M46: 209.32 | N46: 0.23 | O46: COD | P46: 322.3528
A47: SALE45 | B47: 45606 | C47: CUST1470 | D47: =VLOOKUP($C47,'Customer_Dim Cleaned'!$A$1:$H$501,4,FALSE) -> Female | E47: =VLOOKUP($C47,'Customer_Dim Cleaned'!$A$1:$H$501,5,FALSE) -> Kanebury | F47: =VLOOKUP($C47,'Customer_Dim Cleaned'!$A$1:$H$501,6,FALSE) -> New Hampshire | G47: PROD10 | H47: =VLOOKUP($G47,'Product_Dim Cleaned'!$A$1:$G$101,2,FALSE) -> Ceramic Kitchen Bowl Set | I47: =VLOOKUP($G47,'Product_Dim Cleaned'!$A$1:$G$101,3,FALSE) -> Home | J47: =VLOOKUP($G47,'Product_Dim Cleaned'!$A$1:$G$101,4,FALSE) -> Kitchen | K47: STORE8 | L47: 4 | M47: 288.6 | N47: 0.09 | O47: PayPal | P47: 1050.504
... A2001: SALE1999 | B2001: 45267 | C2001: CUST1023 | D2001: =VLOOKUP($C2001,'Customer_Dim Cleaned'!$A$1:$H$501,4,FALSE) -> Female | E2001: =VLOOKUP($C2001,'Customer_Dim Cleaned'!$A$1:$H$501,5,FALSE) -> Molinabury | F2001: =VLOOKUP($C2001,'Customer_Dim Cleaned'!$A$1:$H$501,6,FALSE) -> Oregon | G2001: PROD99 | H2001: =VLOOKUP($G2001,'Product_Dim Cleaned'!$A$1:$G$101,2,FALSE) -> Stainless Steel Cookware Set | I2001: =VLOOKUP($G2001,'Product_Dim Cleaned'!$A$1:$G$101,3,FALSE) -> Home | J2001: =VLOOKUP($G2001,'Product_Dim Cleaned'!$A$1:$G$101,4,FALSE) -> Kitchen | K2001: STORE19 | L2001: 3 | M2001: 68.45 | N2001: 0.17 | O2001: PayPal | P2001: 170.4405

Sheet Pivot Analysis
B1: Pivot Tables and Charts created for Visual analysis
A3: Row Labels | B3: Sum of Total_Amount | D3: Count of Sales_ID | F3: Sum of Total_Amount | H3: Sum of Quantity | J3: Average of Discount | L3: Row Labels | M3: Sum of Total_Amount
A4: Female | B4: 1231444.2 | D4: 2000 | F4: 2174394.7 | H4: 4964 | J4: 0.14796 | L4: 2023 | M4: 223812.72
A5: Male | B5: 942950.47 | L5: 2024 | M5: 1093911.8
A6: Grand Total | B6: 2174394.7 | L6: 2025 | M6: 856670.18
L7: Grand Total | M7: 2174394.7
A9: Row Labels | B9: Sum of Total_Amount | C9: Count of Sales_ID
A10: COD | B10: 702459.42 | C10: 660
A11: Credit Card | B11: 715180.71 | C11: 645
A12: PayPal | B12: 756754.57 | C12: 695
A13: Grand Total | B13: 2174394.7 | C13: 2000
A16: Row Labels | B16: Sum of Total_Amount | C16: Sum of Unit_Price | D16: Sum of Quantity
A17: Beauty | B17: 320700.33 | C17: 150598.96 | D17: 765
A18: Clothing | B18: 386965.21 | C18: 173640.73 | D18: 854
A19: Electronics | B19: 487632.09 | C19: 231525.57 | D19: 1134
A20: Home | B20: 455776.5 | C20: 215195.84 | D20: 993
A21: Sports | B21: 523320.57 | C21: 256204.48 | D21: 1218
A22: Grand Total | B22: 2174394.7 | C22: 1027165.6 | D22: 4964
A25: Category | B25: All
A27: Row Labels | B27: Count of Sales_ID | C27: Sum of Total_Amount
A28: Alabama | B28: 46 | C28: 49377.684
A29: Alaska | B29: 41 | C29: 49032.414
A30: Arizona | B30: 41 | C30: 46317.776
A31: Arkansas | B31: 26 | C31: 24828.745
A32: California | B32: 53 | C32: 47072.305
A33: Colorado | B33: 8 | C33: 9312.2465
A34: Connecticut | B34: 55 | C34: 56723.038
A35: Delaware | B35: 32 | C35: 29967.98
A36: Florida | B36: 52 | C36: 60406.676
A37: Georgia | B37: 50 | C37: 47224.799
A38: Hawaii | B38: 32 | C38: 34436.901
A39: Idaho | B39: 11 | C39: 12801.172
... A52: Missouri | B52: 34 | C52: 36852.567
A53: Montana | B53: 37 | C53: 44400.348 | E53: Row Labels | F53: Count of Sales_ID | G53: Sum of Quantity | H53: Sum of Total_Amount
A54: Nebraska | B54: 22 | C54: 24305.266 | E54: STORE0 | F54: 93 | G54: 204 | H54: 85138.555
A55: Nevada | B55: 55 | C55: 53326.112 | E55: STORE1 | F55: 94 | G55: 232 | H55: 101060.61
A56: New Hampshire | B56: 57 | C56: 69579.925 | E56: STORE10 | F56: 97 | G56: 255 | H56: 109791.72
A57: New Jersey | B57: 55 | C57: 65274.956 | E57: STORE11 | F57: 88 | G57: 206 | H57: 93048.141
A58: New Mexico | B58: 42 | C58: 46228.124 | E58: STORE12 | F58: 100 | G58: 259 | H58: 116829.22
A59: New York | B59: 57 | C59: 57426.729 | E59: STORE13 | F59: 95 | G59: 243 | H59: 114401.47
A60: North Carolina | B60: 49 | C60: 48947.018 | E60: STORE14 | F60: 95 | G60: 224 | H60: 106248.28
A61: North Dakota | B61: 42 | C61: 47101.944 | E61: STORE15 | F61: 95 | G61: 243 | H61: 99679.086
A62: Ohio | B62: 54 | C62: 48009.171 | E62: STORE16 | F62: 106 | G62: 249 | H62: 111704.94
A63: Oklahoma | B63: 54 | C63: 59386.541 | E63: STORE17 | F63: 110 | G63: 277 | H63: 122176.55
A64: Oregon | B64: 52 | C64: 52860.52 | E64: STORE18 | F64: 105 | G64: 247 | H64: 104313.05
A65: Pennsylvania | B65: 46 | C65: 53417.86 | E65: STORE19 | F65: 94 | G65: 240 | H65: 94225.723
... A74: Washington | B74: 43 | C74: 43615.416 | E74: Grand Total | F74: 2000 | G74: 4964 | H74: 2174394.7
A75: West Virginia | B75: 51 | C75: 56405.416
A76: Wisconsin | B76: 39 | C76: 44309.764
A77: Wyoming | B77: 23 | C77: 17815.739
A78: Grand Total | B78: 2000 | C78: 2174394.7

Sheet Final Dashboard
A1: E-Commerce Sales Performance Dashboard

Sheet Summary & Key Insights
A1: Findings Summary | B1: values | E1: Key Insights
A2: Total Revenue generated : | B2: 2174394.7 | E2: 1. promote more discount for online payment to get more revenue
A3: Total Number of Sales | B3: 2000 | E3: 2. Focus on Beauty and Clothing Category to increase sales
A4: Total Number of Products Sold | B4: 4964 | E4: 3. Store Performance are evenly distributed but still need to focusing on direct purchase
A5: Average Discount | B5: 0.15 | E5: 4. 2025 sales low compare than 2024 ,so need to check where the performance is lagging and improve that.
A6: Female Customers generate more revenue than Males | B6: 1231444.2 | E6: 5. overall need to focus on category, payment mode, location and suggest more discount option to bring back the performance like 2024.
A7: Customers perfers Online Payment (Paypal) | B7: 0.35
A8: Sports Category got highiest sales amount | B8: 523320.57
A9: Year 2024 shows more revenue compare than others | B9: 1093911.8
A10: More number of sales occurred and more products sold in store 8 | B10: 127&344 | E10: processing steps.docx
